Workbook
Name RawData: #REF!
Name RawData: #REF!
Name USP순서: [3]USP_RAW시트!$J$4:$BA$709

Sheet Summary
Q1: blog 점수 재계산
B2: LG.com Monitoring Report by Country
Q4: Crawling Date : 25.11.04
B5: REGION | C5: COUNTRY | D5: GP1 Status | E5: SKU | F5: SKU AUG | G5: GAP | H5: Total Score | I5: Total Score AUG | J5: GAP | K5: Monitoring Criteria
K6: SEO HTML Tag | P6: Category | Q6: Blog
K7: 1. Title | L7: 2. Description | M7: 3. H1 | N7: 4. Canonical Link | O7: 5. Alt text_ Feature Cards | P7: 6.Product Category | Q7: 7. Blog
K8: Score (out of 20) | M8: Score (out of 15) | Q8: Additional 10 points
C9: * | E9: 1834 | F9: 1830 | G9: 4 | H9: 94.914666 | I9: 89.386611 | J9: 5.5280551 | K9: =AVERAGEIF(K10:K59, "<>#N/A") -> 14.911224 | L9: =AVERAGEIF(L10:L59, "<>#N/A") -> 17.450312 | M9: =AVERAGEIF(M10:M59, "<>#N/A") -> 13.114907 | N9: =AVERAGEIF(N10:N59, "<>#N/A") -> 14.80959 | O9: =AVERAGEIF(O10:O59, "<>#N/A") -> 14.615264 | P9: =AVERAGEIF(P10:P59, "<>#N/A") -> 14.558824 | Q9: =AVERAGEIF(Q10:Q59, "<>#N/A") -> 5.4545455 | S9: BLOG
B10: NA | C10: Canada | D10: GP1 | E10: 48 | F10: 48 | G10: 0 | H10: 77.1875 | I10: 77.5 | J10: -0.3125 | K10: =IFERROR(AVERAGEIFS(PLP_BUSINESS!X:X, PLP_BUSINESS!$B:$B, Summary!$C10, PLP_BUSINESS!$H:$H, "Y"),0) -> 13.333333 | L10: =IFERROR(AVERAGEIFS(PLP_BUSINESS!Y:Y, PLP_BUSINESS!$B:$B, Summary!$C10, PLP_BUSINESS!$H:$H, "Y"),0) -> 17.916667 | M10: =IFERROR(AVERAGEIFS(PLP_BUSINESS!Z:Z, PLP_BUSINESS!$B:$B, Summary!$C10, PLP_BUSINESS!$H:$H, "Y"),0) -> 1.25 | N10: =IFERROR(AVERAGEIFS(PLP_BUSINESS!AA:AA, PLP_BUSINESS!$B:$B, Summary!$C10, PLP_BUSINESS!$H:$H, "Y"),0) -> 14.6875 | O10: =IFERROR(AVERAGEIFS(PLP_BUSINESS!AB:AB, PLP_BUSINESS!$B:$B, Summary!$C10, PLP_BUSINESS!$H:$H, "Y"),0) -> 15 | P10: =HLOOKUP($C10,'Product Category'!$E$7:$AS$68,62,0) -> 15 | Q10: =IF(ISNUMBER(MATCH(C10,S:S,0)), NA(), IF(ISNA(P10), NA(), _xlfn.XLOOKUP(C10,Blog!C:C,Blog!G:G,0))) -> 0 | R10: =IF(ISNA(P10), "예외", "") | S10: Algeria
B11: LATAM | C11: Colombia | D11: GP1 | E11: 33 | F11: 33 | G11: 0 | H11: 100 | I11: 100 | J11: 0 | K11: =IFERROR(AVERAGEIFS(PLP_BUSINESS!X:X, PLP_BUSINESS!$B:$B, Summary!$C11, PLP_BUSINESS!$H:$H, "Y"),0) -> 20 | L11: =IFERROR(AVERAGEIFS(PLP_BUSINESS!Y:Y, PLP_BUSINESS!$B:$B, Summary!$C11, PLP_BUSINESS!$H:$H, "Y"),0) -> 18.787879 | M11: =IFERROR(AVERAGEIFS(PLP_BUSINESS!Z:Z, PLP_BUSINESS!$B:$B, Summary!$C11, PLP_BUSINESS!$H:$H, "Y"),0) -> 15 | N11: =IFERROR(AVERAGEIFS(PLP_BUSINESS!AA:AA, PLP_BUSINESS!$B:$B, Summary!$C11, PLP_BUSINESS!$H:$H, "Y"),0) -> 15 | O11: =IFERROR(AVERAGEIFS(PLP_BUSINESS!AB:AB, PLP_BUSINESS!$B:$B, Summary!$C11, PLP_BUSINESS!$H:$H, "Y"),0) -> 15 | P11: =HLOOKUP($C11,'Product Category'!$E$7:$AS$68,62,0) -> 15 | Q11: =IF(ISNUMBER(MATCH(C11,S:S,0)), NA(), IF(ISNA(P11), NA(), _xlfn.XLOOKUP(C11,Blog!C:C,Blog!G:G,0))) -> 10 | R11: =IF(ISNA(P11), "예외", "")
B12: LATAM | C12: Ecuador | D12: 5.0 | E12: 36 | F12: 36 | G12: 0 | H12: 99.62963 | I12: 99.62963 | J12: 0 | K12: =IFERROR(AVERAGEIFS(PLP_BUSINESS!X:X, PLP_BUSINESS!$B:$B, Summary!$C12, PLP_BUSINESS!$H:$H, "Y"),0) -> 12.222222 | L12: =IFERROR(AVERAGEIFS(PLP_BUSINESS!Y:Y, PLP_BUSINESS!$B:$B, Summary!$C12, PLP_BUSINESS!$H:$H, "Y"),0) -> 20 | M12: =IFERROR(AVERAGEIFS(PLP_BUSINESS!Z:Z, PLP_BUSINESS!$B:$B, Summary!$C12, PLP_BUSINESS!$H:$H, "Y"),0) -> 12.916667 | N12: =IFERROR(AVERAGEIFS(PLP_BUSINESS!AA:AA, PLP_BUSINESS!$B:$B, Summary!$C12, PLP_BUSINESS!$H:$H, "Y"),0) -> 14.583333 | O12: =IFERROR(AVERAGEIFS(PLP_BUSINESS!AB:AB, PLP_BUSINESS!$B:$B, Summary!$C12, PLP_BUSINESS!$H:$H, "Y"),0) -> 15 | P12: =HLOOKUP($C12,'Product Category'!$E$7:$AS$68,62,0) -> #N/A | Q12: =IF(ISNUMBER(MATCH(C12,S:S,0)), NA(), IF(ISNA(P12), NA(), _xlfn.XLOOKUP(C12,Blog!C:C,Blog!G:G,0))) -> #N/A | R12: =IF(ISNA(P12), "예외", "") -> 예외
B13: LATAM | C13: Mexico | D13: GP1 | E13: 42 | F13: 42 | G13: 0 | H13: 100 | I13: 100 | J13: 0 | K13: =IFERROR(AVERAGEIFS(PLP_BUSINESS!X:X, PLP_BUSINESS!$B:$B, Summary!$C13, PLP_BUSINESS!$H:$H, "Y"),0) -> 20 | L13: =IFERROR(AVERAGEIFS(PLP_BUSINESS!Y:Y, PLP_BUSINESS!$B:$B, Summary!$C13, PLP_BUSINESS!$H:$H, "Y"),0) -> 20 | M13: =IFERROR(AVERAGEIFS(PLP_BUSINESS!Z:Z, PLP_BUSINESS!$B:$B, Summary!$C13, PLP_BUSINESS!$H:$H, "Y"),0) -> 15 | N13: =IFERROR(AVERAGEIFS(PLP_BUSINESS!AA:AA, PLP_BUSINESS!$B:$B, Summary!$C13, PLP_BUSINESS!$H:$H, "Y"),0) -> 14.642857 | O13: =IFERROR(AVERAGEIFS(PLP_BUSINESS!AB:AB, PLP_BUSINESS!$B:$B, Summary!$C13, PLP_BUSINESS!$H:$H, "Y"),0) -> 15 | P13: =HLOOKUP($C13,'Product Category'!$E$7:$AS$68,62,0) -> 15 | Q13: =IF(ISNUMBER(MATCH(C13,S:S,0)), NA(), IF(ISNA(P13), NA(), _xlfn.XLOOKUP(C13,Blog!C:C,Blog!G:G,0))) -> 10 | R13: =IF(ISNA(P13), "예외", "")
B14: LATAM | C14: Chile | D14: GP1 | E14: 31 | F14: 31 | G14: 0 | H14: 100 | I14: 100 | J14: 0 | K14: =IFERROR(AVERAGEIFS(PLP_BUSINESS!X:X, PLP_BUSINESS!$B:$B, Summary!$C14, PLP_BUSINESS!$H:$H, "Y"),0) -> 16.774194 | L14: =IFERROR(AVERAGEIFS(PLP_BUSINESS!Y:Y, PLP_BUSINESS!$B:$B, Summary!$C14, PLP_BUSINESS!$H:$H, "Y"),0) -> 19.354839 | M14: =IFERROR(AVERAGEIFS(PLP_BUSINESS!Z:Z, PLP_BUSINESS!$B:$B, Summary!$C14, PLP_BUSINESS!$H:$H, "Y"),0) -> 15 | N14: =IFERROR(AVERAGEIFS(PLP_BUSINESS!AA:AA, PLP_BUSINESS!$B:$B, Summary!$C14, PLP_BUSINESS!$H:$H, "Y"),0) -> 15 | O14: =IFERROR(AVERAGEIFS(PLP_BUSINESS!AB:AB, PLP_BUSINESS!$B:$B, Summary!$C14, PLP_BUSINESS!$H:$H, "Y"),0) -> 15 | P14: =HLOOKUP($C14,'Product Category'!$E$7:$AS$68,62,0) -> 15 | Q14: =IF(ISNUMBER(MATCH(C14,S:S,0)), NA(), IF(ISNA(P14), NA(), _xlfn.XLOOKUP(C14,Blog!C:C,Blog!G:G,0))) -> 10 | R14: =IF(ISNA(P14), "예외", "")
B15: LATAM | C15: Peru | D15: GP1 | E15: 38 | F15: 38 | G15: 0 | H15: 99.605263 | I15: 93.026316 | J15: 6.5789474 | K15: =IFERROR(AVERAGEIFS(PLP_BUSINESS!X:X, PLP_BUSINESS!$B:$B, Summary!$C15, PLP_BUSINESS!$H:$H, "Y"),0) -> 20 | L15: =IFERROR(AVERAGEIFS(PLP_BUSINESS!Y:Y, PLP_BUSINESS!$B:$B, Summary!$C15, PLP_BUSINESS!$H:$H, "Y"),0) -> 20 | M15: =IFERROR(AVERAGEIFS(PLP_BUSINESS!Z:Z, PLP_BUSINESS!$B:$B, Summary!$C15, PLP_BUSINESS!$H:$H, "Y"),0) -> 15 | N15: =IFERROR(AVERAGEIFS(PLP_BUSINESS!AA:AA, PLP_BUSINESS!$B:$B, Summary!$C15, PLP_BUSINESS!$H:$H, "Y"),0) -> 14.605263 | O15: =IFERROR(AVERAGEIFS(PLP_BUSINESS!AB:AB, PLP_BUSINESS!$B:$B, Summary!$C15, PLP_BUSINESS!$H:$H, "Y"),0) -> 15 | P15: =HLOOKUP($C15,'Product Category'!$E$7:$AS$68,62,0) -> 15 | Q15: =IF(ISNUMBER(MATCH(C15,S:S,0)), NA(), IF(ISNA(P15), NA(), _xlfn.XLOOKUP(C15,Blog!C:C,Blog!G:G,0))) -> 0 | R15: =IF(ISNA(P15), "예외", "")
B16: LATAM | C16: Panama | D16: GP1 | E16: 40 | F16: 40 | G16: 0 | H16: 100 | I16: 100 | J16: 0 | K16: =IFERROR(AVERAGEIFS(PLP_BUSINESS!X:X, PLP_BUSINESS!$B:$B, Summary!$C16, PLP_BUSINESS!$H:$H, "Y"),0) -> 19.5 | L16: =IFERROR(AVERAGEIFS(PLP_BUSINESS!Y:Y, PLP_BUSINESS!$B:$B, Summary!$C16, PLP_BUSINESS!$H:$H, "Y"),0) -> 19.5 | M16: =IFERROR(AVERAGEIFS(PLP_BUSINESS!Z:Z, PLP_BUSINESS!$B:$B, Summary!$C16, PLP_BUSINESS!$H:$H, "Y"),0) -> 14.25 | N16: =IFERROR(AVERAGEIFS(PLP_BUSINESS!AA:AA, PLP_BUSINESS!$B:$B, Summary!$C16, PLP_BUSINESS!$H:$H, "Y"),0) -> 15 | O16: =IFERROR(AVERAGEIFS(PLP_BUSINESS!AB:AB, PLP_BUSINESS!$B:$B, Summary!$C16, PLP_BUSINESS!$H:$H, "Y"),0) -> 15 | P16: =HLOOKUP($C16,'Product Category'!$E$7:$AS$68,62,0) -> 15 | Q16: =IF(ISNUMBER(MATCH(C16,S:S,0)), NA(), IF(ISNA(P16), NA(), _xlfn.XLOOKUP(C16,Blog!C:C,Blog!G:G,0))) -> 10 | R16: =IF(ISNA(P16), "예외", "")
B17: LATAM | C17: Brazil | D17: GP1 | E17: 31 | F17: 30 | G17: 1 | H17: 100 | I17: 97 | J17: 3 | K17: =IFERROR(AVERAGEIFS(PLP_BUSINESS!X:X, PLP_BUSINESS!$B:$B, Summary!$C17, PLP_BUSINESS!$H:$H, "Y"),0) -> 19.354839 | L17: =IFERROR(AVERAGEIFS(PLP_BUSINESS!Y:Y, PLP_BUSINESS!$B:$B, Summary!$C17, PLP_BUSINESS!$H:$H, "Y"),0) -> 18.064516 | M17: =IFERROR(AVERAGEIFS(PLP_BUSINESS!Z:Z, PLP_BUSINESS!$B:$B, Summary!$C17, PLP_BUSINESS!$H:$H, "Y"),0) -> 14.516129 | N17: =IFERROR(AVERAGEIFS(PLP_BUSINESS!AA:AA, PLP_BUSINESS!$B:$B, Summary!$C17, PLP_BUSINESS!$H:$H, "Y"),0) -> 15 | O17: =IFERROR(AVERAGEIFS(PLP_BUSINESS!AB:AB, PLP_BUSINESS!$B:$B, Summary!$C17, PLP_BUSINESS!$H:$H, "Y"),0) -> 15 | P17: =HLOOKUP($C17,'Product Category'!$E$7:$AS$68,62,0) -> 15 | Q17: =IF(ISNUMBER(MATCH(C17,S:S,0)), NA(), IF(ISNA(P17), NA(), _xlfn.XLOOKUP(C17,Blog!C:C,Blog!G:G,0))) -> 10 | R17: =IF(ISNA(P17), "예외", "")
B18: LATAM | C18: Argentina | D18: 5.0 | E18: 51 | F18: 51 | G18: 0 | H18: 89.411765 | I18: 99.411765 | J18: -10 | K18: =IFERROR(AVERAGEIFS(PLP_BUSINESS!X:X, PLP_BUSINESS!$B:$B, Summary!$C18, PLP_BUSINESS!$H:$H, "Y"),0) -> 15.686275 | L18: =IFERROR(AVERAGEIFS(PLP_BUSINESS!Y:Y, PLP_BUSINESS!$B:$B, Summary!$C18, PLP_BUSINESS!$H:$H, "Y"),0) -> 19.607843 | M18: =IFERROR(AVERAGEIFS(PLP_BUSINESS!Z:Z, PLP_BUSINESS!$B:$B, Summary!$C18, PLP_BUSINESS!$H:$H, "Y"),0) -> 11.176471 | N18: =IFERROR(AVERAGEIFS(PLP_BUSINESS!AA:AA, PLP_BUSINESS!$B:$B, Summary!$C18, PLP_BUSINESS!$H:$H, "Y"),0) -> 14.705882 | O18: =IFERROR(AVERAGEIFS(PLP_BUSINESS!AB:AB, PLP_BUSINESS!$B:$B, Summary!$C18, PLP_BUSINESS!$H:$H, "Y"),0) -> 13.235294 | P18: =HLOOKUP($C18,'Product Category'!$E$7:$AS$68,62,0) -> 15 | Q18: =IF(ISNUMBER(MATCH(C18,S:S,0)), NA(), IF(ISNA(P18), NA(), _xlfn.XLOOKUP(C18,Blog!C:C,Blog!G:G,0))) -> 0 | R18: =IF(ISNA(P18), "예외", "")
B19: EU | C19: Croatia | D19: 5.0 | E19: 38 | F19: 38 | G19: 0 | H19: 100 | I19: 100 | J19: 0 | K19: =IFERROR(AVERAGEIFS(PLP_BUSINESS!X:X, PLP_BUSINESS!$B:$B, Summary!$C19, PLP_BUSINESS!$H:$H, "Y"),0) -> 20 | L19: =IFERROR(AVERAGEIFS(PLP_BUSINESS!Y:Y, PLP_BUSINESS!$B:$B, Summary!$C19, PLP_BUSINESS!$H:$H, "Y"),0) -> 20 | M19: =IFERROR(AVERAGEIFS(PLP_BUSINESS!Z:Z, PLP_BUSINESS!$B:$B, Summary!$C19, PLP_BUSINESS!$H:$H, "Y"),0) -> 15 | N19: =IFERROR(AVERAGEIFS(PLP_BUSINESS!AA:AA, PLP_BUSINESS!$B:$B, Summary!$C19, PLP_BUSINESS!$H:$H, "Y"),0) -> 15 | O19: =IFERROR(AVERAGEIFS(PLP_BUSINESS!AB:AB, PLP_BUSINESS!$B:$B, Summary!$C19, PLP_BUSINESS!$H:$H, "Y"),0) -> 15 | P19: =HLOOKUP($C19,'Product Category'!$E$7:$AS$68,62,0) -> #N/A | Q19: =IF(ISNUMBER(MATCH(C19,S:S,0)), NA(), IF(ISNA(P19), NA(), _xlfn.XLOOKUP(C19,Blog!C:C,Blog!G:G,0))) -> #N/A | R19: =IF(ISNA(P19), "예외", "") -> 예외
B20: EU | C20: Germany | D20: GP1 | E20: 33 | F20: 32 | G20: 1 | H20: 84.242424 | I20: 85.9375 | J20: -1.6950758 | K20: =IFERROR(AVERAGEIFS(PLP_BUSINESS!X:X, PLP_BUSINESS!$B:$B, Summary!$C20, PLP_BUSINESS!$H:$H, "Y"),0) -> 13.333333 | L20: =IFERROR(AVERAGEIFS(PLP_BUSINESS!Y:Y, PLP_BUSINESS!$B:$B, Summary!$C20, PLP_BUSINESS!$H:$H, "Y"),0) -> 12.727273 | M20: =IFERROR(AVERAGEIFS(PLP_BUSINESS!Z:Z, PLP_BUSINESS!$B:$B, Summary!$C20, PLP_BUSINESS!$H:$H, "Y"),0) -> 13.636364 | N20: =IFERROR(AVERAGEIFS(PLP_BUSINESS!AA:AA, PLP_BUSINESS!$B:$B, Summary!$C20, PLP_BUSINESS!$H:$H, "Y"),0) -> 14.545455 | O20: =IFERROR(AVERAGEIFS(PLP_BUSINESS!AB:AB, PLP_BUSINESS!$B:$B, Summary!$C20, PLP_BUSINESS!$H:$H, "Y"),0) -> 15 | P20: =HLOOKUP($C20,'Product Category'!$E$7:$AS$68,62,0) -> 15 | Q20: =IF(ISNUMBER(MATCH(C20,S:S,0)), NA(), IF(ISNA(P20), NA(), _xlfn.XLOOKUP(C20,Blog!C:C,Blog!G:G,0))) -> 0 | R20: =IF(ISNA(P20), "예외", "")
B21: EU | C21: Slovakia | D21: 5.0 | E21: 50 | F21: 50 | G21: 0 | H21: 99.066667 | I21: 99.066667 | J21: 0 | K21: =IFERROR(AVERAGEIFS(PLP_BUSINESS!X:X, PLP_BUSINESS!$B:$B, Summary!$C21, PLP_BUSINESS!$H:$H, "Y"),0) -> 12.8 | L21: =IFERROR(AVERAGEIFS(PLP_BUSINESS!Y:Y, PLP_BUSINESS!$B:$B, Summary!$C21, PLP_BUSINESS!$H:$H, "Y"),0) -> 19.2 | M21: =IFERROR(AVERAGEIFS(PLP_BUSINESS!Z:Z, PLP_BUSINESS!$B:$B, Summary!$C21, PLP_BUSINESS!$H:$H, "Y"),0) -> 12.6 | N21: =IFERROR(AVERAGEIFS(PLP_BUSINESS!AA:AA, PLP_BUSINESS!$B:$B, Summary!$C21, PLP_BUSINESS!$H:$H, "Y"),0) -> 15 | O21: =IFERROR(AVERAGEIFS(PLP_BUSINESS!AB:AB, PLP_BUSINESS!$B:$B, Summary!$C21, PLP_BUSINESS!$H:$H, "Y"),0) -> 14.7 | P21: =HLOOKUP($C21,'Product Category'!$E$7:$AS$68,62,0) -> #N/A | Q21: =IF(ISNUMBER(MATCH(C21,S:S,0)), NA(), IF(ISNA(P21), NA(), _xlfn.XLOOKUP(C21,Blog!C:C,Blog!G:G,0))) -> #N/A | R21: =IF(ISNA(P21), "예외", "") -> 예외
B22: EU | C22: Hungary | D22: GP1 | E22: 34 | F22: 34 | G22: 0 | H22: 100 | I22: 87.794118 | J22: 12.205882 | K22: =IFERROR(AVERAGEIFS(PLP_BUSINESS!X:X, PLP_BUSINESS!$B:$B, Summary!$C22, PLP_BUSINESS!$H:$H, "Y"),0) -> 20 | L22: =IFERROR(AVERAGEIFS(PLP_BUSINESS!Y:Y, PLP_BUSINESS!$B:$B, Summary!$C22, PLP_BUSINESS!$H:$H, "Y"),0) -> 20 | M22: =IFERROR(AVERAGEIFS(PLP_BUSINESS!Z:Z, PLP_BUSINESS!$B:$B, Summary!$C22, PLP_BUSINESS!$H:$H, "Y"),0) -> 15 | N22: =IFERROR(AVERAGEIFS(PLP_BUSINESS!AA:AA, PLP_BUSINESS!$B:$B, Summary!$C22, PLP_BUSINESS!$H:$H, "Y"),0) -> 15 | O22: =IFERROR(AVERAGEIFS(PLP_BUSINESS!AB:AB, PLP_BUSINESS!$B:$B, Summary!$C22, PLP_BUSINESS!$H:$H, "Y"),0) -> 15 | P22: =HLOOKUP($C22,'Product Category'!$E$7:$AS$68,62,0) -> 15 | Q22: =IF(ISNUMBER(MATCH(C22,S:S,0)), NA(), IF(ISNA(P22), NA(), _xlfn.XLOOKUP(C22,Blog!C:C,Blog!G:G,0))) -> 10 | R22: =IF(ISNA(P22), "예외", "")
... B59: GLOBAL | C59: Global | D59: 5.0 | E59: 15 | F59: 15 | G59: 0 | H59: 100 | I59: 76 | J59: 24 | K59: =IFERROR(AVERAGEIFS(PLP_BUSINESS!X:X, PLP_BUSINESS!$B:$B, Summary!$C59, PLP_BUSINESS!$H:$H, "Y"),0) -> 20 | L59: =IFERROR(AVERAGEIFS(PLP_BUSINESS!Y:Y, PLP_BUSINESS!$B:$B, Summary!$C59, PLP_BUSINESS!$H:$H, "Y"),0) -> 20 | M59: =IFERROR(AVERAGEIFS(PLP_BUSINESS!Z:Z, PLP_BUSINESS!$B:$B, Summary!$C59, PLP_BUSINESS!$H:$H, "Y"),0) -> 14 | N59: =IFERROR(AVERAGEIFS(PLP_BUSINESS!AA:AA, PLP_BUSINESS!$B:$B, Summary!$C59, PLP_BUSINESS!$H:$H, "Y"),0) -> 13 | O59: =IFERROR(AVERAGEIFS(PLP_BUSINESS!AB:AB, PLP_BUSINESS!$B:$B, Summary!$C59, PLP_BUSINESS!$H:$H, "Y"),0) -> 10 | P59: =HLOOKUP($C59,'Product Category'!$E$7:$AS$68,62,0) -> #N/A | Q59: =IF(ISNUMBER(MATCH(C59,S:S,0)), NA(), IF(ISNA(P59), NA(), _xlfn.XLOOKUP(C59,Blog!C:C,Blog!G:G,0))) -> #N/A | R59: =IF(ISNA(P59), "예외", "") -> 예외

Sheet Summary (최종)
S1: product category 점수 추가(25점, 맨뒤의 탭) | T1: blog 점수(10점 additional)
B2: LG.com Monitoring Report by Country
T4: =Summary!Q4 -> Crawling Date : 25.11.04
B5: REGION | C5: COUNTRY | D5: GP1 Status | E5: SKU | F5: SKU AUG | G5: GAP | H5: Total Score | I5: Total Score AUG | J5: GAP
K6: SEO HTML Tag | P6: Category | Q6: Blog
K7: 1. Title | L7: 2. Description | M7: 3. H1 | N7: 4. Canonical Link | O7: 5. Alt text_ Feature Cards | P7: 6.Product Category | Q7: 7. Blog | R7: August Rank | S7: October Rank | T7: Change
K8: Score (out of 20) | M8: Score (out of 15) | Q8: Additional 10 points
C9: * | E9: 1468 | F9: 1464 | G9: 4 | H9: 97.471458 | I9: 91.862527 | J9: 5.6089317 | K9: {=AVERAGE(_xlfn._xlws.FILTER(K10:K43, ISNA(MATCH($C10:$C43, $V:$V, 0))))} -> 16.438378 | L9: {=AVERAGE(_xlfn._xlws.FILTER(L10:L43, ISNA(MATCH($C10:$C43, $V:$V, 0))))} -> 18.065083 | M9: {=AVERAGE(_xlfn._xlws.FILTER(M10:M43, ISNA(MATCH($C10:$C43, $V:$V, 0))))} -> 13.492513 | N9: {=AVERAGE(_xlfn._xlws.FILTER(N10:N43, ISNA(MATCH($C10:$C43, $V:$V, 0))))} -> 14.87202 | O9: {=AVERAGE(_xlfn._xlws.FILTER(O10:O43, ISNA(MATCH($C10:$C43, $V:$V, 0))))} -> 14.590095 | P9: {=AVERAGE(_xlfn._xlws.FILTER(P10:P43, ISNA(MATCH($C10:$C43, $V:$V, 0))))} -> 14.558824 | Q9: {=AVERAGE(_xlfn._xlws.FILTER(Q10:Q43,ISNA(MATCH($C10:$C43,$V:$V,0))*NOT(ISNA(Q10:Q43))))} -> 5.4545455 | V9: EXCEPTION | W9: BLOG
B10: ASIA | C10: Australia | D10: GP1 | E10: 25 | F10: 25 | G10: 0 | H10: 100 | I10: 100 | J10: 0 | K10: =IF(ISNUMBER(MATCH($C10, $V:$V, 0)), 0, IFERROR(AVERAGEIFS(PLP_BUSINESS!X:X, PLP_BUSINESS!$B:$B, 'Summary (최종)'!$C10, PLP_BUSINESS!$H:$H, "Y"),0)) -> 12.8 | L10: =IF(ISNUMBER(MATCH($C10, $V:$V, 0)), 0, IFERROR(AVERAGEIFS(PLP_BUSINESS!Y:Y, PLP_BUSINESS!$B:$B, 'Summary (최종)'!$C10, PLP_BUSINESS!$H:$H, "Y"),0)) -> 17.6 | M10: =IF(ISNUMBER(MATCH($C10, $V:$V, 0)), 0, IFERROR(AVERAGEIFS(PLP_BUSINESS!Z:Z, PLP_BUSINESS!$B:$B, 'Summary (최종)'!$C10, PLP_BUSINESS!$H:$H, "Y"),0)) -> 15 | N10: =IF(ISNUMBER(MATCH($C10, $V:$V, 0)), 0, IFERROR(AVERAGEIFS(PLP_BUSINESS!AA:AA, PLP_BUSINESS!$B:$B, 'Summary (최종)'!$C10, PLP_BUSINESS!$H:$H, "Y"),0)) -> 15 | O10: =IF(ISNUMBER(MATCH($C10, $V:$V, 0)), 0, IFERROR(AVERAGEIFS(PLP_BUSINESS!AB:AB, PLP_BUSINESS!$B:$B, 'Summary (최종)'!$C10, PLP_BUSINESS!$H:$H, "Y"),0)) -> 15 | P10: =IFERROR(HLOOKUP($C10,'Product Category'!$E$7:$AS$68,62,0), 0) -> 15 | Q10: =IF(ISNUMBER(MATCH(C10,W:W,0)), NA(),_xlfn.XLOOKUP(C10,Blog!C:C,Blog!G:G,0)) -> 10 | R10: {=SUMPRODUCT((ROUND($I$10:$I$43,8)>ROUND(I10,8))*1)+1} -> 1 | S10: {=SUMPRODUCT((ROUND($H$10:$H$43,8)>ROUND(H10,8))*1)+1} -> 1 | T10: =R10-S10 -> 0 | V10: Ecuador | W10: Algeria
B11: LATAM | C11: Brazil | D11: GP1 | E11: 31 | F11: 30 | G11: 1 | H11: 100 | I11: 97 | J11: 3 | K11: =IF(ISNUMBER(MATCH($C11, $V:$V, 0)), 0, IFERROR(AVERAGEIFS(PLP_BUSINESS!X:X, PLP_BUSINESS!$B:$B, 'Summary (최종)'!$C11, PLP_BUSINESS!$H:$H, "Y"),0)) -> 19.354839 | L11: =IF(ISNUMBER(MATCH($C11, $V:$V, 0)), 0, IFERROR(AVERAGEIFS(PLP_BUSINESS!Y:Y, PLP_BUSINESS!$B:$B, 'Summary (최종)'!$C11, PLP_BUSINESS!$H:$H, "Y"),0)) -> 18.064516 | M11: =IF(ISNUMBER(MATCH($C11, $V:$V, 0)), 0, IFERROR(AVERAGEIFS(PLP_BUSINESS!Z:Z, PLP_BUSINESS!$B:$B, 'Summary (최종)'!$C11, PLP_BUSINESS!$H:$H, "Y"),0)) -> 14.516129 | N11: =IF(ISNUMBER(MATCH($C11, $V:$V, 0)), 0, IFERROR(AVERAGEIFS(PLP_BUSINESS!AA:AA, PLP_BUSINESS!$B:$B, 'Summary (최종)'!$C11, PLP_BUSINESS!$H:$H, "Y"),0)) -> 15 | O11: =IF(ISNUMBER(MATCH($C11, $V:$V, 0)), 0, IFERROR(AVERAGEIFS(PLP_BUSINESS!AB:AB, PLP_BUSINESS!$B:$B, 'Summary (최종)'!$C11, PLP_BUSINESS!$H:$H, "Y"),0)) -> 15 | P11: =IFERROR(HLOOKUP($C11,'Product Category'!$E$7:$AS$68,62,0), 0) -> 15 | Q11: =IF(ISNUMBER(MATCH(C11,W:W,0)), NA(),_xlfn.XLOOKUP(C11,Blog!C:C,Blog!G:G,0)) -> 10 | R11: {=SUMPRODUCT((ROUND($I$10:$I$43,8)>ROUND(I11,8))*1)+1} -> 13 | S11: {=SUMPRODUCT((ROUND($H$10:$H$43,8)>ROUND(H11,8))*1)+1} -> 1 | T11: =R11-S11 -> 12 | V11: Croatia
B12: LATAM | C12: Chile | D12: GP1 | E12: 31 | F12: 31 | G12: 0 | H12: 100 | I12: 100 | J12: 0 | K12: =IF(ISNUMBER(MATCH($C12, $V:$V, 0)), 0, IFERROR(AVERAGEIFS(PLP_BUSINESS!X:X, PLP_BUSINESS!$B:$B, 'Summary (최종)'!$C12, PLP_BUSINESS!$H:$H, "Y"),0)) -> 16.774194 | L12: =IF(ISNUMBER(MATCH($C12, $V:$V, 0)), 0, IFERROR(AVERAGEIFS(PLP_BUSINESS!Y:Y, PLP_BUSINESS!$B:$B, 'Summary (최종)'!$C12, PLP_BUSINESS!$H:$H, "Y"),0)) -> 19.354839 | M12: =IF(ISNUMBER(MATCH($C12, $V:$V, 0)), 0, IFERROR(AVERAGEIFS(PLP_BUSINESS!Z:Z, PLP_BUSINESS!$B:$B, 'Summary (최종)'!$C12, PLP_BUSINESS!$H:$H, "Y"),0)) -> 15 | N12: =IF(ISNUMBER(MATCH($C12, $V:$V, 0)), 0, IFERROR(AVERAGEIFS(PLP_BUSINESS!AA:AA, PLP_BUSINESS!$B:$B, 'Summary (최종)'!$C12, PLP_BUSINESS!$H:$H, "Y"),0)) -> 15 | O12: =IF(ISNUMBER(MATCH($C12, $V:$V, 0)), 0, IFERROR(AVERAGEIFS(PLP_BUSINESS!AB:AB, PLP_BUSINESS!$B:$B, 'Summary (최종)'!$C12, PLP_BUSINESS!$H:$H, "Y"),0)) -> 15 | P12: =IFERROR(HLOOKUP($C12,'Product Category'!$E$7:$AS$68,62,0), 0) -> 15 | Q12: =IF(ISNUMBER(MATCH(C12,W:W,0)), NA(),_xlfn.XLOOKUP(C12,Blog!C:C,Blog!G:G,0)) -> 10 | R12: {=SUMPRODUCT((ROUND($I$10:$I$43,8)>ROUND(I12,8))*1)+1} -> 1 | S12: {=SUMPRODUCT((ROUND($H$10:$H$43,8)>ROUND(H12,8))*1)+1} -> 1 | T12: =R12-S12 -> 0 | V12: Slovakia
B13: LATAM | C13: Colombia | D13: GP1 | E13: 33 | F13: 33 | G13: 0 | H13: 100 | I13: 100 | J13: 0 | K13: =IF(ISNUMBER(MATCH($C13, $V:$V, 0)), 0, IFERROR(AVERAGEIFS(PLP_BUSINESS!X:X, PLP_BUSINESS!$B:$B, 'Summary (최종)'!$C13, PLP_BUSINESS!$H:$H, "Y"),0)) -> 20 | L13: =IF(ISNUMBER(MATCH($C13, $V:$V, 0)), 0, IFERROR(AVERAGEIFS(PLP_BUSINESS!Y:Y, PLP_BUSINESS!$B:$B, 'Summary (최종)'!$C13, PLP_BUSINESS!$H:$H, "Y"),0)) -> 18.787879 | M13: =IF(ISNUMBER(MATCH($C13, $V:$V, 0)), 0, IFERROR(AVERAGEIFS(PLP_BUSINESS!Z:Z, PLP_BUSINESS!$B:$B, 'Summary (최종)'!$C13, PLP_BUSINESS!$H:$H, "Y"),0)) -> 15 | N13: =IF(ISNUMBER(MATCH($C13, $V:$V, 0)), 0, IFERROR(AVERAGEIFS(PLP_BUSINESS!AA:AA, PLP_BUSINESS!$B:$B, 'Summary (최종)'!$C13, PLP_BUSINESS!$H:$H, "Y"),0)) -> 15 | O13: =IF(ISNUMBER(MATCH($C13, $V:$V, 0)), 0, IFERROR(AVERAGEIFS(PLP_BUSINESS!AB:AB, PLP_BUSINESS!$B:$B, 'Summary (최종)'!$C13, PLP_BUSINESS!$H:$H, "Y"),0)) -> 15 | P13: =IFERROR(HLOOKUP($C13,'Product Category'!$E$7:$AS$68,62,0), 0) -> 15 | Q13: =IF(ISNUMBER(MATCH(C13,W:W,0)), NA(),_xlfn.XLOOKUP(C13,Blog!C:C,Blog!G:G,0)) -> 10 | R13: {=SUMPRODUCT((ROUND($I$10:$I$43,8)>ROUND(I13,8))*1)+1} -> 1 | S13: {=SUMPRODUCT((ROUND($H$10:$H$43,8)>ROUND(H13,8))*1)+1} -> 1 | T13: =R13-S13 -> 0 | V13: Serbia
B14: EU | C14: Czech | D14: GP1 | E14: 41 | F14: 41 | G14: 0 | H14: 100 | I14: 97.682927 | J14: 2.3170732 | K14: =IF(ISNUMBER(MATCH($C14, $V:$V, 0)), 0, IFERROR(AVERAGEIFS(PLP_BUSINESS!X:X, PLP_BUSINESS!$B:$B, 'Summary (최종)'!$C14, PLP_BUSINESS!$H:$H, "Y"),0)) -> 18.536585 | L14: =IF(ISNUMBER(MATCH($C14, $V:$V, 0)), 0, IFERROR(AVERAGEIFS(PLP_BUSINESS!Y:Y, PLP_BUSINESS!$B:$B, 'Summary (최종)'!$C14, PLP_BUSINESS!$H:$H, "Y"),0)) -> 19.512195 | M14: =IF(ISNUMBER(MATCH($C14, $V:$V, 0)), 0, IFERROR(AVERAGEIFS(PLP_BUSINESS!Z:Z, PLP_BUSINESS!$B:$B, 'Summary (최종)'!$C14, PLP_BUSINESS!$H:$H, "Y"),0)) -> 14.634146 | N14: =IF(ISNUMBER(MATCH($C14, $V:$V, 0)), 0, IFERROR(AVERAGEIFS(PLP_BUSINESS!AA:AA, PLP_BUSINESS!$B:$B, 'Summary (최종)'!$C14, PLP_BUSINESS!$H:$H, "Y"),0)) -> 15 | O14: =IF(ISNUMBER(MATCH($C14, $V:$V, 0)), 0, IFERROR(AVERAGEIFS(PLP_BUSINESS!AB:AB, PLP_BUSINESS!$B:$B, 'Summary (최종)'!$C14, PLP_BUSINESS!$H:$H, "Y"),0)) -> 15 | P14: =IFERROR(HLOOKUP($C14,'Product Category'!$E$7:$AS$68,62,0), 0) -> 15 | Q14: =IF(ISNUMBER(MATCH(C14,W:W,0)), NA(),_xlfn.XLOOKUP(C14,Blog!C:C,Blog!G:G,0)) -> 10 | R14: {=SUMPRODUCT((ROUND($I$10:$I$43,8)>ROUND(I14,8))*1)+1} -> 11 | S14: {=SUMPRODUCT((ROUND($H$10:$H$43,8)>ROUND(H14,8))*1)+1} -> 1 | T14: =R14-S14 -> 10 | V14: Austria
B15: EU | C15: France | D15: GP1 | E15: 24 | F15: 24 | G15: 0 | H15: 100 | I15: 100 | J15: 0 | K15: =IF(ISNUMBER(MATCH($C15, $V:$V, 0)), 0, IFERROR(AVERAGEIFS(PLP_BUSINESS!X:X, PLP_BUSINESS!$B:$B, 'Summary (최종)'!$C15, PLP_BUSINESS!$H:$H, "Y"),0)) -> 20 | L15: =IF(ISNUMBER(MATCH($C15, $V:$V, 0)), 0, IFERROR(AVERAGEIFS(PLP_BUSINESS!Y:Y, PLP_BUSINESS!$B:$B, 'Summary (최종)'!$C15, PLP_BUSINESS!$H:$H, "Y"),0)) -> 20 | M15: =IF(ISNUMBER(MATCH($C15, $V:$V, 0)), 0, IFERROR(AVERAGEIFS(PLP_BUSINESS!Z:Z, PLP_BUSINESS!$B:$B, 'Summary (최종)'!$C15, PLP_BUSINESS!$H:$H, "Y"),0)) -> 15 | N15: =IF(ISNUMBER(MATCH($C15, $V:$V, 0)), 0, IFERROR(AVERAGEIFS(PLP_BUSINESS!AA:AA, PLP_BUSINESS!$B:$B, 'Summary (최종)'!$C15, PLP_BUSINESS!$H:$H, "Y"),0)) -> 15 | O15: =IF(ISNUMBER(MATCH($C15, $V:$V, 0)), 0, IFERROR(AVERAGEIFS(PLP_BUSINESS!AB:AB, PLP_BUSINESS!$B:$B, 'Summary (최종)'!$C15, PLP_BUSINESS!$H:$H, "Y"),0)) -> 15 | P15: =IFERROR(HLOOKUP($C15,'Product Category'!$E$7:$AS$68,62,0), 0) -> 15 | Q15: =IF(ISNUMBER(MATCH(C15,W:W,0)), NA(),_xlfn.XLOOKUP(C15,Blog!C:C,Blog!G:G,0)) -> 0 | R15: {=SUMPRODUCT((ROUND($I$10:$I$43,8)>ROUND(I15,8))*1)+1} -> 1 | S15: {=SUMPRODUCT((ROUND($H$10:$H$43,8)>ROUND(H15,8))*1)+1} -> 1 | T15: =R15-S15 -> 0 | V15: Bulgaria
B16: EU | C16: Hungary | D16: GP1 | E16: 34 | F16: 34 | G16: 0 | H16: 100 | I16: 87.794118 | J16: 12.205882 | K16: =IF(ISNUMBER(MATCH($C16, $V:$V, 0)), 0, IFERROR(AVERAGEIFS(PLP_BUSINESS!X:X, PLP_BUSINESS!$B:$B, 'Summary (최종)'!$C16, PLP_BUSINESS!$H:$H, "Y"),0)) -> 20 | L16: =IF(ISNUMBER(MATCH($C16, $V:$V, 0)), 0, IFERROR(AVERAGEIFS(PLP_BUSINESS!Y:Y, PLP_BUSINESS!$B:$B, 'Summary (최종)'!$C16, PLP_BUSINESS!$H:$H, "Y"),0)) -> 20 | M16: =IF(ISNUMBER(MATCH($C16, $V:$V, 0)), 0, IFERROR(AVERAGEIFS(PLP_BUSINESS!Z:Z, PLP_BUSINESS!$B:$B, 'Summary (최종)'!$C16, PLP_BUSINESS!$H:$H, "Y"),0)) -> 15 | N16: =IF(ISNUMBER(MATCH($C16, $V:$V, 0)), 0, IFERROR(AVERAGEIFS(PLP_BUSINESS!AA:AA, PLP_BUSINESS!$B:$B, 'Summary (최종)'!$C16, PLP_BUSINESS!$H:$H, "Y"),0)) -> 15 | O16: =IF(ISNUMBER(MATCH($C16, $V:$V, 0)), 0, IFERROR(AVERAGEIFS(PLP_BUSINESS!AB:AB, PLP_BUSINESS!$B:$B, 'Summary (최종)'!$C16, PLP_BUSINESS!$H:$H, "Y"),0)) -> 15 | P16: =IFERROR(HLOOKUP($C16,'Product Category'!$E$7:$AS$68,62,0), 0) -> 15 | Q16: =IF(ISNUMBER(MATCH(C16,W:W,0)), NA(),_xlfn.XLOOKUP(C16,Blog!C:C,Blog!G:G,0)) -> 10 | R16: {=SUMPRODUCT((ROUND($I$10:$I$43,8)>ROUND(I16,8))*1)+1} -> 24 | S16: {=SUMPRODUCT((ROUND($H$10:$H$43,8)>ROUND(H16,8))*1)+1} -> 1 | T16: =R16-S16 -> 23 | V16: Netherlands
B17: INDIA | C17: India | D17: GP1 | E17: 35 | F17: 35 | G17: 0 | H17: 100 | I17: 91.714286 | J17: 8.2857143 | K17: =IF(ISNUMBER(MATCH($C17, $V:$V, 0)), 0, IFERROR(AVERAGEIFS(PLP_BUSINESS!X:X, PLP_BUSINESS!$B:$B, 'Summary (최종)'!$C17, PLP_BUSINESS!$H:$H, "Y"),0)) -> 16 | L17: =IF(ISNUMBER(MATCH($C17, $V:$V, 0)), 0, IFERROR(AVERAGEIFS(PLP_BUSINESS!Y:Y, PLP_BUSINESS!$B:$B, 'Summary (최종)'!$C17, PLP_BUSINESS!$H:$H, "Y"),0)) -> 20 | M17: =IF(ISNUMBER(MATCH($C17, $V:$V, 0)), 0, IFERROR(AVERAGEIFS(PLP_BUSINESS!Z:Z, PLP_BUSINESS!$B:$B, 'Summary (최종)'!$C17, PLP_BUSINESS!$H:$H, "Y"),0)) -> 15 | N17: =IF(ISNUMBER(MATCH($C17, $V:$V, 0)), 0, IFERROR(AVERAGEIFS(PLP_BUSINESS!AA:AA, PLP_BUSINESS!$B:$B, 'Summary (최종)'!$C17, PLP_BUSINESS!$H:$H, "Y"),0)) -> 15 | O17: =IF(ISNUMBER(MATCH($C17, $V:$V, 0)), 0, IFERROR(AVERAGEIFS(PLP_BUSINESS!AB:AB, PLP_BUSINESS!$B:$B, 'Summary (최종)'!$C17, PLP_BUSINESS!$H:$H, "Y"),0)) -> 15 | P17: =IFERROR(HLOOKUP($C17,'Product Category'!$E$7:$AS$68,62,0), 0) -> 15 | Q17: =IF(ISNUMBER(MATCH(C17,W:W,0)), NA(),_xlfn.XLOOKUP(C17,Blog!C:C,Blog!G:G,0)) -> 10 | R17: {=SUMPRODUCT((ROUND($I$10:$I$43,8)>ROUND(I17,8))*1)+1} -> 19 | S17: {=SUMPRODUCT((ROUND($H$10:$H$43,8)>ROUND(H17,8))*1)+1} -> 1 | T17: =R17-S17 -> 18 | V17: Portugal
B18: ASIA | C18: Indonesia | D18: GP1 | E18: 41 | F18: 41 | G18: 0 | H18: 100 | I18: 100 | J18: 0 | K18: =IF(ISNUMBER(MATCH($C18, $V:$V, 0)), 0, IFERROR(AVERAGEIFS(PLP_BUSINESS!X:X, PLP_BUSINESS!$B:$B, 'Summary (최종)'!$C18, PLP_BUSINESS!$H:$H, "Y"),0)) -> 19.512195 | L18: =IF(ISNUMBER(MATCH($C18, $V:$V, 0)), 0, IFERROR(AVERAGEIFS(PLP_BUSINESS!Y:Y, PLP_BUSINESS!$B:$B, 'Summary (최종)'!$C18, PLP_BUSINESS!$H:$H, "Y"),0)) -> 18.04878 | M18: =IF(ISNUMBER(MATCH($C18, $V:$V, 0)), 0, IFERROR(AVERAGEIFS(PLP_BUSINESS!Z:Z, PLP_BUSINESS!$B:$B, 'Summary (최종)'!$C18, PLP_BUSINESS!$H:$H, "Y"),0)) -> 13.170732 | N18: =IF(ISNUMBER(MATCH($C18, $V:$V, 0)), 0, IFERROR(AVERAGEIFS(PLP_BUSINESS!AA:AA, PLP_BUSINESS!$B:$B, 'Summary (최종)'!$C18, PLP_BUSINESS!$H:$H, "Y"),0)) -> 15 | O18: =IF(ISNUMBER(MATCH($C18, $V:$V, 0)), 0, IFERROR(AVERAGEIFS(PLP_BUSINESS!AB:AB, PLP_BUSINESS!$B:$B, 'Summary (최종)'!$C18, PLP_BUSINESS!$H:$H, "Y"),0)) -> 15 | P18: =IFERROR(HLOOKUP($C18,'Product Category'!$E$7:$AS$68,62,0), 0) -> 15 | Q18: =IF(ISNUMBER(MATCH(C18,W:W,0)), NA(),_xlfn.XLOOKUP(C18,Blog!C:C,Blog!G:G,0)) -> 10 | R18: {=SUMPRODUCT((ROUND($I$10:$I$43,8)>ROUND(I18,8))*1)+1} -> 1 | S18: {=SUMPRODUCT((ROUND($H$10:$H$43,8)>ROUND(H18,8))*1)+1} -> 1 | T18: =R18-S18 -> 0 | V18: Uzbekistan
B19: MEA | C19: Kenya | D19: 5.0 | E19: 39 | F19: 39 | G19: 0 | H19: 100 | I19: 85.512821 | J19: 14.487179 | K19: =IF(ISNUMBER(MATCH($C19, $V:$V, 0)), 0, IFERROR(AVERAGEIFS(PLP_BUSINESS!X:X, PLP_BUSINESS!$B:$B, 'Summary (최종)'!$C19, PLP_BUSINESS!$H:$H, "Y"),0)) -> 18.974359 | L19: =IF(ISNUMBER(MATCH($C19, $V:$V, 0)), 0, IFERROR(AVERAGEIFS(PLP_BUSINESS!Y:Y, PLP_BUSINESS!$B:$B, 'Summary (최종)'!$C19, PLP_BUSINESS!$H:$H, "Y"),0)) -> 19.487179 | M19: =IF(ISNUMBER(MATCH($C19, $V:$V, 0)), 0, IFERROR(AVERAGEIFS(PLP_BUSINESS!Z:Z, PLP_BUSINESS!$B:$B, 'Summary (최종)'!$C19, PLP_BUSINESS!$H:$H, "Y"),0)) -> 15 | N19: =IF(ISNUMBER(MATCH($C19, $V:$V, 0)), 0, IFERROR(AVERAGEIFS(PLP_BUSINESS!AA:AA, PLP_BUSINESS!$B:$B, 'Summary (최종)'!$C19, PLP_BUSINESS!$H:$H, "Y"),0)) -> 15 | O19: =IF(ISNUMBER(MATCH($C19, $V:$V, 0)), 0, IFERROR(AVERAGEIFS(PLP_BUSINESS!AB:AB, PLP_BUSINESS!$B:$B, 'Summary (최종)'!$C19, PLP_BUSINESS!$H:$H, "Y"),0)) -> 13.846154 | P19: =IFERROR(HLOOKUP($C19,'Product Category'!$E$7:$AS$68,62,0), 0) -> 15 | Q19: =IF(ISNUMBER(MATCH(C19,W:W,0)), NA(),_xlfn.XLOOKUP(C19,Blog!C:C,Blog!G:G,0)) -> 10 | R19: {=SUMPRODUCT((ROUND($I$10:$I$43,8)>ROUND(I19,8))*1)+1} -> 27 | S19: {=SUMPRODUCT((ROUND($H$10:$H$43,8)>ROUND(H19,8))*1)+1} -> 1 | T19: =R19-S19 -> 26 | V19: Kazakhstan
B20: LATAM | C20: Mexico | D20: GP1 | E20: 42 | F20: 42 | G20: 0 | H20: 100 | I20: 100 | J20: 0 | K20: =IF(ISNUMBER(MATCH($C20, $V:$V, 0)), 0, IFERROR(AVERAGEIFS(PLP_BUSINESS!X:X, PLP_BUSINESS!$B:$B, 'Summary (최종)'!$C20, PLP_BUSINESS!$H:$H, "Y"),0)) -> 20 | L20: =IF(ISNUMBER(MATCH($C20, $V:$V, 0)), 0, IFERROR(AVERAGEIFS(PLP_BUSINESS!Y:Y, PLP_BUSINESS!$B:$B, 'Summary (최종)'!$C20, PLP_BUSINESS!$H:$H, "Y"),0)) -> 20 | M20: =IF(ISNUMBER(MATCH($C20, $V:$V, 0)), 0, IFERROR(AVERAGEIFS(PLP_BUSINESS!Z:Z, PLP_BUSINESS!$B:$B, 'Summary (최종)'!$C20, PLP_BUSINESS!$H:$H, "Y"),0)) -> 15 | N20: =IF(ISNUMBER(MATCH($C20, $V:$V, 0)), 0, IFERROR(AVERAGEIFS(PLP_BUSINESS!AA:AA, PLP_BUSINESS!$B:$B, 'Summary (최종)'!$C20, PLP_BUSINESS!$H:$H, "Y"),0)) -> 14.642857 | O20: =IF(ISNUMBER(MATCH($C20, $V:$V, 0)), 0, IFERROR(AVERAGEIFS(PLP_BUSINESS!AB:AB, PLP_BUSINESS!$B:$B, 'Summary (최종)'!$C20, PLP_BUSINESS!$H:$H, "Y"),0)) -> 15 | P20: =IFERROR(HLOOKUP($C20,'Product Category'!$E$7:$AS$68,62,0), 0) -> 15 | Q20: =IF(ISNUMBER(MATCH(C20,W:W,0)), NA(),_xlfn.XLOOKUP(C20,Blog!C:C,Blog!G:G,0)) -> 10 | R20: {=SUMPRODUCT((ROUND($I$10:$I$43,8)>ROUND(I20,8))*1)+1} -> 1 | S20: {=SUMPRODUCT((ROUND($H$10:$H$43,8)>ROUND(H20,8))*1)+1} -> 1 | T20: =R20-S20 -> 0 | V20: Morocco
B21: LATAM | C21: Panama | D21: GP1 | E21: 40 | F21: 40 | G21: 0 | H21: 100 | I21: 100 | J21: 0 | K21: =IF(ISNUMBER(MATCH($C21, $V:$V, 0)), 0, IFERROR(AVERAGEIFS(PLP_BUSINESS!X:X, PLP_BUSINESS!$B:$B, 'Summary (최종)'!$C21, PLP_BUSINESS!$H:$H, "Y"),0)) -> 19.5 | L21: =IF(ISNUMBER(MATCH($C21, $V:$V, 0)), 0, IFERROR(AVERAGEIFS(PLP_BUSINESS!Y:Y, PLP_BUSINESS!$B:$B, 'Summary (최종)'!$C21, PLP_BUSINESS!$H:$H, "Y"),0)) -> 19.5 | M21: =IF(ISNUMBER(MATCH($C21, $V:$V, 0)), 0, IFERROR(AVERAGEIFS(PLP_BUSINESS!Z:Z, PLP_BUSINESS!$B:$B, 'Summary (최종)'!$C21, PLP_BUSINESS!$H:$H, "Y"),0)) -> 14.25 | N21: =IF(ISNUMBER(MATCH($C21, $V:$V, 0)), 0, IFERROR(AVERAGEIFS(PLP_BUSINESS!AA:AA, PLP_BUSINESS!$B:$B, 'Summary (최종)'!$C21, PLP_BUSINESS!$H:$H, "Y"),0)) -> 15 | O21: =IF(ISNUMBER(MATCH($C21, $V:$V, 0)), 0, IFERROR(AVERAGEIFS(PLP_BUSINESS!AB:AB, PLP_BUSINESS!$B:$B, 'Summary (최종)'!$C21, PLP_BUSINESS!$H:$H, "Y"),0)) -> 15 | P21: =IFERROR(HLOOKUP($C21,'Product Category'!$E$7:$AS$68,62,0), 0) -> 15 | Q21: =IF(ISNUMBER(MATCH(C21,W:W,0)), NA(),_xlfn.XLOOKUP(C21,Blog!C:C,Blog!G:G,0)) -> 10 | R21: {=SUMPRODUCT((ROUND($I$10:$I$43,8)>ROUND(I21,8))*1)+1} -> 1 | S21: {=SUMPRODUCT((ROUND($H$10:$H$43,8)>ROUND(H21,8))*1)+1} -> 1 | T21: =R21-S21 -> 0 | V21: Iran
B22: ASIA | C22: Singapore | D22: GP1 | E22: 40 | F22: 40 | G22: 0 | H22: 100 | I22: 76.875 | J22: 23.125 | K22: =IF(ISNUMBER(MATCH($C22, $V:$V, 0)), 0, IFERROR(AVERAGEIFS(PLP_BUSINESS!X:X, PLP_BUSINESS!$B:$B, 'Summary (최종)'!$C22, PLP_BUSINESS!$H:$H, "Y"),0)) -> 19.5 | L22: =IF(ISNUMBER(MATCH($C22, $V:$V, 0)), 0, IFERROR(AVERAGEIFS(PLP_BUSINESS!Y:Y, PLP_BUSINESS!$B:$B, 'Summary (최종)'!$C22, PLP_BUSINESS!$H:$H, "Y"),0)) -> 20 | M22: =IF(ISNUMBER(MATCH($C22, $V:$V, 0)), 0, IFERROR(AVERAGEIFS(PLP_BUSINESS!Z:Z, PLP_BUSINESS!$B:$B, 'Summary (최종)'!$C22, PLP_BUSINESS!$H:$H, "Y"),0)) -> 15 | N22: =IF(ISNUMBER(MATCH($C22, $V:$V, 0)), 0, IFERROR(AVERAGEIFS(PLP_BUSINESS!AA:AA, PLP_BUSINESS!$B:$B, 'Summary (최종)'!$C22, PLP_BUSINESS!$H:$H, "Y"),0)) -> 15 | O22: =IF(ISNUMBER(MATCH($C22, $V:$V, 0)), 0, IFERROR(AVERAGEIFS(PLP_BUSINESS!AB:AB, PLP_BUSINESS!$B:$B, 'Summary (최종)'!$C22, PLP_BUSINESS!$H:$H, "Y"),0)) -> 15 | P22: =IFERROR(HLOOKUP($C22,'Product Category'!$E$7:$AS$68,62,0), 0) -> 15 | Q22: =IF(ISNUMBER(MATCH(C22,W:W,0)), NA(),_xlfn.XLOOKUP(C22,Blog!C:C,Blog!G:G,0)) -> 10 | R22: {=SUMPRODUCT((ROUND($I$10:$I$43,8)>ROUND(I22,8))*1)+1} -> 31 | S22: {=SUMPRODUCT((ROUND($H$10:$H$43,8)>ROUND(H22,8))*1)+1} -> 1 | T22: =R22-S22 -> 30 | V22: Bangladesh
... B25: MEA | C25: UAE | D25: 5.0 | E25: 85 | F25: 84 | G25: 1 | H25: 100 | I25: 78.511905 | J25: 21.488095 | K25: =IF(ISNUMBER(MATCH($C25, $V:$V, 0)), 0, IFERROR(AVERAGEIFS(PLP_BUSINESS!X:X, PLP_BUSINESS!$B:$B, 'Summary (최종)'!$C25, PLP_BUSINESS!$H:$H, "Y"),0)) -> 19.529412 | L25: =IF(ISNUMBER(MATCH($C25, $V:$V, 0)), 0, IFERROR(AVERAGEIFS(PLP_BUSINESS!Y:Y, PLP_BUSINESS!$B:$B, 'Summary (최종)'!$C25, PLP_BUSINESS!$H:$H, "Y"),0)) -> 19.764706 | M25: =IF(ISNUMBER(MATCH($C25, $V:$V, 0)), 0, IFERROR(AVERAGEIFS(PLP_BUSINESS!Z:Z, PLP_BUSINESS!$B:$B, 'Summary (최종)'!$C25, PLP_BUSINESS!$H:$H, "Y"),0)) -> 15 | N25: =IF(ISNUMBER(MATCH($C25, $V:$V, 0)), 0, IFERROR(AVERAGEIFS(PLP_BUSINESS!AA:AA, PLP_BUSINESS!$B:$B, 'Summary (최종)'!$C25, PLP_BUSINESS!$H:$H, "Y"),0)) -> 14.470588 | O25: =IF(ISNUMBER(MATCH($C25, $V:$V, 0)), 0, IFERROR(AVERAGEIFS(PLP_BUSINESS!AB:AB, PLP_BUSINESS!$B:$B, 'Summary (최종)'!$C25, PLP_BUSINESS!$H:$H, "Y"),0)) -> 14.470588 | P25: =IFERROR(HLOOKUP($C25,'Product Category'!$E$7:$AS$68,62,0), 0) -> 10 | Q25: =IF(ISNUMBER(MATCH(C25,W:W,0)), NA(),_xlfn.XLOOKUP(C25,Blog!C:C,Blog!G:G,0)) -> 10 | R25: {=SUMPRODUCT((ROUND($I$10:$I$43,8)>ROUND(I25,8))*1)+1} -> 28 | S25: {=SUMPRODUCT((ROUND($H$10:$H$43,8)>ROUND(H25,8))*1)+1} -> 1 | T25: =R25-S25 -> 27 | V25: Taiwan
B26: ASIA | C26: Vietnam | D26: GP1 | E26: 44 | F26: 43 | G26: 1 | H26: 100 | I26: 99.883721 | J26: 0.11627907 | K26: =IF(ISNUMBER(MATCH($C26, $V:$V, 0)), 0, IFERROR(AVERAGEIFS(PLP_BUSINESS!X:X, PLP_BUSINESS!$B:$B, 'Summary (최종)'!$C26, PLP_BUSINESS!$H:$H, "Y"),0)) -> 19.545455 | L26: =IF(ISNUMBER(MATCH($C26, $V:$V, 0)), 0, IFERROR(AVERAGEIFS(PLP_BUSINESS!Y:Y, PLP_BUSINESS!$B:$B, 'Summary (최종)'!$C26, PLP_BUSINESS!$H:$H, "Y"),0)) -> 19.545455 | M26: =IF(ISNUMBER(MATCH($C26, $V:$V, 0)), 0, IFERROR(AVERAGEIFS(PLP_BUSINESS!Z:Z, PLP_BUSINESS!$B:$B, 'Summary (최종)'!$C26, PLP_BUSINESS!$H:$H, "Y"),0)) -> 15 | N26: =IF(ISNUMBER(MATCH($C26, $V:$V, 0)), 0, IFERROR(AVERAGEIFS(PLP_BUSINESS!AA:AA, PLP_BUSINESS!$B:$B, 'Summary (최종)'!$C26, PLP_BUSINESS!$H:$H, "Y"),0)) -> 15 | O26: =IF(ISNUMBER(MATCH($C26, $V:$V, 0)), 0, IFERROR(AVERAGEIFS(PLP_BUSINESS!AB:AB, PLP_BUSINESS!$B:$B, 'Summary (최종)'!$C26, PLP_BUSINESS!$H:$H, "Y"),0)) -> 15 | P26: =IFERROR(HLOOKUP($C26,'Product Category'!$E$7:$AS$68,62,0), 0) -> 15 | Q26: =IF(ISNUMBER(MATCH(C26,W:W,0)), NA(),_xlfn.XLOOKUP(C26,Blog!C:C,Blog!G:G,0)) -> 10 | R26: {=SUMPRODUCT((ROUND($I$10:$I$43,8)>ROUND(I26,8))*1)+1} -> 8 | S26: {=SUMPRODUCT((ROUND($H$10:$H$43,8)>ROUND(H26,8))*1)+1} -> 1 | T26: =R26-S26 -> 7
B27: LATAM | C27: Peru | D27: GP1 | E27: 38 | F27: 38 | G27: 0 | H27: 99.605263 | I27: 93.026316 | J27: 6.5789474 | K27: =IF(ISNUMBER(MATCH($C27, $V:$V, 0)), 0, IFERROR(AVERAGEIFS(PLP_BUSINESS!X:X, PLP_BUSINESS!$B:$B, 'Summary (최종)'!$C27, PLP_BUSINESS!$H:$H, "Y"),0)) -> 20 | L27: =IF(ISNUMBER(MATCH($C27, $V:$V, 0)), 0, IFERROR(AVERAGEIFS(PLP_BUSINESS!Y:Y, PLP_BUSINESS!$B:$B, 'Summary (최종)'!$C27, PLP_BUSINESS!$H:$H, "Y"),0)) -> 20 | M27: =IF(ISNUMBER(MATCH($C27, $V:$V, 0)), 0, IFERROR(AVERAGEIFS(PLP_BUSINESS!Z:Z, PLP_BUSINESS!$B:$B, 'Summary (최종)'!$C27, PLP_BUSINESS!$H:$H, "Y"),0)) -> 15 | N27: =IF(ISNUMBER(MATCH($C27, $V:$V, 0)), 0, IFERROR(AVERAGEIFS(PLP_BUSINESS!AA:AA, PLP_BUSINESS!$B:$B, 'Summary (최종)'!$C27, PLP_BUSINESS!$H:$H, "Y"),0)) -> 14.605263 | O27: =IF(ISNUMBER(MATCH($C27, $V:$V, 0)), 0, IFERROR(AVERAGEIFS(PLP_BUSINESS!AB:AB, PLP_BUSINESS!$B:$B, 'Summary (최종)'!$C27, PLP_BUSINESS!$H:$H, "Y"),0)) -> 15 | P27: =IFERROR(HLOOKUP($C27,'Product Category'!$E$7:$AS$68,62,0), 0) -> 15 | Q27: =IF(ISNUMBER(MATCH(C27,W:W,0)), NA(),_xlfn.XLOOKUP(C27,Blog!C:C,Blog!G:G,0)) -> 0 | R27: {=SUMPRODUCT((ROUND($I$10:$I$43,8)>ROUND(I27,8))*1)+1} -> 17 | S27: {=SUMPRODUCT((ROUND($H$10:$H$43,8)>ROUND(H27,8))*1)+1} -> 18 | T27: =R27-S27 -> -1
B28: MEA | C28: Jordan | D28: 5.0 | E28: 73 | F28: 73 | G28: 0 | H28: 98.493151 | I28: 77.671233 | J28: 20.821918 | K28: =IF(ISNUMBER(MATCH($C28, $V:$V, 0)), 0, IFERROR(AVERAGEIFS(PLP_BUSINESS!X:X, PLP_BUSINESS!$B:$B, 'Summary (최종)'!$C28, PLP_BUSINESS!$H:$H, "Y"),0)) -> 19.726027 | L28: =IF(ISNUMBER(MATCH($C28, $V:$V, 0)), 0, IFERROR(AVERAGEIFS(PLP_BUSINESS!Y:Y, PLP_BUSINESS!$B:$B, 'Summary (최종)'!$C28, PLP_BUSINESS!$H:$H, "Y"),0)) -> 20 | M28: =IF(ISNUMBER(MATCH($C28, $V:$V, 0)), 0, IFERROR(AVERAGEIFS(PLP_BUSINESS!Z:Z, PLP_BUSINESS!$B:$B, 'Summary (최종)'!$C28, PLP_BUSINESS!$H:$H, "Y"),0)) -> 14.794521 | N28: =IF(ISNUMBER(MATCH($C28, $V:$V, 0)), 0, IFERROR(AVERAGEIFS(PLP_BUSINESS!AA:AA, PLP_BUSINESS!$B:$B, 'Summary (최종)'!$C28, PLP_BUSINESS!$H:$H, "Y"),0)) -> 14.383562 | O28: =IF(ISNUMBER(MATCH($C28, $V:$V, 0)), 0, IFERROR(AVERAGEIFS(PLP_BUSINESS!AB:AB, PLP_BUSINESS!$B:$B, 'Summary (최종)'!$C28, PLP_BUSINESS!$H:$H, "Y"),0)) -> 14.589041 | P28: =IFERROR(HLOOKUP($C28,'Product Category'!$E$7:$AS$68,62,0), 0) -> 15 | Q28: =IF(ISNUMBER(MATCH(C28,W:W,0)), NA(),_xlfn.XLOOKUP(C28,Blog!C:C,Blog!G:G,0)) -> 0 | R28: {=SUMPRODUCT((ROUND($I$10:$I$43,8)>ROUND(I28,8))*1)+1} -> 29 | S28: {=SUMPRODUCT((ROUND($H$10:$H$43,8)>ROUND(H28,8))*1)+1} -> 19 | T28: =R28-S28 -> 10
B29: MEA | C29: SaudiArabia | D29: GP1 | E29: 60 | F29: 60 | G29: 0 | H29: 98.166667 | I29: 98.166667 | J29: 0 | K29: =IF(ISNUMBER(MATCH($C29, $V:$V, 0)), 0, IFERROR(AVERAGEIFS(PLP_BUSINESS!X:X, PLP_BUSINESS!$B:$B, 'Summary (최종)'!$C29, PLP_BUSINESS!$H:$H, "Y"),0)) -> 19 | L29: =IF(ISNUMBER(MATCH($C29, $V:$V, 0)), 0, IFERROR(AVERAGEIFS(PLP_BUSINESS!Y:Y, PLP_BUSINESS!$B:$B, 'Summary (최종)'!$C29, PLP_BUSINESS!$H:$H, "Y"),0)) -> 19.666667 | M29: =IF(ISNUMBER(MATCH($C29, $V:$V, 0)), 0, IFERROR(AVERAGEIFS(PLP_BUSINESS!Z:Z, PLP_BUSINESS!$B:$B, 'Summary (최종)'!$C29, PLP_BUSINESS!$H:$H, "Y"),0)) -> 14.5 | N29: =IF(ISNUMBER(MATCH($C29, $V:$V, 0)), 0, IFERROR(AVERAGEIFS(PLP_BUSINESS!AA:AA, PLP_BUSINESS!$B:$B, 'Summary (최종)'!$C29, PLP_BUSINESS!$H:$H, "Y"),0)) -> 15 | O29: =IF(ISNUMBER(MATCH($C29, $V:$V, 0)), 0, IFERROR(AVERAGEIFS(PLP_BUSINESS!AB:AB, PLP_BUSINESS!$B:$B, 'Summary (최종)'!$C29, PLP_BUSINESS!$H:$H, "Y"),0)) -> 15 | P29: =IFERROR(HLOOKUP($C29,'Product Category'!$E$7:$AS$68,62,0), 0) -> 15 | Q29: =IF(ISNUMBER(MATCH(C29,W:W,0)), NA(),_xlfn.XLOOKUP(C29,Blog!C:C,Blog!G:G,0)) -> 0 | R29: {=SUMPRODUCT((ROUND($I$10:$I$43,8)>ROUND(I29,8))*1)+1} -> 10 | S29: {=SUMPRODUCT((ROUND($H$10:$H$43,8)>ROUND(H29,8))*1)+1} -> 20 | T29: =R29-S29 -> -10
B30: EU | C30: UK | D30: GP1 | E30: 28 | F30: 28 | G30: 0 | H30: 96.785714 | I30: 96.785714 | J30: 0 | K30: =IF(ISNUMBER(MATCH($C30, $V:$V, 0)), 0, IFERROR(AVERAGEIFS(PLP_BUSINESS!X:X, PLP_BUSINESS!$B:$B, 'Summary (최종)'!$C30, PLP_BUSINESS!$H:$H, "Y"),0)) -> 13.571429 | L30: =IF(ISNUMBER(MATCH($C30, $V:$V, 0)), 0, IFERROR(AVERAGEIFS(PLP_BUSINESS!Y:Y, PLP_BUSINESS!$B:$B, 'Summary (최종)'!$C30, PLP_BUSINESS!$H:$H, "Y"),0)) -> 16.428571 | M30: =IF(ISNUMBER(MATCH($C30, $V:$V, 0)), 0, IFERROR(AVERAGEIFS(PLP_BUSINESS!Z:Z, PLP_BUSINESS!$B:$B, 'Summary (최종)'!$C30, PLP_BUSINESS!$H:$H, "Y"),0)) -> 11.785714 | N30: =IF(ISNUMBER(MATCH($C30, $V:$V, 0)), 0, IFERROR(AVERAGEIFS(PLP_BUSINESS!AA:AA, PLP_BUSINESS!$B:$B, 'Summary (최종)'!$C30, PLP_BUSINESS!$H:$H, "Y"),0)) -> 15 | O30: =IF(ISNUMBER(MATCH($C30, $V:$V, 0)), 0, IFERROR(AVERAGEIFS(PLP_BUSINESS!AB:AB, PLP_BUSINESS!$B:$B, 'Summary (최종)'!$C30, PLP_BUSINESS!$H:$H, "Y"),0)) -> 15 | P30: =IFERROR(HLOOKUP($C30,'Product Category'!$E$7:$AS$68,62,0), 0) -> 15 | Q30: =IF(ISNUMBER(MATCH(C30,W:W,0)), NA(),_xlfn.XLOOKUP(C30,Blog!C:C,Blog!G:G,0)) -> 10 | R30: {=SUMPRODUCT((ROUND($I$10:$I$43,8)>ROUND(I30,8))*1)+1} -> 14 | S30: {=SUMPRODUCT((ROUND($H$10:$H$43,8)>ROUND(H30,8))*1)+1} -> 21 | T30: =R30-S30 -> -7
B31: ASIA | C31: China | D31: 5.0 | E31: 39 | F31: 39 | G31: 0 | H31: 95 | I31: 95 | J31: 0 | K31: =IF(ISNUMBER(MATCH($C31, $V:$V, 0)), 0, IFERROR(AVERAGEIFS(PLP_BUSINESS!X:X, PLP_BUSINESS!$B:$B, 'Summary (최종)'!$C31, PLP_BUSINESS!$H:$H, "Y"),0)) -> 15.384615 | L31: =IF(ISNUMBER(MATCH($C31, $V:$V, 0)), 0, IFERROR(AVERAGEIFS(PLP_BUSINESS!Y:Y, PLP_BUSINESS!$B:$B, 'Summary (최종)'!$C31, PLP_BUSINESS!$H:$H, "Y"),0)) -> 20 | M31: =IF(ISNUMBER(MATCH($C31, $V:$V, 0)), 0, IFERROR(AVERAGEIFS(PLP_BUSINESS!Z:Z, PLP_BUSINESS!$B:$B, 'Summary (최종)'!$C31, PLP_BUSINESS!$H:$H, "Y"),0)) -> 14.615385 | N31: =IF(ISNUMBER(MATCH($C31, $V:$V, 0)), 0, IFERROR(AVERAGEIFS(PLP_BUSINESS!AA:AA, PLP_BUSINESS!$B:$B, 'Summary (최종)'!$C31, PLP_BUSINESS!$H:$H, "Y"),0)) -> 15 | O31: =IF(ISNUMBER(MATCH($C31, $V:$V, 0)), 0, IFERROR(AVERAGEIFS(PLP_BUSINESS!AB:AB, PLP_BUSINESS!$B:$B, 'Summary (최종)'!$C31, PLP_BUSINESS!$H:$H, "Y"),0)) -> 15 | P31: =IFERROR(HLOOKUP($C31,'Product Category'!$E$7:$AS$68,62,0), 0) -> 15 | Q31: =IF(ISNUMBER(MATCH(C31,W:W,0)), NA(),_xlfn.XLOOKUP(C31,Blog!C:C,Blog!G:G,0)) -> 0 | R31: {=SUMPRODUCT((ROUND($I$10:$I$43,8)>ROUND(I31,8))*1)+1} -> 15 | S31: {=SUMPRODUCT((ROUND($H$10:$H$43,8)>ROUND(H31,8))*1)+1} -> 22 | T31: =R31-S31 -> -7
B32: MEA | C32: Nigeria | D32: 5.0 | E32: 74 | F32: 74 | G32: 0 | H32: 93.851351 | I32: 93.851351 | J32: 0 | K32: =IF(ISNUMBER(MATCH($C32, $V:$V, 0)), 0, IFERROR(AVERAGEIFS(PLP_BUSINESS!X:X, PLP_BUSINESS!$B:$B, 'Summary (최종)'!$C32, PLP_BUSINESS!$H:$H, "Y"),0)) -> 12.162162 | L32: =IF(ISNUMBER(MATCH($C32, $V:$V, 0)), 0, IFERROR(AVERAGEIFS(PLP_BUSINESS!Y:Y, PLP_BUSINESS!$B:$B, 'Summary (최종)'!$C32, PLP_BUSINESS!$H:$H, "Y"),0)) -> 18.918919 | M32: =IF(ISNUMBER(MATCH($C32, $V:$V, 0)), 0, IFERROR(AVERAGEIFS(PLP_BUSINESS!Z:Z, PLP_BUSINESS!$B:$B, 'Summary (최종)'!$C32, PLP_BUSINESS!$H:$H, "Y"),0)) -> 14.189189 | N32: =IF(ISNUMBER(MATCH($C32, $V:$V, 0)), 0, IFERROR(AVERAGEIFS(PLP_BUSINESS!AA:AA, PLP_BUSINESS!$B:$B, 'Summary (최종)'!$C32, PLP_BUSINESS!$H:$H, "Y"),0)) -> 14.797297 | O32: =IF(ISNUMBER(MATCH($C32, $V:$V, 0)), 0, IFERROR(AVERAGEIFS(PLP_BUSINESS!AB:AB, PLP_BUSINESS!$B:$B, 'Summary (최종)'!$C32, PLP_BUSINESS!$H:$H, "Y"),0)) -> 13.783784 | P32: =IFERROR(HLOOKUP($C32,'Product Category'!$E$7:$AS$68,62,0), 0) -> 10 | Q32: =IF(ISNUMBER(MATCH(C32,W:W,0)), NA(),_xlfn.XLOOKUP(C32,Blog!C:C,Blog!G:G,0)) -> 10 | R32: {=SUMPRODUCT((ROUND($I$10:$I$43,8)>ROUND(I32,8))*1)+1} -> 16 | S32: {=SUMPRODUCT((ROUND($H$10:$H$43,8)>ROUND(H32,8))*1)+1} -> 23 | T32: =R32-S32 -> -7
B33: ASIA | C33: Philippines | D33: GP1 | E33: 43 | F33: 43 | G33: 0 | H33: 93.023256 | I33: 89.767442 | J33: 3.255814 | K33: =IF(ISNUMBER(MATCH($C33, $V:$V, 0)), 0, IFERROR(AVERAGEIFS(PLP_BUSINESS!X:X, PLP_BUSINESS!$B:$B, 'Summary (최종)'!$C33, PLP_BUSINESS!$H:$H, "Y"),0)) -> 14.883721 | L33: =IF(ISNUMBER(MATCH($C33, $V:$V, 0)), 0, IFERROR(AVERAGEIFS(PLP_BUSINESS!Y:Y, PLP_BUSINESS!$B:$B, 'Summary (최종)'!$C33, PLP_BUSINESS!$H:$H, "Y"),0)) -> 18.139535 | M33: =IF(ISNUMBER(MATCH($C33, $V:$V, 0)), 0, IFERROR(AVERAGEIFS(PLP_BUSINESS!Z:Z, PLP_BUSINESS!$B:$B, 'Summary (최종)'!$C33, PLP_BUSINESS!$H:$H, "Y"),0)) -> 15 | N33: =IF(ISNUMBER(MATCH($C33, $V:$V, 0)), 0, IFERROR(AVERAGEIFS(PLP_BUSINESS!AA:AA, PLP_BUSINESS!$B:$B, 'Summary (최종)'!$C33, PLP_BUSINESS!$H:$H, "Y"),0)) -> 15 | O33: =IF(ISNUMBER(MATCH($C33, $V:$V, 0)), 0, IFERROR(AVERAGEIFS(PLP_BUSINESS!AB:AB, PLP_BUSINESS!$B:$B, 'Summary (최종)'!$C33, PLP_BUSINESS!$H:$H, "Y"),0)) -> 15 | P33: =IFERROR(HLOOKUP($C33,'Product Category'!$E$7:$AS$68,62,0), 0) -> 15 | Q33: =IF(ISNUMBER(MATCH(C33,W:W,0)), NA(),_xlfn.XLOOKUP(C33,Blog!C:C,Blog!G:G,0)) -> 0 | R33: {=SUMPRODUCT((ROUND($I$10:$I$43,8)>ROUND(I33,8))*1)+1} -> 21 | S33: {=SUMPRODUCT((ROUND($H$10:$H$43,8)>ROUND(H33,8))*1)+1} -> 24 | T33: =R33-S33 -> -3
B34: LATAM | C34: Argentina | D34: 5.0 | E34: 51 | F34: 51 | G34: 0 | H34: 89.411765 | I34: 99.411765 | J34: -10 | K34: =IF(ISNUMBER(MATCH($C34, $V:$V, 0)), 0, IFERROR(AVERAGEIFS(PLP_BUSINESS!X:X, PLP_BUSINESS!$B:$B, 'Summary (최종)'!$C34, PLP_BUSINESS!$H:$H, "Y"),0)) -> 15.686275 | L34: =IF(ISNUMBER(MATCH($C34, $V:$V, 0)), 0, IFERROR(AVERAGEIFS(PLP_BUSINESS!Y:Y, PLP_BUSINESS!$B:$B, 'Summary (최종)'!$C34, PLP_BUSINESS!$H:$H, "Y"),0)) -> 19.607843 | M34: =IF(ISNUMBER(MATCH($C34, $V:$V, 0)), 0, IFERROR(AVERAGEIFS(PLP_BUSINESS!Z:Z, PLP_BUSINESS!$B:$B, 'Summary (최종)'!$C34, PLP_BUSINESS!$H:$H, "Y"),0)) -> 11.176471 | N34: =IF(ISNUMBER(MATCH($C34, $V:$V, 0)), 0, IFERROR(AVERAGEIFS(PLP_BUSINESS!AA:AA, PLP_BUSINESS!$B:$B, 'Summary (최종)'!$C34, PLP_BUSINESS!$H:$H, "Y"),0)) -> 14.705882 | O34: =IF(ISNUMBER(MATCH($C34, $V:$V, 0)), 0, IFERROR(AVERAGEIFS(PLP_BUSINESS!AB:AB, PLP_BUSINESS!$B:$B, 'Summary (최종)'!$C34, PLP_BUSINESS!$H:$H, "Y"),0)) -> 13.235294 | P34: =IFERROR(HLOOKUP($C34,'Product Category'!$E$7:$AS$68,62,0), 0) -> 15 | Q34: =IF(ISNUMBER(MATCH(C34,W:W,0)), NA(),_xlfn.XLOOKUP(C34,Blog!C:C,Blog!G:G,0)) -> 0 | R34: {=SUMPRODUCT((ROUND($I$10:$I$43,8)>ROUND(I34,8))*1)+1} -> 9 | S34: {=SUMPRODUCT((ROUND($H$10:$H$43,8)>ROUND(H34,8))*1)+1} -> 25 | T34: =R34-S34 -> -16
B35: MEA | C35: SouthAfrica | D35: GP1 | E35: 33 | F35: 33 | G35: 0 | H35: 88.939394 | I35: 88.939394 | J35: 0 | K35: =IF(ISNUMBER(MATCH($C35, $V:$V, 0)), 0, IFERROR(AVERAGEIFS(PLP_BUSINESS!X:X, PLP_BUSINESS!$B:$B, 'Summary (최종)'!$C35, PLP_BUSINESS!$H:$H, "Y"),0)) -> 13.939394 | L35: =IF(ISNUMBER(MATCH($C35, $V:$V, 0)), 0, IFERROR(AVERAGEIFS(PLP_BUSINESS!Y:Y, PLP_BUSINESS!$B:$B, 'Summary (최종)'!$C35, PLP_BUSINESS!$H:$H, "Y"),0)) -> 16.363636 | M35: =IF(ISNUMBER(MATCH($C35, $V:$V, 0)), 0, IFERROR(AVERAGEIFS(PLP_BUSINESS!Z:Z, PLP_BUSINESS!$B:$B, 'Summary (최종)'!$C35, PLP_BUSINESS!$H:$H, "Y"),0)) -> 13.636364 | N35: =IF(ISNUMBER(MATCH($C35, $V:$V, 0)), 0, IFERROR(AVERAGEIFS(PLP_BUSINESS!AA:AA, PLP_BUSINESS!$B:$B, 'Summary (최종)'!$C35, PLP_BUSINESS!$H:$H, "Y"),0)) -> 15 | O35: =IF(ISNUMBER(MATCH($C35, $V:$V, 0)), 0, IFERROR(AVERAGEIFS(PLP_BUSINESS!AB:AB, PLP_BUSINESS!$B:$B, 'Summary (최종)'!$C35, PLP_BUSINESS!$H:$H, "Y"),0)) -> 15 | P35: =IFERROR(HLOOKUP($C35,'Product Category'!$E$7:$AS$68,62,0), 0) -> 15 | Q35: =IF(ISNUMBER(MATCH(C35,W:W,0)), NA(),_xlfn.XLOOKUP(C35,Blog!C:C,Blog!G:G,0)) -> 0 | R35: {=SUMPRODUCT((ROUND($I$10:$I$43,8)>ROUND(I35,8))*1)+1} -> 22 | S35: {=SUMPRODUCT((ROUND($H$10:$H$43,8)>ROUND(H35,8))*1)+1} -> 26 | T35: =R35-S35 -> -4
B36: MEA | C36: Algeria | D36: 5.0 | E36: 32 | F36: 32 | G36: 0 | H36: 87.8125 | I36: 87.8125 | J36: 0 | K36: =IF(ISNUMBER(MATCH($C36, $V:$V, 0)), 0, IFERROR(AVERAGEIFS(PLP_BUSINESS!X:X, PLP_BUSINESS!$B:$B, 'Summary (최종)'!$C36, PLP_BUSINESS!$H:$H, "Y"),0)) -> 18.125 | L36: =IF(ISNUMBER(MATCH($C36, $V:$V, 0)), 0, IFERROR(AVERAGEIFS(PLP_BUSINESS!Y:Y, PLP_BUSINESS!$B:$B, 'Summary (최종)'!$C36, PLP_BUSINESS!$H:$H, "Y"),0)) -> 17.5 | M36: =IF(ISNUMBER(MATCH($C36, $V:$V, 0)), 0, IFERROR(AVERAGEIFS(PLP_BUSINESS!Z:Z, PLP_BUSINESS!$B:$B, 'Summary (최종)'!$C36, PLP_BUSINESS!$H:$H, "Y"),0)) -> 13.59375 | N36: =IF(ISNUMBER(MATCH($C36, $V:$V, 0)), 0, IFERROR(AVERAGEIFS(PLP_BUSINESS!AA:AA, PLP_BUSINESS!$B:$B, 'Summary (최종)'!$C36, PLP_BUSINESS!$H:$H, "Y"),0)) -> 14.53125 | O36: =IF(ISNUMBER(MATCH($C36, $V:$V, 0)), 0, IFERROR(AVERAGEIFS(PLP_BUSINESS!AB:AB, PLP_BUSINESS!$B:$B, 'Summary (최종)'!$C36, PLP_BUSINESS!$H:$H, "Y"),0)) -> 14.0625 | P36: =IFERROR(HLOOKUP($C36,'Product Category'!$E$7:$AS$68,62,0), 0) -> 10 | Q36: =IF(ISNUMBER(MATCH(C36,W:W,0)), NA(),_xlfn.XLOOKUP(C36,Blog!C:C,Blog!G:G,0)) -> #N/A | R36: {=SUMPRODUCT((ROUND($I$10:$I$43,8)>ROUND(I36,8))*1)+1} -> 23 | S36: {=SUMPRODUCT((ROUND($H$10:$H$43,8)>ROUND(H36,8))*1)+1} -> 27 | T36: =R36-S36 -> -4
B37: MEA | C37: Egypt | D37: GP1 | E37: 124 | F37: 124 | G37: 0 | H37: 85.846774 | I37: 85.725806 | J37: 0.12096774 | K37: =IF(ISNUMBER(MATCH($C37, $V:$V, 0)), 0, IFERROR(AVERAGEIFS(PLP_BUSINESS!X:X, PLP_BUSINESS!$B:$B, 'Summary (최종)'!$C37, PLP_BUSINESS!$H:$H, "Y"),0)) -> 13.387097 | L37: =IF(ISNUMBER(MATCH($C37, $V:$V, 0)), 0, IFERROR(AVERAGEIFS(PLP_BUSINESS!Y:Y, PLP_BUSINESS!$B:$B, 'Summary (최종)'!$C37, PLP_BUSINESS!$H:$H, "Y"),0)) -> 13.548387 | M37: =IF(ISNUMBER(MATCH($C37, $V:$V, 0)), 0, IFERROR(AVERAGEIFS(PLP_BUSINESS!Z:Z, PLP_BUSINESS!$B:$B, 'Summary (최종)'!$C37, PLP_BUSINESS!$H:$H, "Y"),0)) -> 14.032258 | N37: =IF(ISNUMBER(MATCH($C37, $V:$V, 0)), 0, IFERROR(AVERAGEIFS(PLP_BUSINESS!AA:AA, PLP_BUSINESS!$B:$B, 'Summary (최종)'!$C37, PLP_BUSINESS!$H:$H, "Y"),0)) -> 14.879032 | O37: =IF(ISNUMBER(MATCH($C37, $V:$V, 0)), 0, IFERROR(AVERAGEIFS(PLP_BUSINESS!AB:AB, PLP_BUSINESS!$B:$B, 'Summary (최종)'!$C37, PLP_BUSINESS!$H:$H, "Y"),0)) -> 15 | P37: =IFERROR(HLOOKUP($C37,'Product Category'!$E$7:$AS$68,62,0), 0) -> 15 | Q37: =IF(ISNUMBER(MATCH(C37,W:W,0)), NA(),_xlfn.XLOOKUP(C37,Blog!C:C,Blog!G:G,0)) -> 0 | R37: {=SUMPRODUCT((ROUND($I$10:$I$43,8)>ROUND(I37,8))*1)+1} -> 26 | S37: {=SUMPRODUCT((ROUND($H$10:$H$43,8)>ROUND(H37,8))*1)+1} -> 28 | T37: =R37-S37 -> -2
... B43: EU | C43: Greece | D43: 5.0 | E43: 29 | F43: 29 | G43: 0 | H43: 70.517241 | I43: 70.517241 | J43: 0 | K43: =IF(ISNUMBER(MATCH($C43, $V:$V, 0)), 0, IFERROR(AVERAGEIFS(PLP_BUSINESS!X:X, PLP_BUSINESS!$B:$B, 'Summary (최종)'!$C43, PLP_BUSINESS!$H:$H, "Y"),0)) -> 8.2758621 | L43: =IF(ISNUMBER(MATCH($C43, $V:$V, 0)), 0, IFERROR(AVERAGEIFS(PLP_BUSINESS!Y:Y, PLP_BUSINESS!$B:$B, 'Summary (최종)'!$C43, PLP_BUSINESS!$H:$H, "Y"),0)) -> 13.103448 | M43: =IF(ISNUMBER(MATCH($C43, $V:$V, 0)), 0, IFERROR(AVERAGEIFS(PLP_BUSINESS!Z:Z, PLP_BUSINESS!$B:$B, 'Summary (최종)'!$C43, PLP_BUSINESS!$H:$H, "Y"),0)) -> 10.862069 | N43: =IF(ISNUMBER(MATCH($C43, $V:$V, 0)), 0, IFERROR(AVERAGEIFS(PLP_BUSINESS!AA:AA, PLP_BUSINESS!$B:$B, 'Summary (최종)'!$C43, PLP_BUSINESS!$H:$H, "Y"),0)) -> 15 | O43: =IF(ISNUMBER(MATCH($C43, $V:$V, 0)), 0, IFERROR(AVERAGEIFS(PLP_BUSINESS!AB:AB, PLP_BUSINESS!$B:$B, 'Summary (최종)'!$C43, PLP_BUSINESS!$H:$H, "Y"),0)) -> 8.2758621 | P43: =IFERROR(HLOOKUP($C43,'Product Category'!$E$7:$AS$68,62,0), 0) -> 15 | Q43: =IF(ISNUMBER(MATCH(C43,W:W,0)), NA(),_xlfn.XLOOKUP(C43,Blog!C:C,Blog!G:G,0)) -> 0 | R43: {=SUMPRODUCT((ROUND($I$10:$I$43,8)>ROUND(I43,8))*1)+1} -> 33 | S43: {=SUMPRODUCT((ROUND($H$10:$H$43,8)>ROUND(H43,8))*1)+1} -> 34 | T43: =R43-S43 -> -1

Sheet Monitoring Detail

Sheet Checklist & Criteria
B2: LG.com Contents Monitoring Detail Information
L3: 2025.10.16
B4: Category | C4: Checklist | D4: Scoring Criteria | J4: Improvement Guide
D5: Criteria | E5: Score Table | J5: Criteria Area | L5: Improvement Guide
E6: All conditions must be met to receive Full Points
B7: SEO Tag | C7: 1) Check <Title> | D7: 1) Follow Character Limit * Character Limit - Title Tag length is 40 ~ 60 characters : 20 Points - Less than 40 or over 60 characters : 0 Points *Character limit for 2byte character countries is 5 ~ 40 characters : HongKong(zh), Japan, Taiwan | E7: Type | F7: 1) Character Limit | I7: Total Score | K7: [Pass Case] | L7: - Follow Character Limit - Refer to the 'Meta tag guideline' shared by HQ
E8: Basic | F8: Pass | I8: 20
F9: Fail | I9: 0
E10: 2bytes | F10: Pass | I10: 20
F11: Fail | I11: 0
C12: 2) Check <Description> | D12: 1) Follow Character Limit * Character Limit - Description Tag length is 60 ~ 160 characters : 20 Points - Less than 60 or over 160 characters : 0 Points *Character limit for 2byte character countries is 40 ~ 90 characters : HongKong(zh), Japan, Taiwan | E12: Type | F12: 1) Character Limit | I12: Total Score | K12: [Pass Case] | L12: - Follow Character Limit - Refer to the 'Meta tag guideline' shared by HQ
E13: basic | F13: Pass | I13: 20
F14: Fail | I14: 0
E15: 2bytes | F15: Pass | I15: 20
F16: Fail | I16: 0
C17: 3) Check <H1> | D17: 1) Use H1 tag only for PLP titles | E17: Type | F17: 1) Should only be used for PLP title | I17: Total Score | K17: [Pass Case] | L17: - Avoid using multiple H1 Tags and use only for PLP title Refer to the 'Meta tag guideline' shared by HQ
D18: * There should only be one H1 tag in a page | E18: All | F18: Pass | I18: 15
F19: Fail | I19: 0
C20: 4) Check <Canonical Link> | D20: 1) Canonical Link or Redirect Link have the same URL or main tags Information as PDP | E20: Type | F20: 1) 'Canonical Link' or 'Redirect Link' and 'PDP' have the same URL | I20: Total Score | K20: [Pass Case] | L20: - Fill the same information as the current PLP URL
D21: * If the main tags of the 'canonical link' or 'redirect link page' and 'PDP' are same, it is pass even if the URLs are different | E21: All | F21: Pass | I21: 15
D22: - main tag : <title>, <description>, <UFN> | F22: Fail | I22: 0
C23: 5) Check <Alt Text> of Feature Cards | D23: 1) Follow Character Limit * Character Limit - Alt Text length is 1 ~ 125 characters : 15 Points - Alt Text is not set (length is 0) : 0 Points - Alt Text length over 125 characters : 0 Points * Feature Cards with alt text character limit errors are listed in "PLP_BUSINESS" Sheet - only fail case are listed. Pass case are not listed - If there is more than two fail cases, the alt texts are listed with comma * In the S column, the number of feature cards that needs to be fixied among all feature cards is displayed in the format of [Number of feature cards requiring modification]/[Total number of feature cards] | E23: Type | F23: 1) Character Limit | I23: Total Score | K23: [Pass Case] | L23: - Follow Character Limit Refer to the 'Meta tag guideline' shared by HQ
E24: All | F24: Pass | I24: 15
F25: Fail | I25: 0
B26: Category | C26: 6) Check Product Category Page Upload Status | D26: 1) Product Category Page is uploaded * Refer to the 'Product Category' sheet | E26: Type | F26: 1) Product Category Page is uploaded | I26: Total Score
E27: All | F27: Uploaded | I27: 15
F28: Uploaded more than 90% | I28: 10
F29: Not Uploaded | I29: 0
B30: Blog | C30: 7) Latest Blog Update (Additional 10 points) | D30: 1) 10 points if article is uploaded during 3 months prior to the reporting month * Scores exceeding 100 (including Blog score) will be adjusted to 100 | E30: Type | F30: 1) Article is uploaded during 3 months prior to the reporting month | I30: Total Score
E31: All | F31: Uploaded | I31: 10
F32: Not Uploaded | I32: 0

Sheet PLP_BUSINESS
J1: Tag <Title> | L1: Tag <Description> | N1: Tag <H1> | Q1: Tag <Canonical Link> | T1: Tag <Alt text>_(Front Image) | W1: Scoring
A2: Region | B2: Country | C2: Locale | D2: Page Type | E2: CAT/PLP | F2: GNB | G2: GNB ENG Trans | H2: Scoring Y/N | I2: URL | J2: Title Tag Text | K2: Length of title tag | L2: Description Tag | M2: Length of Description tag | N2: All H1 | O2: # of H1 tag | P2: H1 tag P/F | Q2: Canonical Link Tag | R2: Redirect Link | S2: Redirect Link P/F | T2: Issue / TTL * of Feature Cards | U2: Fail case of Alt text | V2: Length of Alt text | W2: Total Score | X2: Title Tag Score | Y2: Description Tag Score | Z2: H1 Tag Score | AA2: Canonical Link Score | AB2: Feature Alt Score
A3: MEA | B3: UAE | C3: AE : AE (en) | D3: 5.0 | E3: PLP | F3: Absorption Chiller Direct Fired Type | G3: Absorption Chiller Direct Fired Type | H3: Y | I3: https://www.lg.com/ae/business/hvac/commercial-solutions/chiller/absorption-chiller-direct-fired-type | J3: Absorption Chiller Direct Fired - HVAC | Business | LG UAE | K3: 58 | L3: LG Absorption Chiller Direct Fired Type employs water as a refrigerant, optimizing energy use and maximizing installation convenience with its parts partition. | M3: 159 | N3: ['Absorption Chiller Direct Fired Type'] | O3: 1 | P3: Pass | Q3: https://www.lg.com/ae/business/hvac/commercial-solutions/chiller/absorption-chiller-direct-fired-type | S3: Pass | T3: 0% | U3: ['pass'] | V3: [] | W3: 85 | X3: 20 | Y3: 20 | Z3: 15 | AA3: 15 | AB3: 15
A4: MEA | B4: UAE | C4: AE : AE (en) | D4: 5.0 | E4: PLP | F4: Absorption Chiller Hot Water Type | G4: Absorption Chiller Hot Water Type | H4: Y | I4: https://www.lg.com/ae/business/hvac/commercial-solutions/chiller/absorption-chiller-hot-water-type | J4: Absorption Chiller Hot Water - HVAC | Business | LG UAE | K4: 55 | L4: LG Absorption Chiller Hot Water Type offers an eco-friendly cooling and heating solution by utilizing wastewater from nearby factories or power plants. | M4: 151 | N4: ['Absorption Chiller Hot Water Type'] | O4: 1 | P4: Pass | Q4: https://www.lg.com/ae/business/hvac/commercial-solutions/chiller/absorption-chiller-hot-water-type | S4: Pass | T4: 0% | U4: ['pass'] | V4: [] | W4: 85 | X4: 20 | Y4: 20 | Z4: 15 | AA4: 15 | AB4: 15
A5: MEA | B5: UAE | C5: AE : AE (en) | D5: 5.0 | E5: PLP | F5: Absorption Chiller Steam Type | G5: Absorption Chiller Steam Type | H5: Y | I5: https://www.lg.com/ae/business/hvac/commercial-solutions/chiller/absorption-chiller-steam-type | J5: Absorption Chiller Steam - HVAC | Business | LG UAE | K5: 51 | L5: LG Absorption Chiller Steam Type maintains steady, eco-friendly performance in power-short areas by leveraging various thermal heat sources. | M5: 140 | N5: ['Absorption Chiller Steam Type'] | O5: 1 | P5: Pass | Q5: https://www.lg.com/ae/business/hvac/commercial-solutions/chiller/absorption-chiller-steam-type | S5: Pass | T5: 0% | U5: ['pass'] | V5: [] | W5: 85 | X5: 20 | Y5: 20 | Z5: 15 | AA5: 15 | AB5: 15
A6: MEA | B6: UAE | C6: AE : AE (en) | D6: 5.0 | E6: PLP | F6: Air Cooled Inverter Scroll Chiller | G6: Air Cooled Inverter Scroll Chiller | H6: Y | I6: https://www.lg.com/ae/business/hvac/commercial-solutions/chiller/air-cooled-inverter-scroll-chiller | J6: Air Cooled Inverter Scroll Chiller - HVAC| Business | LG UAE | K6: 60 | L6: LG Inverter Scroll Chiller delivers efficient heating, a wide operational range, and optimal refrigerant control via its twin inverter compressor. | M6: 146 | N6: ['Inverter Scroll Chiller'] | O6: 1 | P6: Pass | Q6: https://www.lg.com/ae/business/hvac/commercial-solutions/chiller/air-cooled-inverter-scroll-chiller | S6: Pass | T6: 0% | U6: ['pass'] | V6: [] | W6: 85 | X6: 20 | Y6: 20 | Z6: 15 | AA6: 15 | AB6: 15
A7: MEA | B7: UAE | C7: AE : AE (en) | D7: 5.0 | E7: PLP | F7: Air Cooled Screw Chiller | G7: Air Cooled Screw Chiller | H7: Y | I7: https://www.lg.com/ae/business/hvac/commercial-solutions/chiller/air-cooled-screw-chiller | J7: Air Cooled Screw Chiller - HVAC | Business | LG UAE | K7: 51 | L7: LG Air-cooled Screw Chiller maximizes heat transfer with its corrosion-resistant heat exchanger, accentuated by a gold-colored coated fin. | M7: 138 | N7: ['Air-cooled Screw Chiller'] | O7: 1 | P7: Pass | Q7: https://www.lg.com/ae/business/hvac/commercial-solutions/chiller/air-cooled-screw-chiller | S7: Pass | T7: 0% | U7: ['pass'] | V7: [] | W7: 85 | X7: 20 | Y7: 20 | Z7: 15 | AA7: 15 | AB7: 15
A8: MEA | B8: UAE | C8: AE : AE (en) | D8: 5.0 | E8: PLP | F8: Air Handling Unit | G8: Air Handling Unit | H8: Y | I8: https://www.lg.com/ae/business/hvac/commercial-solutions/vrf-system/integrated-unit/air-handling-unit | J8: Air Handling Unit - VRF System - HVAC | Business | LG UAE | K8: 57 | L8: LG Air Handling Unit (AHU) ensures efficient, comfortable air solutions all year round, courtesy of its high expandability. | M8: 123 | N8: ['Air Handling Unit (AHU)'] | O8: 1 | P8: Pass | Q8: https://www.lg.com/ae/business/hvac/commercial-solutions/vrf-system/integrated-unit/air-handling-unit | S8: Pass | T8: 0% | U8: ['pass'] | V8: [] | W8: 85 | X8: 20 | Y8: 20 | Z8: 15 | AA8: 15 | AB8: 15
A9: MEA | B9: UAE | C9: AE : AE (en) | D9: 5.0 | E9: PLP | F9: Air to Water Heat Pumps | G9: Air to Water Heat Pumps | H9: Y | I9: https://www.lg.com/ae/business/hvac/residential-solutions/air-to-water-heat-pumps | J9: Heating Solution (AWHP) - HVAC | Business | LG UAE | K9: 50 | L9: LG Air to Water Heat Pump, THERMA V, Sustainable solution providing heating, cooling & hot water for comfort, replacing gas boilers with renewable technology. | M9: 158 | N9: ['Heating Solution (AWHP)'] | O9: 1 | P9: Pass | Q9: https://www.lg.com/ae/business/hvac/residential-solutions/air-to-water-heat-pumps | S9: Pass | T9: 0% | U9: ['pass'] | V9: [] | W9: 85 | X9: 20 | Y9: 20 | Z9: 15 | AA9: 15 | AB9: 15
A10: MEA | B10: UAE | C10: AE : AE (en) | D10: 5.0 | E10: PLP | F10: Application Controller | G10: Application Controller | H10: Y | I10: https://www.lg.com/ae/business/hvac/control-solutions/application-controller | J10: Application Controller - HVAC | Business | LG UAE | K10: 49 | L10: The LG HVAC Application Controller manages building systems for enhanced comfort, featuring flexible integration, energy monitoring, and AHU control. | M10: 149 | N10: ['Application Controller'] | O10: 1 | P10: Pass | Q10: https://www.lg.com/ae/business/hvac/control-solutions/application-controller | S10: Pass | T10: 0% | U10: ['pass'] | V10: [] | W10: 85 | X10: 20 | Y10: 20 | Z10: 15 | AA10: 15 | AB10: 15
A11: MEA | B11: UAE | C11: AE : AE (en) | D11: 5.0 | E11: PLP | F11: COMMERCIAL SOLUTIONS | G11: COMMERCIAL SOLUTIONS | H11: N | I11: https://www.lg.com/ae/business/hvac/commercial-solutions | J11: Commercial Solutions - HVAC | Business | LG UAE | K11: 47 | L11: LG HVAC Commercial Solutions increase your space's value with green energy technologies. Find out more powerful performance and smart management feature of it on our website. | M11: 174 | N11: ['Commercial Solutions'] | O11: 1 | P11: Pass | Q11: https://www.lg.com/ae/business/hvac/commercial-solutions | S11: Pass | T11: 83% | U11: ['Five system perks: energy control, fresh office air, LEED certification solutions, easy building link link, and eco-friendliness reducing costs.', 'LG air conditioner models horizontally showcased to the left and building icons to the right. Central control device links the building and air conditioners.', 'An outdoor unit of MULTI V i standing on a rooftop of a builing. 45 degree right side of LEED certification displayed to the right.', 'Five features in hotel: Public facilities, swimming and shower room, guest room, lobby and reception hall in hotel, smart central control system.', 'A ceiling concealed duct supplying blue-colored air current in a hotel room with brown toned walls and a queen bed covered with white beddings.', 'A restaurant, public lounge and gym in hotel displayed side by side featuring blue-colored air current coming from LG air conditioning indoor units.', 'Five customer cases: Showrooms, large restaurants, stylish coffee shops, limited space clothing stores, restaurants with hot water washing.', 'Air conditioning unit on the ceiling creates blue air streams in a restaurant with multiple tables and chairs. Enlarged product image to the left.', 'Smart 4 way cassette with human detect sensor adjusts air direction to two people walking in a vehicle showroom. Enlarged product image to the right.', 'MULTI V S creating cool air stream in a large cafeteria with arrays of tables and sofas. Enlarged image of hands washing lettuce with water in a sink.', "MUlTI V M mounted on the ceiling of a store with men's apparels displayed. Blurred image of an outdoor unit connected with an indoor unit in the store.", 'Clothing store, accessory shop and a café displayed side by side. Three distinct indoor units on the ceiling create blue air streams in each picture.', 'Ceiling concealed ducts supply blue-colored air stream in a large three-storied atrium building with multiple indoor stores and long escalators.', "An operating room with white walls featuring patient's bed, multiple medical devices connected via electric cables and monitors with black screen.", 'Three ceiling mounted air conditions create blue-colored air stream in a waiting room in hospital with a series of chairs and a reception desk to the right.', 'Ceiling cassette type air condition unit dispenses blue-colored air current in an office featuring monotone desks and chairs with a meeting room to the right .', 'A ceiling concealed duct supplying blue-colored air current in a large hotel lobby with high ceiling, tall brown pillars and ivory-toned sofas.', 'Three round cassette units creating cool air currents in a café decorated with antique tables, chairs and lights. Enlarged product image to the right.', 'Ceiling mounted units create blue-colored air streams in a cafeteria with arrays of tables and chairs. Round lamps above each seat hanging from the ceiling.', 'Ceiling mounted unit creates air streams in a patient room with three beds and curtains. Three separate components at the top display air filtering process.'] | V11: [144, 157, 131, 145, 143, 148, 139, 146, 149, 150, 151, 149, 144, 146, 156, 159, 143, 150, 156, 156] | W11: 50 | X11: 20 | Y11: 0 | Z11: 15 | AA11: 15 | AB11: 0
A12: MEA | B12: UAE | C12: AE : AE (en) | D12: 5.0 | E12: PLP | F12: CONTROL SOLUTIONS | G12: CONTROL SOLUTIONS | H12: Y | I12: https://www.lg.com/ae/business/hvac/control-solutions | J12: Control Solutions - HVAC | Business | LG UAE | K12: 44 | L12: LG HVAC Control Solutions offer an array of convenient controls, allowing you to set the perfect temperature for your business environment. | M12: 139 | N12: ['Control Solutions'] | O12: 1 | P12: Pass | Q12: https://www.lg.com/ae/business/hvac/control-solutions | S12: Pass | T12: 0% | U12: ['pass'] | V12: [] | W12: 85 | X12: 20 | Y12: 20 | Z12: 15 | AA12: 15 | AB12: 15
A13: MEA | B13: UAE | C13: AE : AE (en) | D13: 5.0 | E13: PLP | F13: Case Study | G13: Case Study | H13: N | I13: https://www.lg.com/ae/business/hvac/case-study | J13: Case Study - Technical Insights - HVAC | Business | LG UAE | K13: 58 | L13: Discover various LG HVAC case study all around the world and all around the industry. | M13: 85 | N13: ['CASE STUDY'] | O13: 1 | P13: Pass | Q13: https://www.lg.com/ae/business/hvac-case-study | R13: https://www.lg.com/ae/business/hvac/case-study | S13: Fail | T13: 0% | U13: ['pass'] | V13: [] | W13: 85 | X13: 20 | Y13: 20 | Z13: 15 | AA13: 15 | AB13: 15
A14: MEA | B14: UAE | C14: AE : AE (en) | D14: 5.0 | E14: PLP | F14: Ceiling Concealed Duct | G14: Ceiling Concealed Duct | H14: Y | I14: https://www.lg.com/ae/business/hvac/commercial-solutions/vrf-system/indoor-unit/ceiling-concealed-duct | J14: Ceiling Concealed Duct - VRF - HVAC | Business | LG UAE | K14: 55 | L14: LG Ceiling Concealed Duct provides smart and optimized cooling and heating solutions to a variety of spaces. | M14: 108 | N14: ['Ceiling Concealed Duct'] | O14: 1 | P14: Pass | Q14: https://www.lg.com/ae/business/hvac/commercial-solutions/vrf-system/indoor-unit/ceiling-concealed-duct | S14: Pass | T14: 0% | U14: ['pass'] | V14: [] | W14: 85 | X14: 20 | Y14: 20 | Z14: 15 | AA14: 15 | AB14: 15
A15: MEA | B15: UAE | C15: AE : AE (en) | D15: 5.0 | E15: PLP | F15: Ceiling Concealed Duct | G15: Ceiling Concealed Duct | H15: Y | I15: https://www.lg.com/ae/business/hvac/residential-solutions/single-split/ceiling-concealed-duct | J15: Ceiling Concealed Duct - Single S - HVAC | Business | LG UAE | K15: 60 | L15: LG Ceiling Concealed Duct provides smart and optimized cooling and heating solutions to a variety of spaces. | M15: 108 | N15: ['Ceiling Concealed Duct'] | O15: 1 | P15: Pass | Q15: https://www.lg.com/ae/business/hvac/residential-solutions/single-split/ceiling-concealed-duct | S15: Pass | T15: 0% | U15: ['pass'] | V15: [] | W15: 85 | X15: 20 | Y15: 20 | Z15: 15 | AA15: 15 | AB15: 15
A16: MEA | B16: UAE | C16: AE : AE (en) | D16: 5.0 | E16: PLP | F16: Ceiling Mounted Cassette | G16: Ceiling Mounted Cassette | H16: Y | I16: https://www.lg.com/ae/business/hvac/commercial-solutions/vrf-system/indoor-unit/ceiling-mounted-cassette | J16: Ceiling Mounted Cassette - VRF - HVAC | Business | LG UAE | K16: 57 | L16: LG Ceiling Mounted Cassette fan coil unit(FCU) provides a comfortable environment purifying air for a fresher and healthier space. | M16: 130 | N16: ['Ceiling Mounted Cassette'] | O16: 1 | P16: Pass | Q16: https://www.lg.com/ae/business/hvac/commercial-solutions/vrf-system/indoor-unit/ceiling-mounted-cassette | S16: Pass | T16: 0% | U16: ['pass'] | V16: [] | W16: 85 | X16: 20 | Y16: 20 | Z16: 15 | AA16: 15 | AB16: 15
A17: MEA | B17: UAE | C17: AE : AE (en) | D17: 5.0 | E17: PLP | F17: Ceiling Mounted Cassette | G17: Ceiling Mounted Cassette | H17: Y | I17: https://www.lg.com/ae/business/hvac/residential-solutions/single-split/ceiling-mounted-cassette | J17: Ceiling Mounted Cassette - Split - HVAC | Business | LG UAE | K17: 59 | L17: LG Ceiling Mounted Cassette: a single split system with up/down swing and indirect airflow for enhanced comfort. Aesthetically pleasing and efficient. | M17: 150 | N17: ['Ceiling Mounted Cassette'] | O17: 1 | P17: Pass | Q17: https://www.lg.com/ae/business/hvac/residential-solutions/single-split/ceiling-mounted-cassette | S17: Pass | T17: 0% | U17: ['pass'] | V17: [] | W17: 85 | X17: 20 | Y17: 20 | Z17: 15 | AA17: 15 | AB17: 15
A18: MEA | B18: UAE | C18: AE : AE (en) | D18: 5.0 | E18: PLP | F18: Ceiling Suspended | G18: Ceiling Suspended | H18: Y | I18: https://www.lg.com/ae/business/hvac/residential-solutions/single-split/ceiling-suspended | J18: Ceiling Suspended - Single Split - HVAC | Business | LG UAE | K18: 59 | L18: LG Ceiling Suspended units offer a powerful and convenient cooling and heating solution, seamlessly integrating into any space with their award-winning design. | M18: 159 | N18: ['Ceiling Suspended'] | O18: 1 | P18: Pass | Q18: https://www.lg.com/ae/business/hvac/residential-solutions/single-split/ceiling-suspended | S18: Pass | T18: 0% | U18: ['pass'] | V18: [] | W18: 85 | X18: 20 | Y18: 20 | Z18: 15 | AA18: 15 | AB18: 15
A19: MEA | B19: UAE | C19: AE : AE (en) | D19: 5.0 | E19: PLP | F19: Ceiling Suspended Floor Convertible | G19: Ceiling Suspended Floor Convertible | H19: Y | I19: https://www.lg.com/ae/business/hvac/commercial-solutions/vrf-system/indoor-unit/ceiling-suspended-floor-convertible | J19: Ceiling Suspended & Floor Convertible, HVAC| LG UAE Business | K19: 60 | L19: LG Ceiling Suspended & Floor Convertible offers a powerful and convenient cooling and heating solution, seamlessly integrating into any space. | M19: 142 | N19: ['Ceiling Suspended & Floor Convertible'] | O19: 1 | P19: Pass | Q19: https://www.lg.com/ae/business/hvac/commercial-solutions/vrf-system/indoor-unit/ceiling-suspended-floor-convertible | S19: Pass | T19: 0% | U19: ['pass'] | V19: [] | W19: 85 | X19: 20 | Y19: 20 | Z19: 15 | AA19: 15 | AB19: 15
A20: MEA | B20: UAE | C20: AE : AE (en) | D20: 5.0 | E20: PLP | F20: Central Controller | G20: Central Controller | H20: Y | I20: https://www.lg.com/ae/business/hvac/control-solutions/central-controller | J20: Central Controller - HVAC | Business | LG UAE | K20: 45 | L20: The LG HVAC Central Controller offers advanced control solutions with models like the AC Manager 5 and ACP 5, optimizing building management. | M20: 141 | N20: ['Central Controller Line Up'] | O20: 1 | P20: Pass | Q20: https://www.lg.com/ae/business/hvac/control-solutions/central-controller | S20: Pass | T20: 0% | U20: ['pass'] | V20: [] | W20: 85 | X20: 20 | Y20: 20 | Z20: 15 | AA20: 15 | AB20: 15
A21: MEA | B21: UAE | C21: AE : AE (en) | D21: 5.0 | E21: PLP | F21: Centrifugal Chiller | G21: Centrifugal Chiller | H21: Y | I21: https://www.lg.com/ae/business/hvac/commercial-solutions/chiller/centrifugal-chiller | J21: Centrifugal Chiller - Chiller - HVAC | Business | LG UAE | K21: 56 | L21: LG Centrifugal Chiller offers stable operation and maximized energy efficiency through its two-stage compressor system. | M21: 119 | N21: ['Centrifugal Chiller'] | O21: 1 | P21: Pass | Q21: https://www.lg.com/ae/business/hvac/commercial-solutions/chiller/centrifugal-chiller | S21: Pass | T21: 0% | U21: ['pass'] | V21: [] | W21: 85 | X21: 20 | Y21: 20 | Z21: 15 | AA21: 15 | AB21: 15
A22: MEA | B22: UAE | C22: AE : AE (en) | D22: 5.0 | E22: PLP | F22: Chiller | G22: Chiller | H22: Y | I22: https://www.lg.com/ae/business/hvac/commercial-solutions/chiller | J22: Chiller -Commercial Solutions- HVAC | Business | LG UAE | K22: 55 | L22: LG Chiller offers powerful and ideal cooling solution for large buildings and industrial facilities. | M22: 100 | N22: ['Chiller'] | O22: 1 | P22: Pass | Q22: https://www.lg.com/ae/business/hvac/commercial-solutions/chiller | S22: Pass | T22: 0% | U22: ['pass'] | V22: [] | W22: 85 | X22: 20 | Y22: 20 | Z22: 15 | AA22: 15 | AB22: 15
A23: MEA | B23: UAE | C23: AE : AE (en) | D23: 5.0 | E23: PLP | F23: Chiller Annual Maintenance | G23: Chiller Annual Maintenance | H23: N | I23: https://www.lg.com/ae/business/hvac/service-maintenance/chiller-annual-maintenance | J23: Chiller Annual Maintenance - HVAC | Business | LG UAE | K23: 53 | L23: LG Chiller Annual Maintenance guarantees top-notch efficiency, damage prevention, and superior performance through surge analysis and prevention. | M23: 145 | N23: ['Keep Your Chiller Running Properly with Regular Maintenance'] | O23: 1 | P23: Pass | Q23: https://www.lg.com/ae/business/hvac/service-maintenance/chiller-annual-maintenance | S23: Pass | T23: 29% | U23: ['A substantial black-colored LG Chiller unit commands attention in a machine-filled room, its presence accentuated by gray-tone pipes.', 'LG Centrifugal Chiller unit, grey-toned assembly of circular and rectangular forms, adorned with red tags marking centrifugal, absorption, and screw.'] | V23: [133, 149] | W23: 70 | X23: 20 | Y23: 20 | Z23: 15 | AA23: 15 | AB23: 0
A24: MEA | B24: UAE | C24: AE : AE (en) | D24: 5.0 | E24: PLP | F24: Chiller Renewal Service | G24: Chiller Renewal Service | H24: N | I24: https://www.lg.com/ae/business/hvac/service-maintenance/chiller-renewal-service | J24: Chiller Renewal Service - HVAC | Business | LG UAE | K24: 50 | L24: LG Chiller Renewal Service provides meticulously optimizing chiller units and overhauling compressor parts for consistent efficiency and reliability. | M24: 149 | N24: ['Optimize Your Chiller with the Renewal Service'] | O24: 1 | P24: Pass | Q24: https://www.lg.com/ae/business/hvac/service-maintenance/chiller-renewal-service | S24: Pass | T24: 17% | U24: ['LG Centrifugal Chiller unit, grey-toned assembly of circular and rectangular forms, adorned with red tags marking centrifugal, absorption, and screw.', 'A substantial gray-toned LG Chiller unit commands attention in a machine-filled room, its presence accentuated by green/blue pipes.'] | V24: [149, 131] | W24: 70 | X24: 20 | Y24: 20 | Z24: 15 | AA24: 15 | AB24: 0
A25: MEA | B25: UAE | C25: AE : AE (en) | D25: 5.0 | E25: PLP | F25: Commercial ERV (Ventilation) | G25: Commercial ERV (Ventilation) | H25: Y | I25: https://www.lg.com/ae/business/hvac/commercial-solutions/commercial-erv-ventilation | J25: Commercial ERV Ventilation - HVAC | Business | LG UAE | K25: 53 | L25: LG Commercial ERV Ventilation ensures efficient, clean indoor air using diverse energy-saving technologies like heat exchangers and a multi-filter system. | M25: 154 | N25: ['Ceiling Suspended & Floor Convertible'] | O25: 1 | P25: Pass | Q25: https://www.lg.com/ae/business/hvac/commercial-solutions/commercial-erv-ventilation | S25: Pass | T25: 0% | U25: ['pass'] | V25: [] | W25: 85 | X25: 20 | Y25: 20 | Z25: 15 | AA25: 15 | AB25: 15
... A27: MEA | B27: UAE | C27: AE : AE (en) | D27: 5.0 | E27: PLP | F27: Console | G27: Console | H27: Y | I27: https://www.lg.com/ae/business/hvac/residential-solutions/single-split/console | J27: Console - Single Split - HVAC | Business | LG UAE | K27: 49 | L27: LG Console delivers a healthier, optimized airflow into a room, offering flexible flow direction through an adjustable vane. | M27: 124 | N27: ['Console'] | O27: 1 | P27: Pass | Q27: https://www.lg.com/ae/business/hvac/residential-solutions/single-split/console | S27: Pass | T27: 0% | U27: ['pass'] | V27: [] | W27: 85 | X27: 20 | Y27: 20 | Z27: 15 | AA27: 15 | AB27: 15
A28: MEA | B28: UAE | C28: AE : AE (en) | D28: 5.0 | E28: PLP | F28: Consultant | G28: Consultant | H28: N | I28: https://www.lg.com/ae/business/hvac/consultant | J28: Consultant - HVAC | Business | LG UAE | K28: 37 | L28: LG HVAC offers a variety of technical data, tools, software, and the right technologies to make consultants' HVAC designs more efficient and successful. | M28: 152 | N28: ['Bringing the Optimal Design for Your HVAC Projects'] | O28: 1 | P28: Pass | Q28: https://www.lg.com/ae/business/air-solution/consultant | R28: https://www.lg.com/ae/business/hvac/consultant | S28: Fail | T28: 12% | U28: ['A man dressed in a white shirt and a hard hat is observed studying a blueprint, with gray buildings visible in the background.', 'LG HVAC solutions are arranged vertically within the confines of barbed wire, while lush green trees and grass flourish on the right side outside the perimeter.'] | V28: [126, 160] | W28: 50 | X28: 0 | Y28: 20 | Z28: 15 | AA28: 15 | AB28: 0
A29: MEA | B29: UAE | C29: AE : AE (en) | D29: 5.0 | E29: PLP | F29: ENGINEERING SUPPORT | G29: ENGINEERING SUPPORT | H29: N | I29: https://www.lg.com/ae/business/hvac/engineering-support | J29: Engineering Support - HVAC | Business | LG UAE | K29: 46 | L29: Access a range of engineering support, including in-depth technical data. | M29: 73 | N29: ['Engineering Support'] | O29: 1 | P29: Pass | Q29: https://www.lg.com/ae/business/air-solution/engineering-support | R29: https://www.lg.com/ae/business/hvac/engineering-support | S29: Fail | T29: 100% | U29: ['6 gray gradient chips align left. Gradient chips under the top right 3 monitor outline with graph, protractor, and cube show distinct steps.'] | V29: [140] | W29: 70 | X29: 20 | Y29: 20 | Z29: 15 | AA29: 15 | AB29: 0
A30: MEA | B30: UAE | C30: AE : AE (en) | D30: 5.0 | E30: PLP | F30: Floor Standing | G30: Floor Standing | H30: Y | I30: https://www.lg.com/ae/business/hvac/residential-solutions/single-split/floor-standing | J30: Floor Standing Unit - Single Split - HVAC | Business |LG UAE | K30: 60 | L30: LG Floor Standing Unit efficiently heats and cools large spaces, providing even temperature distribution while complementing modern interiors. | M30: 142 | N30: ['Floor Standing Unit'] | O30: 1 | P30: Pass | Q30: https://www.lg.com/ae/business/hvac/residential-solutions/single-split/floor-standing | S30: Pass | T30: 0% | U30: ['pass'] | V30: [] | W30: 85 | X30: 20 | Y30: 20 | Z30: 15 | AA30: 15 | AB30: 15
A31: MEA | B31: UAE | C31: AE : AE (en) | D31: 5.0 | E31: PLP | F31: HVAC | G31: HVAC | H31: Y | I31: https://www.lg.com/ae/business/hvac | J31: HVAC Solutions - HVAC | Business | LG UAE | K31: 41 | L31: LG HVAC solutions are designed for diverse business environments and all climate needs. Discover LG's high-quality, energy-efficient air solutions from a trusted supplier. | M31: 171 | N31: [''] | O31: 1 | P31: Pass | Q31: https://www.lg.com/ae/business/hvac | S31: Pass | T31: 0% | U31: ['pass'] | V31: [] | W31: 65 | X31: 20 | Y31: 0 | Z31: 15 | AA31: 15 | AB31: 15
A32: MEA | B32: UAE | C32: AE : AE (en) | D32: 5.0 | E32: PLP | F32: HVAC Design Award | G32: HVAC Design Award | H32: N | I32: https://www.lg.com/ae/business/hvac/lg-hvac-design-award | J32: UAE & KSA HVAC Design Award | LG UAE Business | K32: 45 | M32: 0 | N32: [] | O32: 0 | P32: No H1 | Q32: https://www.lg.com/ae/business/hvac/lg-hvac-design-award | S32: Pass | T32: 0% | U32: ['pass'] | V32: [] | W32: 50 | X32: 20 | Y32: 0 | Z32: 0 | AA32: 15 | AB32: 15
A33: MEA | B33: UAE | C33: AE : AE (en) | D33: 5.0 | E33: PLP | F33: Hot Water Solution | G33: Hot Water Solution | H33: Y | I33: https://www.lg.com/ae/business/hvac/commercial-solutions/vrf-system/integrated-unit/hot-water-solution | J33: Hot Water Solution - VRF System - HVAC | Business | LG UAE | K33: 58 | L33: LG Hot Water Soltuion (Hydro Kit), a compact and powerful solution, assures a warm and comfortable indoor environment while maximizing efficiency. | M33: 146 | N33: ['Hot Water Solution (Hydro Kit)'] | O33: 1 | P33: Pass | Q33: https://www.lg.com/ae/business/hvac/commercial-solutions/vrf-system/integrated-unit/hot-water-solution | S33: Pass | T33: 0% | U33: ['pass'] | V33: [] | W33: 85 | X33: 20 | Y33: 20 | Z33: 15 | AA33: 15 | AB33: 15
A34: MEA | B34: UAE | C34: AE : AE (en) | D34: 5.0 | E34: PLP | F34: Ice Thermal Storage Centrifugal Chiller | G34: Ice Thermal Storage Centrifugal Chiller | H34: Y | I34: https://www.lg.com/ae/business/hvac/commercial-solutions/chiller/ice-thermal-storage-centrifugal-chiller | J34: Ice Thermal Storage Chiller - HVAC | Business | LG UAE | K34: 54 | L34: LG Ice Thermal Storage Centrifugal Chiller delivers efficient, dependable cooling to buildings via a two-stage compressor and melting night-generated ice. | M34: 154 | N34: ['Ice Thermal Storage Centrifugal Chiller'] | O34: 1 | P34: Pass | Q34: https://www.lg.com/ae/business/hvac/commercial-solutions/chiller/ice-thermal-storage-centrifugal-chiller | S34: Pass | T34: 0% | U34: ['pass'] | V34: [] | W34: 85 | X34: 20 | Y34: 20 | Z34: 15 | AA34: 15 | AB34: 15
A35: MEA | B35: UAE | C35: AE : AE (en) | D35: 5.0 | E35: PLP | F35: Individual Controller | G35: Individual Controller | H35: Y | I35: https://www.lg.com/ae/business/hvac/control-solutions/individual-controller | J35: Individual Controller - HVAC | Business | LG UAE | K35: 48 | L35: LG HVAC Individual Controllers feature air quality display, energy management, and remote control via the LG ThinQ app for efficient indoor air management | M35: 154 | N35: ['Individual Controller'] | O35: 1 | P35: Pass | Q35: https://www.lg.com/ae/business/hvac/control-solutions/individual-controller | S35: Pass | T35: 0% | U35: ['pass'] | V35: [] | W35: 85 | X35: 20 | Y35: 20 | Z35: 15 | AA35: 15 | AB35: 15
A36: MEA | B36: UAE | C36: AE : AE (en) | D36: 5.0 | E36: PLP | F36: MULTI V 5 | G36: MULTI V 5 | H36: Y | I36: https://www.lg.com/ae/business/hvac/commercial-solutions/vrf-system/outdoor-unit/multi-v-5 | J36: MULTI V 5 - VRF System - HVAC | Business | LG UAE | K36: 49 | L36: MULTI V is LG's VRF system with lower operation cost and minimum to no ductwork. Multi V 5 senses humidity & temperature to provide a perfect comfort level. | M36: 156 | N36: ['LG VRF: MULTI V 5'] | O36: 1 | P36: Pass | Q36: https://www.lg.com/ae/business/hvac/commercial-solutions/vrf-system/outdoor-unit/multi-v-5 | S36: Pass | T36: 0% | U36: ['pass'] | V36: [] | W36: 85 | X36: 20 | Y36: 20 | Z36: 15 | AA36: 15 | AB36: 15
A37: MEA | B37: UAE | C37: AE : AE (en) | D37: 5.0 | E37: PLP | F37: MULTI V S | G37: MULTI V S | H37: Y | I37: https://www.lg.com/ae/business/hvac/commercial-solutions/vrf-system/outdoor-unit/multi-v-s | J37: MULTI V S - VRF System - HVAC | Business | LG UAE | K37: 49 | L37: LG MULTI V S is a compact yet powerful indoor solution offering efficient and optimized air solution designs to fit your space's layout. | M37: 136 | N37: ['MULTI V S'] | O37: 1 | P37: Pass | Q37: https://www.lg.com/ae/business/hvac/commercial-solutions/vrf-system/outdoor-unit/multi-v-s | S37: Pass | T37: 0% | U37: ['pass'] | V37: [] | W37: 85 | X37: 20 | Y37: 20 | Z37: 15 | AA37: 15 | AB37: 15
A38: MEA | B38: UAE | C38: AE : AE (en) | D38: 5.0 | E38: PLP | F38: MULTI V WATER IV | G38: MULTI V WATER IV | H38: Y | I38: https://www.lg.com/ae/business/hvac/commercial-solutions/vrf-system/outdoor-unit/multi-v-water-iv | J38: MULTI V Water IV - VRF System - HVAC | Business | LG UAE | K38: 56 | L38: LG MULTI V Water IV provides an economical highly efficient water cooled VRF system with flexible installation for optimal commercial climate control | M38: 149 | N38: ['MULTI V WATER IV'] | O38: 1 | P38: Pass | Q38: https://www.lg.com/ae/business/hvac/commercial-solutions/vrf-system/outdoor-unit/multi-v-water-iv | S38: Pass | T38: 0% | U38: ['pass'] | V38: [] | W38: 85 | X38: 20 | Y38: 20 | Z38: 15 | AA38: 15 | AB38: 15
A39: MEA | B39: UAE | C39: AE : AE (en) | D39: 5.0 | E39: PLP | F39: Manuals | G39: Manuals | H39: N | I39: https://www.lg.com/ae/support/manuals | J39: LG Manuals | LG U.A.E | K39: 21 | L39: LG Manuals : Download the reference materials related to LG Products | M39: 68 | N39: ['Manuals & Documents'] | O39: 1 | P39: Pass | Q39: https://www.lg.com/ae/support/manuals | S39: Pass | T39: 0% | U39: ['pass'] | V39: [] | W39: 65 | X39: 0 | Y39: 20 | Z39: 15 | AA39: 15 | AB39: 15
A40: MEA | B40: UAE | C40: AE : AE (en) | D40: 5.0 | E40: PLP | F40: Modbus Gateway | G40: Modbus Gateway | H40: Y | I40: https://www.lg.com/ae/business/hvac/control-solutions/modbus-gateway | J40: Modbus Gateway- HVAC | Business | LG UAE | K40: 40 | L40: The LG Modbus Gateway focuses on solutions that facilitate seamless connections between LG air conditioning products and existing building management systems. | M40: 158 | N40: ['Modbus Gateway'] | O40: 1 | P40: Pass | Q40: https://www.lg.com/ae/business/hvac/control-solutions/modbus-gateway | S40: Pass | T40: 0% | U40: ['pass'] | V40: [] | W40: 85 | X40: 20 | Y40: 20 | Z40: 15 | AA40: 15 | AB40: 15
A41: MEA | B41: UAE | C41: AE : AE (en) | D41: 5.0 | E41: PLP | F41: Modular Chiller | G41: Modular Chiller | H41: Y | I41: https://www.lg.com/ae/business/hvac/commercial-solutions/chiller/modular-chiller | J41: Modular Centrifugal Chiller - HVAC | Business | LG UAE | K41: 54 | L41: LG Modular chiller offers optimized installation flexibility through modular combinations that maximize partial load efficiency. | M41: 128 | N41: ['Modular Chiller'] | O41: 1 | P41: Pass | Q41: https://www.lg.com/ae/business/hvac/commercial-solutions/chiller/modular-chiller | S41: Pass | T41: 0% | U41: ['pass'] | V41: [] | W41: 85 | X41: 20 | Y41: 20 | Z41: 15 | AA41: 15 | AB41: 15
A42: MEA | B42: UAE | C42: AE : AE (en) | D42: 5.0 | E42: PLP | F42: Multi Split | G42: Multi Split | H42: Y | I42: https://www.lg.com/ae/business/hvac/residential-solutions/multi-split | J42: Multi Split - Residential - HVAC | Business | LG UAE | K42: 52 | L42: LG Multi Split ac system, ideal for spacious environments, promises comfortable and efficient air conditioning across every space with its expandability. | M42: 153 | N42: ['Multi Split'] | O42: 1 | P42: Pass | Q42: https://www.lg.com/ae/business/hvac/residential-solutions/multi-split | S42: Pass | T42: 0% | U42: ['pass'] | V42: [] | W42: 85 | X42: 20 | Y42: 20 | Z42: 15 | AA42: 15 | AB42: 15
A43: MEA | B43: UAE | C43: AE : AE (en) | D43: 5.0 | E43: PLP | F43: Oil-free Magnetic Bearing Centrifugal Chiller | G43: Oil-free Magnetic Bearing Centrifugal Chiller | H43: Y | I43: https://www.lg.com/ae/business/hvac/commercial-solutions/chiller/oil-free-centrifugal-chiller | J43: Oil Free Centrifugal Chiller - HVAC | Business | LG UAE | K43: 55 | L43: LG Oil-free Centrifugal Chiller provides an efficient chiller system through its simplified piping structure and low-noise level. | M43: 129 | N43: ['Oil-free Centrifugal Chiller'] | O43: 1 | P43: Pass | Q43: https://www.lg.com/ae/business/hvac/commercial-solutions/chiller/oil-free-centrifugal-chiller | S43: Pass | T43: 0% | U43: ['pass'] | V43: [] | W43: 85 | X43: 20 | Y43: 20 | Z43: 15 | AA43: 15 | AB43: 15
A44: MEA | B44: UAE | C44: AE : AE (en) | D44: 5.0 | E44: PLP | F44: RESIDENTIAL SOLUTIONS | G44: RESIDENTIAL SOLUTIONS | H44: N | I44: https://www.lg.com/ae/business/hvac/residential-solutions | J44: Residential Solutions - HVAC | Business | LG UAE | K44: 48 | L44: LG HVAC residential solutions provide comfort environment and enhance energy efficiency. | M44: 88 | N44: ['A smarter way to keep home energy-efficient'] | O44: 1 | P44: Pass | Q44: https://www.lg.com/ae/business/hvac/residential-solutions | S44: Pass | T44: 50% | U44: ['A woman lies in bed, absorbed in her newspaper. Back window reveals a blue sky, while an lg hvac air conditioner(AC) on the right providing cool air.', 'A person is using a smartphone application to control a lg hvac ceiling-mounted cassette air conditioning unit in the living room.', 'Starting from the left, a room is being heated, the bathtub water is warm with visible steam, and a white cylindrical indoor unit can be seen.', 'On the wooden-floored terrace with two corner plants, a high-resolution air conditioner(AC) outdoor unit is displayed, supplemented by two outlined units.', 'Large townhouse complex blends white and brick exteriors with ivy adornments. The backyard, featuring a pool, is completed with two beach chairs.', 'A luxury residence building with a white roof on the left half and a black roof on the right half. Both residences boast a backyard pool.', 'A joyful family, father mother and a young daughter, is having a conversation on a living room sofa, LG hvac wall-mounted air conditioner(AC) providing cool comfort to all.'] | V44: [149, 130, 142, 154, 145, 137, 172] | W44: 70 | X44: 20 | Y44: 20 | Z44: 15 | AA44: 15 | AB44: 0
... A47: MEA | B47: UAE | C47: AE : AE (en) | D47: 5.0 | E47: PLP | F47: Round Cassette | G47: Round Cassette | H47: Y | I47: https://www.lg.com/ae/business/hvac/residential-solutions/single-split/round-cassette | J47: Round Cassette - Single Split - HVAC | Business | LG UAE | K47: 56 | L47: LG Round Cassette utilizes a unique circular shape to deliver precise, rapid cooling over large areas. | M47: 102 | N47: ['Round Cassette'] | O47: 1 | P47: Pass | Q47: https://www.lg.com/ae/business/hvac/residential-solutions/single-split/round-cassette | S47: Pass | T47: 0% | U47: ['pass'] | V47: [] | W47: 85 | X47: 20 | Y47: 20 | Z47: 15 | AA47: 15 | AB47: 15
A48: MEA | B48: UAE | C48: AE : AE (en) | D48: 5.0 | E48: PLP | F48: SERVICES & MAINTENANCE | G48: SERVICES & MAINTENANCE | H48: N | I48: https://www.lg.com/ae/business/hvac/service-maintenance | J48: Service & Maintenance - HVAC | Business | LG UAE | K48: 48 | L48: LG Service & Maintenance offers exceptional support for VRF and Chillers, guaranteeing continuous efficiency and powerful performance at all times. | M48: 147 | N48: ['Services & Maintenance'] | O48: 1 | P48: Pass | Q48: https://www.lg.com/ae/business/service-maintenance | R48: https://www.lg.com/ae/business/hvac/service-maintenance | S48: Fail | T48: 67% | U48: ['A person is using a red rectangular tool connected to a laptop, diagnosing an open LG outdoor unit, its internal wiring fully exposed.', 'The LG ceiling-mounted cassette displayed centrally reveals a stark contrast. Its left half is covered in dust, while the right half remains clean.', 'A program window displaying various details sits at the center, connected by red dotted lines to diverse types of chiller units.', 'Documents with a black outline are neatly overwrapped, featuring a circular shape with a downward-pointing arrow at the bottom right corner.', 'Three word bubbles of distinct sizes, each outlined in black, contain different marks, an exclamation, a question, and a check, respectively.', 'Connected by gray lines, LG BECON Connect API and 3rd Party Service exchange data via commercial and residential devices, merging into end-users.'] | V48: [134, 147, 128, 140, 141, 145] | W48: 70 | X48: 20 | Y48: 20 | Z48: 15 | AA48: 15 | AB48: 0
A49: MEA | B49: UAE | C49: AE : AE (en) | D49: 5.0 | E49: PLP | F49: SUPPORT | G49: SUPPORT | H49: N | I49: https://www.lg.com/ae/support | J49: Customer Care | LG U.A.E | K49: 24 | L49: LG team is always there to answer your inquiries. Learn more about how to contact LG customer care in the UAE via telephone, e-mail, and more. | M49: 142 | N49: ['SupportWelcome to LG Customer Care Team!How can we help you?'] | O49: 1 | P49: Pass | Q49: https://www.lg.com/ae/support | S49: Pass | T49: 0% | U49: ['pass'] | V49: [] | W49: 50 | X49: 0 | Y49: 20 | Z49: 15 | AA49: 0 | AB49: 15
A50: MEA | B50: UAE | C50: AE : AE (en) | D50: 5.0 | E50: PLP | F50: Single Packaged | G50: Single Packaged | H50: Y | I50: https://www.lg.com/ae/business/hvac/commercial-solutions/single-packaged | J50: Inverter Single Package - HVAC | Business | LG UAE | K50: 50 | L50: LG Inverter Single Package, with a direct fan and dual sensor for humidity and temperature, delivers efficient cooling and heating solution for various spaces. | M50: 159 | N50: ['Inverter Single Package'] | O50: 1 | P50: Pass | Q50: https://www.lg.com/ae/business/hvac/commercial-solutions/single-packaged | S50: Pass | T50: 0% | U50: ['pass'] | V50: [] | W50: 85 | X50: 20 | Y50: 20 | Z50: 15 | AA50: 15 | AB50: 15
A51: MEA | B51: UAE | C51: AE : AE (en) | D51: 5.0 | E51: PLP | F51: Single Split | G51: Single Split | H51: Y | I51: https://www.lg.com/ae/business/hvac/commercial-solutions/single-split | J51: Single Split - Residential - HVAC | Business | LG UAE | K51: 53 | L51: LG Single Split system is an ideal choice for various spaces. This air conditioning system provides optimal energy efficiency and reliable performance. | M51: 151 | N51: ['Single Split'] | O51: 1 | P51: Pass | Q51: https://www.lg.com/ae/business/hvac/residential-solutions/single-split | S51: Pass | T51: 0% | U51: ['pass'] | V51: [] | W51: 70 | X51: 20 | Y51: 20 | Z51: 15 | AA51: 0 | AB51: 15
A52: MEA | B52: UAE | C52: AE : AE (en) | D52: 5.0 | E52: PLP | F52: Single Split | G52: Single Split | H52: Y | I52: https://www.lg.com/ae/business/hvac/residential-solutions/single-split | J52: Single Split - Residential - HVAC | Business | LG UAE | K52: 53 | L52: LG Single Split system is an ideal choice for various spaces. This air conditioning system provides optimal energy efficiency and reliable performance. | M52: 151 | N52: ['Single Split'] | O52: 1 | P52: Pass | Q52: https://www.lg.com/ae/business/hvac/residential-solutions/single-split | S52: Pass | T52: 0% | U52: ['pass'] | V52: [] | W52: 85 | X52: 20 | Y52: 20 | Z52: 15 | AA52: 15 | AB52: 15
A53: MEA | B53: UAE | C53: AE : AE (en) | D53: 5.0 | E53: PLP | F53: VRF Annual Maintenance | G53: VRF Annual Maintenance | H53: N | I53: https://www.lg.com/ae/business/hvac/service-maintenance/vrf-system-annual-maintenance | J53: VRF System Annual Maintenance - HVAC | Business | LG UAE | K53: 56 | L53: LG VRF System Annual Maintenance guarantees efficient and powerful performance through routine inspections, cleanings, and parts replacement. | M53: 141 | N53: ['Optimize Multi V and Save Energy with Regular Maintenance'] | O53: 1 | P53: Pass | Q53: https://www.lg.com/ae/business/hvac/service-maintenance/vrf-system-annual-maintenance | S53: Pass | T53: 43% | U53: ['Comparison chart outlines basic, and premium packages, each offering unique inspection, cleaning, replacement, BECON, and energy management services.', 'A Smartphone illuminates with the LGMV application on its display, complemented by a hovering white rectangular instrument to the left.', 'LG Ceiling Mounted Indoor unit is elegantly featured on the left, while an LG Multi V 5 Outdoor unit takes stance on the right.', 'A man donning a safety helmet is diligently covering an open indoor unit perched on the ceiling with a protective plastic cover.', 'On the left, a dusty, dirt-covered grill of an indoor unit contrasts starkly with its counterpart on the right, which is clean and gleams brightly.', 'In their right hand, a person wields a water pressure washer, applying a stream of water to cleanse the outdoor unit thoroughly.', "From left to right, a '24' texted circular timer, a monitor-like object, and a database occupy the center, with '365' atop a calendar on the right.", 'A graph plots temperature against time, with a red area signifying a normal temperature range, while standout white peaks flag up abnormal values.', "A magnifier at the center zooms into an object blending a monitor and database, circled by the words 'AI' on the left and 'Big Data' on the right.", 'A person is using a red rectangular tool connected to a laptop, diagnosing an open LG outdoor unit, its internal wiring fully exposed.'] | V53: [149, 135, 127, 128, 147, 128, 147, 146, 146, 134] | W53: 70 | X53: 20 | Y53: 20 | Z53: 15 | AA53: 15 | AB53: 0
A54: MEA | B54: UAE | C54: AE : AE (en) | D54: 5.0 | E54: PLP | F54: VRF Renewal Service | G54: VRF Renewal Service | H54: N | I54: https://www.lg.com/ae/business/hvac/service-maintenance/vrf-system-renewal-service | J54: VRF System Renewal Service - HVAC | Business | LG UAE | K54: 53 | L54: LG VRF System Renewal Service offers a cost-effective strategy to prolong your equipment's lifespan while sustaining its clean, powerful air performance. | M54: 153 | N54: ["Extend Your Multi V's Lifespan with Renewal Service."] | O54: 1 | P54: Pass | Q54: https://www.lg.com/ae/business/hvac/service-maintenance/vrf-system-renewal-service | S54: Pass | T54: 33% | U54: ['The LG ceiling-mounted cassette displayed centrally reveals a stark contrast. Its left half is covered in dust, while the right half remains clean.', 'In a triangular formation, three circles present a wrench and driver at the top, two rotating rectangles on the left, and a towel-clad hand.', 'LG VRF Human detection sensors highlight the energy-saving feature in the image, shown in a close-up view of a part of the product.', 'LG ceiling-mounted VRF Multi V unit displayed centrally reveals a stark contrast. Its left half is covered in dust, while the right remains clean.'] | V54: [147, 140, 131, 146] | W54: 70 | X54: 20 | Y54: 20 | Z54: 15 | AA54: 15 | AB54: 0
A55: MEA | B55: UAE | C55: AE : AE (en) | D55: 5.0 | E55: PLP | F55: VRF System | G55: VRF System | H55: Y | I55: https://www.lg.com/ae/business/hvac/commercial-solutions/vrf-system | J55: VRF System - Commercial Solutions - HVAC | Business | LG UAE | K55: 60 | L55: LG VRF System minimizes efficiency losses while providing optimized, reliable, and energy-saving solutions for heating, ventilation, and air conditioning. | M55: 154 | N55: [''] | O55: 1 | P55: Pass | Q55: https://www.lg.com/ae/business/hvac/commercial-solutions/vrf-system | S55: Pass | T55: 22% | U55: ['There is an indoor office on the left side and an outdoor rooftop on the right side. In the middle, AHU provides heating and cooling fresh air on each side.', 'An installer wearing a safety helmet and glasses tries to separate the front panel of the Ceiling Mounted Cassette installed on the ceiling.'] | V55: [156, 140] | W55: 70 | X55: 20 | Y55: 20 | Z55: 15 | AA55: 15 | AB55: 0
A56: MEA | B56: UAE | C56: AE : AE (en) | D56: 5.0 | E56: PLP | F56: Wall Mounted | G56: Wall Mounted | H56: Y | I56: https://www.lg.com/ae/business/hvac/commercial-solutions/vrf-system/indoor-unit/wall-mounted | J56: Wall Mounted - VRF System - HVAC | Business | LG UAE | K56: 52 | L56: LG Wall Mounted Unit offers powerful cooling and heating, ensures energy efficiency, and supports quick, easy installation in various applications. | M56: 147 | N56: ['Wall Mounted Unit'] | O56: 1 | P56: Pass | Q56: https://www.lg.com/ae/business/hvac/commercial-solutions/vrf-system/indoor-unit/wall-mounted | S56: Pass | T56: 0% | U56: ['pass'] | V56: [] | W56: 85 | X56: 20 | Y56: 20 | Z56: 15 | AA56: 15 | AB56: 15
A57: MEA | B57: UAE | C57: AE : AE (en) | D57: 5.0 | E57: PLP | F57: Wall Mounted | G57: Wall Mounted | H57: Y | I57: https://www.lg.com/ae/business/hvac/residential-solutions/single-split/wall-mounted | J57: Wall Mounted - Single Split - HVAC | Business | LG UAE | K57: 54 | L57: LG Wall Mounted Unit offers powerful cooling and heating, ensures energy efficiency, and supports quick, easy installation in various applications. | M57: 147 | N57: ['Wall mounted'] | O57: 1 | P57: Pass | Q57: https://www.lg.com/ae/business/hvac/residential-solutions/single-split/wall-mounted | S57: Pass | T57: 0% | U57: ['pass'] | V57: [] | W57: 85 | X57: 20 | Y57: 20 | Z57: 15 | AA57: 15 | AB57: 15
A58: MEA | B58: UAE | C58: AE : AE (en) | D58: 5.0 | E58: PLP | F58: Water Cooled Screw Chiller | G58: Water Cooled Screw Chiller | H58: Y | I58: https://www.lg.com/ae/business/hvac/commercial-solutions/chiller/water-cooled-screw-chiller | J58: Water Cooled Screw Chiller - Chiller - HVAC | Business | LG UAE | K58: 63 | L58: LG Water-cooled Screw Chiller provides a quiet and reliable operation system, featuring an oil recovery system and a high-efficiency load evaporator. | M58: 149 | N58: ['Water-cooled Screw Chiller'] | O58: 1 | P58: Pass | Q58: https://www.lg.com/ae/business/hvac/commercial-solutions/chiller/water-cooled-screw-chiller | S58: Pass | T58: 0% | U58: ['pass'] | V58: [] | W58: 65 | X58: 0 | Y58: 20 | Z58: 15 | AA58: 15 | AB58: 15
A59: MEA | B59: UAE | C59: AE_AR : AE (ar) | D59: 5.0 | E59: PLP | F59: وحدة مناولة الهواء (AHU) | G59: Air Handling Unit (AHU) | H59: Y | I59: https://www.lg.com/ae_ar/business/air-handling-unit | J59: وحدة مناولة الهواء (AHU) | HVAC | ال جي الإمارات | K59: 48 | L59: تُعد وحدة معالجة الهواء من إل جي الإمارات هي نظام منقي للهواء وموفر للطاقة، والذي يعمل على التحكم في درجة نقاء الهواء في المنزل أو المكتب ويحافظ عليها ويرصدها. | M59: 159 | N59: ['Air Handing Unit (AHU)'] | O59: 1 | P59: Pass | Q59: https://www.lg.com/ae_ar/business/air-handling-unit | S59: Pass | T59: 0% | U59: ['pass'] | V59: [] | W59: 85 | X59: 20 | Y59: 20 | Z59: 15 | AA59: 15 | AB59: 15
A60: MEA | B60: UAE | C60: AE_AR : AE (ar) | D60: 5.0 | E60: PLP | F60: حلول أنظمة التكييف | G60: Air conditioning systems solutions | H60: Y | I60: https://www.lg.com/ae_ar/business/air-solution | J60: أجدد حلول التدفئة وتكييف الهواء من إل جي | LG UAE Business | K60: 58 | L60: أنظمة التكييف والتبريد التي توفرها إل جي الإمارات للشركات التي تبحث عن حلول رقمية وصديقة للبيئة في مجال التدفئة والتهوية والتبريد. اكتشف المزيد من التفاصيل. | M60: 156 | N60: ['أجدد حلول التدفئة وتكييف الهواء من إل جي'] | O60: 1 | P60: Pass | Q60: https://www.lg.com/ae_ar/business/air-solution | S60: Pass | T60: 0% | U60: ['pass'] | V60: [] | W60: 85 | X60: 20 | Y60: 20 | Z60: 15 | AA60: 15 | AB60: 15
... A63: MEA | B63: UAE | C63: AE_AR : AE (ar) | D63: 5.0 | E63: PLP | F63: وحدة مجمعة | G63: Combined unit | H63: Y | I63: https://www.lg.com/ae_ar/business/single-packaged | J63: Inverter Single Package‏ - HVAC | الشركات | إل جي الإمارات | K63: 58 | L63: LG Inverter Single Package المزود بريشة مباشرة ومستشعر مزدوج للرطوبة ودرجة الحرارة يوفر حلاً فعالاً للتبريد والتدفئة لمختلف المساحات. | M63: 133 | N63: ['مكيف Inverter Single Package'] | O63: 1 | P63: Pass | Q63: https://www.lg.com/ae_ar/business/single-packaged | S63: Pass | T63: 0% | U63: ['pass'] | V63: [] | W63: 85 | X63: 20 | Y63: 20 | Z63: 15 | AA63: 15 | AB63: 15
A64: MEA | B64: UAE | C64: AE_AR : AE (ar) | D64: 5.0 | E64: PLP | F64: Commercial End User | G64: Commercial End User | H64: N | I64: https://www.lg.com/ae/business/hvac/commercial-end-user | J64: Commercial End User - HVAC | Business | LG UAE | K64: 46 | L64: LG HVAC solutions provide fast, reliable, and optimal solutions for commercial end users by meeting customer service needs with quality service and maintenance, offering a wide range of services and service packages. | M64: 216 | N64: ['Build Confidence and Efficiency with LG HVAC Solutions'] | O64: 1 | P64: Pass | Q64: https://www.lg.com/ae/business/air-solution/commercial-end-user | R64: https://www.lg.com/ae/business/hvac/commercial-end-user | S64: Fail | T64: 26% | U64: ['A man and a woman are seated at a desk, collaboratively working while viewing a laptop screen. The background showcases a stylized, abstract design, reflecting a modern, tech-savvy environment.', 'A modern residential interior features smart home technology controlled by a tablet, with a clean, bright design that emphasizes comfort and innovation.', 'A spacious, well-lit hotel room with a comfortable bed and modern furnishings creates an inviting ambiance that aims to provide a restful experience for guests.', 'Stylishly designed retail space with warm lighting and an inviting atmosphere highlighting a chic, customer-friendly environment.', 'Captures a large, airy shopping mall with expansive walkways and modern architecture. The design focuses on providing a luxurious and spacious shopping experience.', 'A technician wearing a headset is seated in front of multiple computer screens displaying HVAC system data for service and maintenance, with a backdrop of digital graphics and cloud icons.'] | V64: [193, 152, 160, 129, 163, 188] | W64: 50 | X64: 20 | Y64: 0 | Z64: 15 | AA64: 15 | AB64: 0
A65: MEA | B65: UAE | C65: AE_AR : AE (ar) | D65: 5.0 | E65: PLP | F65: مبرد امتصاصي مركب | G65: Compound absorption chiller | H65: Y | I65: https://www.lg.com/ae_ar/business/absorption-chiller-complex-type | J65: مبرد امتصاصي مركب | إل جي الإمارات العربية المتحدة التجارية | K65: 59 | L65: تعرف على أحدث مبردات امتصاص الطاقة المركبة من إل جي والتي تقدم حلول تبريد مميزة لأعمالكم. تعرف على المزيد على موقع إل جي الإمارات العربية المتحدة التجارية | M65: 154 | N65: ['مبرد هجين يعمل بنظام التبريد بالامتصاص'] | O65: 1 | P65: Pass | Q65: https://www.lg.com/ae_ar/business/absorption-chiller-complex-type | S65: Pass | T65: 0% | U65: ['pass'] | V65: [] | W65: 85 | X65: 20 | Y65: 20 | Z65: 15 | AA65: 15 | AB65: 15
A66: MEA | B66: UAE | C66: AE_AR : AE (ar) | D66: 5.0 | E66: PLP | F66: حلول التحكم | G66: Control Solutions | H66: Y | I66: https://www.lg.com/ae_ar/business/air-control-solutions | J66: حلول التحكم | HVAC | ال جي الإمارات للأعمال | K66: 43 | L66: توفر حلول التحكم من إل جي الإمارات مجموعة كبيرة من أساليب التحكم المناسبة، مما يسمح بتحديد درجة الحرارة الأمثل لبيئة أعمالك. | M66: 124 | N66: ['حلول التحكم'] | O66: 1 | P66: Pass | Q66: https://www.lg.com/ae_ar/business/air-control-solutions | S66: Pass | T66: 0% | U66: ['pass'] | V66: [] | W66: 85 | X66: 20 | Y66: 20 | Z66: 15 | AA66: 15 | AB66: 15
A67: MEA | B67: UAE | C67: AE_AR : AE (ar) | D67: 5.0 | E67: PLP | F67: سقف وأرضية قابلة للتحويل | G67: Convertible roof and floor | H67: Y | I67: https://www.lg.com/ae_ar/business/single-split-ceiling-suspended | J67: سقف وأرضية قابلة للتحويل | HVAC | ال جي الإمارات | K67: 48 | L67: يجمع المكيف التجاري السقفي المعلق من إل جي الإمارات بين التصميم العصري والشكل الديكوري الأنيق الذي يتناسب تمامًا مع البيئة المحيطة. | M67: 131 | N67: ['السقف معلق'] | O67: 1 | P67: Pass | Q67: https://www.lg.com/ae_ar/business/single-packaged-air-solution | R67: https://www.lg.com/ae_ar/business/single-packaged | S67: Fail | T67: 0% | U67: ['pass'] | V67: [] | W67: 70 | X67: 20 | Y67: 20 | Z67: 15 | AA67: 0 | AB67: 15
A68: MEA | B68: UAE | C68: AE_AR : AE (ar) | D68: 5.0 | E68: PLP | F68: مبرد التبريد بالامتصاص يعمل بطاقة مباشرة | G68: Direct-cooled absorption chiller | H68: Y | I68: https://www.lg.com/ae_ar/business/absorption-chiller-direct-fired-type | J68: مبرد التبريد بالامتصاص يعمل بطاقة مباشرة | HVAC | ال جي UAE | K68: 59 | L68: وفّر الطاقة مع نظام تبريد إل جي بالامتصاص والتبخير. يستخدم الحرارة بدلاً من الكهرباء، مما يجعله الحل الأمثل في المناطق قليلة الإمداد بالطاقة. | M68: 141 | N68: ['مبرد الامتصاص نوع يعمل مباشرة'] | O68: 1 | P68: Pass | Q68: https://www.lg.com/ae_ar/business/absorption-chiller-direct-fired-type | S68: Pass | T68: 0% | U68: ['pass'] | V68: [] | W68: 85 | X68: 20 | Y68: 20 | Z68: 15 | AA68: 15 | AB68: 15
A69: MEA | B69: UAE | C69: AE_AR : AE (ar) | D69: 5.0 | E69: PLP | F69: الدعم الهندسي | G69: Engineering support | H69: N | I69: https://www.lg.com/ae_ar/business/air-solution/engineering-support | J69: الدعم الهندسي | إل جي الإمارات العربية المتحدة التجارية | K69: 55 | L69: توفر إل جي مجموعة واسعة من الحلول الهندسية لتدعم عملية تركيب وتشغليل أنضمة HVAC وتحقيق أفضل أداء. تعرف على حلول الدعم الهندسي على موقع إل جي الإمارات التجارية | M69: 158 | N69: ['الدعم الهندسي'] | O69: 1 | P69: Pass | Q69: https://www.lg.com/ae_ar/business/air-solution/engineering-support | S69: Pass | T69: 0% | U69: ['pass'] | V69: [] | W69: 85 | X69: 20 | Y69: 20 | Z69: 15 | AA69: 15 | AB69: 15
A70: MEA | B70: UAE | C70: AE_AR : AE (ar) | D70: 5.0 | E70: PLP | F70: مبرد التبريد بالامتصاص يعمل بالبخار | G70: Evaporative absorption chiller | H70: Y | I70: https://www.lg.com/ae_ar/business/absorption-chiller-steam-type | J70: مبرد التبريد بالامتصاص يعمل بالبخار | HVAC | ال جي الإمارات | K70: 59 | L70: اكتشف نظام التبريد بامتصاص الماء الساخن من إل جي. يستخدم الجهاز الحرارة بدلاً من الكهرباء، مما يجعله الخيار الأفضل للمناطق قليلة الإمداد بالطاقة. | M70: 145 | N70: ['Absorption Chiller Steam Type'] | O70: 1 | P70: Pass | Q70: https://www.lg.com/ae_ar/business/absorption-chiller-steam-type | S70: Pass | T70: 0% | U70: ['pass'] | V70: [] | W70: 85 | X70: 20 | Y70: 20 | Z70: 15 | AA70: 15 | AB70: 15
A71: MEA | B71: UAE | C71: AE_AR : AE (ar) | D71: 5.0 | E71: PLP | F71: HVAC BLOG-ON AIR | G71: HVAC BLOG-ON AIR | H71: N | I71: https://www.lg.com/ae_ar/business/air-solution/blog-list | J71: HVAC BLOG-ON AIR | HVAC | ال جي الإمارات | K71: 40 | L71: اكتشف أحدث الاتجاهات والقصص من أنظمة التدفئة والتهوية وتكييف الهواء من إل جي في الإمارات | M71: 88 | N71: [] | O71: 0 | P71: No H1 | Q71: https://www.lg.com/ae_ar/business/air-solution/blog-list | S71: Pass | T71: 0% | U71: ['pass'] | V71: [] | W71: 70 | X71: 20 | Y71: 20 | Z71: 0 | AA71: 15 | AB71: 15
A72: MEA | B72: UAE | C72: AE_AR : AE (ar) | D72: 5.0 | E72: PLP | F72: حل التدفئة (AWHP) | G72: Heating Solution (AWHP) | H72: Y | I72: https://www.lg.com/ae_ar/business/heating-awhp | J72: حل التدفئة (AWHP) | HVAC | ال جي الإمارات | K72: 41 | L72: يٌعد حل التدفئة AWHP من إل جي الإمارات نظام عالي الكفاءة يسمح بتدفئة المباني والتدفئة الأرضية والتبريد والإمداد بالمياه الساخنة. | M72: 128 | N72: ['حل التدفئة (AWHP)'] | O72: 1 | P72: Pass | Q72: https://www.lg.com/ae_ar/business/heating-awhp | S72: Pass | T72: 0% | U72: ['pass'] | V72: [] | W72: 85 | X72: 20 | Y72: 20 | Z72: 15 | AA72: 15 | AB72: 15
A73: MEA | B73: UAE | C73: AE_AR : AE (ar) | D73: 5.0 | E73: PLP | F73: حل المياه الساخنة (Hydro Kit) | G73: Hot Water Solution (Hydro Kit) | H73: Y | I73: https://www.lg.com/ae_ar/business/hot-water-solution-hydro-kit | J73: حل المياه الساخنة (Hydro Kit) | HVAC | ال جي الإمارات | K73: 53 | L73: يستخدم سخان كيت هيدرو من إلى جي الإمارات الماء الساخن لتوفير بيئة داخلية دافئة، كما أنه يعمل من خلال الدمج مع نظام ملتي في. | M73: 123 | N73: ['حلول المياه الساخنة (Hydro Kit)'] | O73: 1 | P73: Pass | Q73: https://www.lg.com/ae_ar/business/hot-water-solution-hydro-kit | S73: Pass | T73: 0% | U73: ['pass'] | V73: [] | W73: 85 | X73: 20 | Y73: 20 | Z73: 15 | AA73: 15 | AB73: 15
A74: MEA | B74: UAE | C74: AE_AR : AE (ar) | D74: 5.0 | E74: PLP | F74: مبرد التبريد بالامتصاص يعمل بالماء الساخن | G74: Hot water absorption chiller | H74: Y | I74: https://www.lg.com/ae_ar/business/absorption-chiller-hot-water-type | J74: مبرد التبريد بالامتصاص يعمل بالماء الساخن | HVAC | ال جي UAE | K74: 60 | L74: وفّر الطاقة مع نظام تبريد إل جي المبتكر. يعمل بالامتصاص المركب ويستخدم الحرارة بدلاً من الكهرباء، مما يجعله الحل الأمثل للمناطق ذات الطاقة المحدودة. | M74: 148 | N74: ['Absorption Chiller Hot Water Type'] | O74: 1 | P74: Pass | Q74: https://www.lg.com/ae_ar/business/absorption-chiller-hot-water-type | S74: Pass | T74: 0% | U74: ['pass'] | V74: [] | W74: 85 | X74: 20 | Y74: 20 | Z74: 15 | AA74: 15 | AB74: 15
A75: MEA | B75: UAE | C75: AE_AR : AE (ar) | D75: 5.0 | E75: PLP | F75: مقاول تركيب | G75: Installation contractor | H75: N | I75: https://www.lg.com/ae_ar/business/air-solution/installer | J75: مقاول تركيب | إل جي الإمارات العربية المتحدة التجارية | K75: 53 | L75: استكشف الميزات المبتكرة لحلول تكييف الهواء من إل جي التي تزيد التحكم في كل نظام بناء لتحقيق عملية بناء متماسكة. تعرف على المزيد على موقع إل جي الإمارات التجارية | M75: 160 | N75: ['تركيب سهل مع حلول HVAC من LG'] | O75: 1 | P75: Pass | Q75: https://www.lg.com/ae_ar/business/air-solution/installer | S75: Pass | T75: 0% | U75: ['pass'] | V75: [] | W75: 85 | X75: 20 | Y75: 20 | Z75: 15 | AA75: 15 | AB75: 15
A76: MEA | B76: UAE | C76: AE_AR : AE (ar) | D76: 5.0 | E76: PLP | F76: MULTI V 5 | G76: MULTI V 5 | H76: Y | I76: https://www.lg.com/ae_ar/business/multi-v-5 | J76: مكيف هواء ملتي في 5 - أنواع المكيفات المركزية | إل جي UAE | K76: 57 | L76: تبحث عن مكيف مركزي؟ اكتشف مكيف LG MULTI V 5 الذي يناسب كافة الاحتياجات. ابحث عن الأفضل لمنزلك أو عملك الآن. | M76: 107 | N76: ['الحل الأمثل عالي الكفاءة لجودة الهواء'] | O76: 1 | P76: Pass | Q76: https://www.lg.com/ae_ar/business/multi-v-5 | S76: Pass | T76: 0% | U76: ['pass'] | V76: [] | W76: 85 | X76: 20 | Y76: 20 | Z76: 15 | AA76: 15 | AB76: 15
A77: MEA | B77: UAE | C77: AE_AR : AE (ar) | D77: 5.0 | E77: PLP | F77: MULTI V WATER IV | G77: MULTI V WATER IV | H77: Y | I77: https://www.lg.com/ae_ar/business/multi-v-water-iv | J77: MULTI V WATER IV | HVAC | ال جي الإمارات | K77: 40 | L77: صُممت أنظمة تبريد المياه ملتي في IV التجارية من إل جي الإمارات لتوفير طاقة فائقة تمنح المشغلين خيار تكييف الهواء أو تدفئته في المناطق المستخدمة بها فقط. | M77: 152 | N77: ['MULTI V WATER IV'] | O77: 1 | P77: Pass | Q77: https://www.lg.com/ae_ar/business/multi-v-water-iv | S77: Pass | T77: 0% | U77: ['pass'] | V77: [] | W77: 85 | X77: 20 | Y77: 20 | Z77: 15 | AA77: 15 | AB77: 15
A78: MEA | B78: UAE | C78: AE_AR : AE (ar) | D78: 5.0 | E78: PLP | F78: MULTI V S | G78: MULTI VS | H78: Y | I78: https://www.lg.com/ae_ar/business/multi-v-s | J78: MULTI V S | التدفئة والتهوية وتكييف الهواء | ال جي الإمارات | K78: 59 | L78: يعمل مكيف كاسيت من إل جي على زيادة جماليات الأماكن المغلقة مع توفير بيئة مريحة، مما يجعله الركيزة المثالية لأعمالك. تعلم المزيد الآن. | M78: 133 | N78: ['MULTI V S'] | O78: 1 | P78: Pass | Q78: https://www.lg.com/ae_ar/business/multi-v-s | S78: Pass | T78: 0% | U78: ['pass'] | V78: [] | W78: 85 | X78: 20 | Y78: 20 | Z78: 15 | AA78: 15 | AB78: 15
A79: MEA | B79: UAE | C79: AE_AR : AE (ar) | D79: 5.0 | E79: PLP | F79: وحدات منفصلة متعددة | G79: Multiple separate units | H79: Y | I79: https://www.lg.com/ae_ar/business/multi-split | J79: Multi Split - HVAC | للشركات | إل جي الإمارات للأعمال | K79: 53 | L79: تُعد أنظمة التقسيم المتعددة مثالية للمساحات الواسعة، وتقدم تبريد فعّال ومريح عبر أي مساحة بفضل إمكانية مضاعفتها وتوسعها. | M79: 120 | N79: ['استكشف المزيد حول أنظمة Multi Split'] | O79: 1 | P79: Pass | Q79: https://www.lg.com/ae_ar/business/multi-split | S79: Pass | T79: 0% | U79: ['pass'] | V79: [] | W79: 85 | X79: 20 | Y79: 20 | Z79: 15 | AA79: 15 | AB79: 15
... A97: MEA | B97: UAE | C97: AE_AR : AE (ar) | D97: 5.0 | E97: PLP | F97: استشاري | G97: consultative | H97: N | I97: https://www.lg.com/ae_ar/business/air-solution/consultant | J97: استشاري | إل جي الإمارات العربية المتحدة التجارية | K97: 49 | L97: اكتشف أحدث منتجات تكييف الهواء من إل جي بميزات منقطعة النظير لإرضاء متطلباتك عملائك ومنحهم أقصى قدر من الأداء. تعرف على المزيد على موقع إل جي الإمارات التجارية | M97: 159 | N97: ['نجلب التصميم الأمثل لمشاريع HVAC الخاصة بك'] | O97: 1 | P97: Pass | Q97: https://www.lg.com/ae_ar/business/air-solution/consultant | S97: Pass | T97: 0% | U97: ['pass'] | V97: [] | W97: 85 | X97: 20 | Y97: 20 | Z97: 15 | AA97: 15 | AB97: 15
A98: MEA | B98: UAE | C98: AE_AR : AE (ar) | D98: 5.0 | E98: PLP | F98: مبرد | G98: cooler | H98: Y | I98: https://www.lg.com/ae_ar/business/chiller | J98: مبرد | HVAC | ال جي الإمارات | K98: 28 | L98: يوفر المبرد من إل جي الإمارات حلول تكييف هواء مركزية مبردة بالماء فعالة ومثالية للمرافق الصناعية والمباني الكبرى. | M98: 113 | N98: ['نظام التبريد (CHILLER)'] | O98: 1 | P98: Pass | Q98: https://www.lg.com/ae/business/chiller | R98: https://www.lg.com/ae/business/hvac/commercial-solutions/chiller | S98: Fail | T98: 0% | U98: ['pass'] | V98: [] | W98: 50 | X98: 0 | Y98: 20 | Z98: 15 | AA98: 0 | AB98: 15
A99: MEA | B99: UAE | C99: AE_AR : AE (ar) | D99: 5.0 | E99: PLP | F99: قائم على الأرضية | G99: floor-standing | H99: Y | I99: https://www.lg.com/ae_ar/business/single-split-floor-standing | J99: وحدة تكييف أرضية - HVAC | ال جي الإمارات للأعمال | K99: 48 | L99: تعمل وحدة LG Floor Standing Unit على تدفئة المساحات الكبيرة وتبريدها بكفاءة، مما يوفر توزيعًا متساويًا لدرجة الحرارة مع استكمال التصميمات الداخلية الحديثة. | M99: 155 | N99: ['وحدة تكييف أرضية'] | O99: 1 | P99: Pass | Q99: https://www.lg.com/ae_ar/business/single-split-floor-standing | S99: Pass | T99: 0% | U99: ['pass'] | V99: [] | W99: 85 | X99: 20 | Y99: 20 | Z99: 15 | AA99: 15 | AB99: 15
A100: MEA | B100: UAE | C100: AE_AR : AE (ar) | D100: 5.0 | E100: PLP | F100: بوابة | G100: gate | H100: Y | I100: https://www.lg.com/ae_ar/business/gateway | J100: بوابة مودبوس | HVAC | ال جي الإمارات للأعمال | K100: 44 | L100: يُعد جهاز Modbus Gateway من إل جي الإمارات حلاً يربط بين منتجات إل جي ونظام المبنى الحالي لوحدة أعمالك. | M100: 103 | N100: ['بوابة مودبوس'] | O100: 1 | P100: Pass | Q100: https://www.lg.com/ae_ar/business/gateway | S100: Pass | T100: 0% | U100: ['pass'] | V100: [] | W100: 85 | X100: 20 | Y100: 20 | Z100: 15 | AA100: 15 | AB100: 15
A101: MEA | B101: UAE | C101: AE_AR : AE (ar) | D101: 5.0 | E101: PLP | F101: قناة مخفية | G101: hidden channel | H101: Y | I101: https://www.lg.com/ae_ar/business/single-split-concealed-duct | J101: Ceiling Concealed Duct - HVAC | ال جي الإمارات للأعمال | K101: 54 | L101: يوفر LG Ceiling Concealed Duct حلول تبريد وتدفئة ذكية ومحسّنة لمجموعة متنوعة من المساحات. | M101: 89 | N101: ['Ceiling Concealed Duct'] | O101: 1 | P101: Pass | Q101: https://www.lg.com/ae_ar/business/single-split-concealed-duct | S101: Pass | T101: 12% | U101: ['رسم تخطيطي لتدفق هواء LG Ceiling Concealed Duct مع الصورة العلوية التي توضح الاتجاهات الداخلية بالأسهم الحمراء والصورة السفلية التي تبرز مسارات سحب الهواء النقي (fresh air intake) وتدويره بالأسهم الحمراء.'] | V101: [204] | W101: 70 | X101: 20 | Y101: 20 | Z101: 15 | AA101: 15 | AB101: 0
A102: MEA | B102: UAE | C102: AE_AR : AE (ar) | D102: 5.0 | E102: PLP | F102: مستشفى | G102: hospital | H102: N | I102: https://www.lg.com/ae_ar/business/hospital | J102: مستشفى | HVAC | ال جي الإمارات | K102: 30 | L102: يوفر حل مستشفى من أنظمة التدفئة والتهوية وتكييف الهواء من إل جي الإمارات الراحة والأمان للمرضى مع تسهيل التحكم في البيئة ومراقبتها. | M102: 131 | N102: ['عناية بالهواء على مدار 24/7 لتحقيق الصحة والراحة'] | O102: 1 | P102: Pass | Q102: https://www.lg.com/ae_ar/business/hospital | S102: Pass | T102: 0% | U102: ['pass'] | V102: [] | W102: 65 | X102: 0 | Y102: 20 | Z102: 15 | AA102: 15 | AB102: 15
A103: MEA | B103: UAE | C103: AE_AR : AE (ar) | D103: 5.0 | E103: PLP | F103: فندق | G103: hotel | H103: N | I103: https://www.lg.com/ae_ar/business/hotel | J103: فندق | HVAC | ال جي الإمارات | K103: 28 | L103: يوفر الحل الفندقي من أنظمة التدفئة والتهوية وتكييف الهواء من إل جي الإمارات طريقة أكثر فعالية للحفاظ على فندقك ممتعًا ومميزًا. | M103: 126 | N103: ['طريقة أكثر فعالية للحفاظ على الفندق الخاص بك ممتعًا'] | O103: 1 | P103: Pass | Q103: https://www.lg.com/ae_ar/business/hotel | S103: Pass | T103: 0% | U103: ['pass'] | V103: [] | W103: 65 | X103: 0 | Y103: 20 | Z103: 15 | AA103: 15 | AB103: 15
A104: MEA | B104: UAE | C104: AE_AR : AE (ar) | D104: 5.0 | E104: PLP | F104: سكن | G104: housing | H104: N | I104: https://www.lg.com/ae_ar/business/residence | J104: سكن | HVAC | ال جي الإمارات | K104: 27 | L104: يوفر الحل السكني من أنظمة التدفئة والتهوية وتكييف الهواء من إل جي الإمارات طريقة أكثر ذكاءً للحفاظ على كفاءة الطاقة في المنزل | M104: 125 | N104: ['طريقة أكثر ذكاءً للحفاظ على كفاءة الطاقة في المنزل'] | O104: 1 | P104: Pass | Q104: https://www.lg.com/ae_ar/business/residence | S104: Pass | T104: 0% | U104: ['pass'] | V104: [] | W104: 65 | X104: 0 | Y104: 20 | Z104: 15 | AA104: 15 | AB104: 15
A105: MEA | B105: UAE | C105: AE_AR : AE (ar) | D105: 5.0 | E105: PLP | F105: indoor ceiling concealed duct | G105: indoor ceiling concealed duct | H105: Y | I105: https://www.lg.com/ae_ar/business/indoor-ceiling-concealed-duct | J105: الوحدات الداخلية: قناة مخفية في السقف | HVAC | ال جي UAE | K105: 56 | L105: يوفر مكيف دكت المخفي داخل السقف من إل جي الإمارات حل تبريد غير مرئي مناسبًا للاستخدامات التي تتطلب جمالاً في الديكورات الداخلية. . | M105: 130 | N105: ['داكت معلق مخفي'] | O105: 1 | P105: Pass | Q105: https://www.lg.com/ae_ar/business/indoor-ceiling-concealed-duct | S105: Pass | T105: 0% | U105: ['pass'] | V105: [] | W105: 85 | X105: 20 | Y105: 20 | Z105: 15 | AA105: 15 | AB105: 15
A106: MEA | B106: UAE | C106: AE_AR : AE (ar) | D106: 5.0 | E106: PLP | F106: indoor ceiling floor | G106: indoor ceiling floor | H106: Y | I106: https://www.lg.com/ae_ar/business/indoor-ceiling-floor | J106: وحدات داخلية: سقف وأرضية قابلة للتحويل | HVAC | ال جي UAE | K106: 57 | L106: يجمع المكيف السقفي والأرضي القابل للتحويل من إل جي الإمارات بين روعة وجمال التصميم العصري والذوق الرفيع الذي يتناسب تمامًا مع البيئة الداخلية. . | M106: 144 | N106: ['الأسقف المعلقة والأرضيات القابلة للتحويل'] | O106: 1 | P106: Pass | Q106: https://www.lg.com/ae_ar/business/indoor-ceiling-floor | S106: Pass | T106: 0% | U106: ['pass'] | V106: [] | W106: 85 | X106: 20 | Y106: 20 | Z106: 15 | AA106: 15 | AB106: 15
A107: MEA | B107: UAE | C107: AE_AR : AE (ar) | D107: 5.0 | E107: PLP | F107: indoor ceiling mounted cassette | G107: indoor ceiling mounted cassette | H107: Y | I107: https://www.lg.com/ae_ar/business/indoor-ceiling-mounted-cassette | J107: وحدات داخلية: كاسيت مثبت على السقف | HVAC | ال جي الإمارات | K107: 58 | L107: يُضفي مكيف كاسيت السقفي من إل جي الإمارات مظهرًا جماليًا على الديكورات الداخلية، كما أنه يوفر بيئة مريحة هادئة تجعله الخيار الأمثل لأداء أعمالك. . | M107: 146 | N107: ['مكيف كاسيت المثبت بالسقف'] | O107: 1 | P107: Pass | Q107: https://www.lg.com/ae_ar/business/indoor-ceiling-mounted-cassette | S107: Pass | T107: 0% | U107: ['pass'] | V107: [] | W107: 85 | X107: 20 | Y107: 20 | Z107: 15 | AA107: 15 | AB107: 15
A108: MEA | B108: UAE | C108: AE_AR : AE (ar) | D108: 5.0 | E108: PLP | F108: indoor console | G108: indoor console | H108: Y | I108: https://www.lg.com/ae_ar/business/indoor-console | J108: الوحدات الداخلية: لوحة مراقبة | HVAC | ال جي الإمارات | K108: 53 | L108: مكيف كونسول من إل جي يوفر تبريدًا فائقًا من الأسفل ليغطي الغرفة بالكامل. استمتع ببيئة هادئة ومريحة للغاية، وتصميم يندمج مع ديكور منزلك. | M108: 135 | N108: ['لوحة تحكم'] | O108: 1 | P108: Pass | Q108: https://www.lg.com/ae_ar/business/indoor-console | S108: Pass | T108: 0% | U108: ['pass'] | V108: [] | W108: 85 | X108: 20 | Y108: 20 | Z108: 15 | AA108: 15 | AB108: 15
A109: MEA | B109: UAE | C109: AE_AR : AE (ar) | D109: 5.0 | E109: PLP | F109: indoor round cassette | G109: indoor round cassette | H109: Y | I109: https://www.lg.com/ae_ar/business/indoor-round-cassette | J109: الوحدات الداخلية: كاسيت دائري | HVAC | ال جي الإمارات | K109: 53 | L109: يوفر مكيف كاسيت المستدير من إل جي الإمارات تدفق هواء مريح بتصميم دائري ممتاز لمساحة داخلية فاخرة. حجم مضغوط ورقيق، لون نقي وأنيق. اكتشف المزيد! | M109: 143 | N109: ['مكيف كاسيت المستدير'] | O109: 1 | P109: Pass | Q109: https://www.lg.com/ae_ar/business/indoor-round-cassette | S109: Pass | T109: 0% | U109: ['pass'] | V109: [] | W109: 85 | X109: 20 | Y109: 20 | Z109: 15 | AA109: 15 | AB109: 15
A110: MEA | B110: UAE | C110: AE_AR : AE (ar) | D110: 5.0 | E110: PLP | F110: indoor wall mounted unit | G110: indoor wall mounted unit | H110: Y | I110: https://www.lg.com/ae_ar/business/indoor-wall-mounted-unit | J110: وحدات داخلية: وحدة مثبتة على الحائط | HVAC | ال جي الإمارات | K110: 59 | L110: يُعد المكيف الجداري من إل جي الإمارات الحل الأمثل لأداء أعمالك في بيئة مريحة تناسب جميع الاستخدامات. . | M110: 102 | N110: ['مكيف جداري'] | O110: 1 | P110: Pass | Q110: https://www.lg.com/ae_ar/business/indoor-wall-mounted-unit | S110: Pass | T110: 0% | U110: ['pass'] | V110: [] | W110: 85 | X110: 20 | Y110: 20 | Z110: 15 | AA110: 15 | AB110: 15
... A127: MEA | B127: Nigeria | C127: AFRICA : NG (en) | D127: 5.0 | E127: PLP | F127: Control Solutions | G127: Control Solutions | H127: Y | I127: https://www.lg.com/africa/business/air-control-solutions | J127: LG CONTROL SOLUTIONS | HVAC | LG Africa Business | K127: 48 | L127: LG Control Solutions offer an array of convenient controls, allowing you to set the perfect temperature for your business environment. | M127: 134 | N127: ['Advanced Air Control Systems for Efficient HVAC Operation'] | O127: 1 | P127: Pass | Q127: https://www.lg.com/africa/business/air-control-solutions | S127: Pass | T127: 0% | U127: ['pass'] | V127: [] | W127: 85 | X127: 20 | Y127: 20 | Z127: 15 | AA127: 15 | AB127: 15
A128: MEA | B128: Nigeria | C128: AFRICA : NG (en) | D128: 5.0 | E128: PLP | F128: Engineering Support | G128: Engineering Support | H128: N | I128: https://www.lg.com/africa/business/air-solution/business-resources/engineering-support | J128: LG Engineering Support | HVAC | LG Air-Solution Business-Resources | K128: 66 | M128: 0 | N128: ['Engineering Support'] | O128: 1 | P128: Pass | Q128: https://www.lg.com/africa/business/air-solution/business-resources/engineering-support | S128: Pass | T128: 0% | U128: ['pass'] | V128: [] | W128: 45 | X128: 0 | Y128: 0 | Z128: 15 | AA128: 15 | AB128: 15
A129: MEA | B129: Nigeria | C129: AFRICA : NG (en) | D129: 5.0 | E129: PLP | F129: Floor Standing | G129: Floor Standing | H129: Y | I129: https://www.lg.com/africa/business/single-split-floor-standing | J129: LG Single Split Floor Standing AC for Powerful Cooling | LG Africa Business | K129: 75 | L129: LG Floor Standing Unit efficiently heats and cools large spaces, providing even temperature distribution while complementing modern interiors. | M129: 142 | N129: ['Floor Standing Unit'] | O129: 1 | P129: Pass | Q129: https://www.lg.com/africa/business/single-split-floor-standing | S129: Pass | T129: 0% | U129: ['pass'] | V129: [] | W129: 65 | X129: 0 | Y129: 20 | Z129: 15 | AA129: 15 | AB129: 15
A130: MEA | B130: Nigeria | C130: AFRICA : NG (en) | D130: 5.0 | E130: PLP | F130: Gateway | G130: Gateway | H130: Y | I130: https://www.lg.com/africa/business/gateway | J130: LG Gateway Solutions for Integrated HVAC Connectivity | LG Africa Business | K130: 74 | L130: LG Modbus Gateway is a solution that easily connects LG products with the existing building system of your business. | M130: 116 | N130: ['Modbus Gateway'] | O130: 1 | P130: Pass | Q130: https://www.lg.com/africa/business/gateway | S130: Pass | T130: 0% | U130: ['pass'] | V130: [] | W130: 65 | X130: 0 | Y130: 20 | Z130: 15 | AA130: 15 | AB130: 15
A131: MEA | B131: Nigeria | C131: AFRICA : NG (en) | D131: 5.0 | E131: PLP | F131: HVAC | G131: HVAC | H131: Y | I131: https://www.lg.com/africa/business/air-solution | J131: LG Air Solution: Advanced HVAC Systems for Businesses | LG Africa Business | K131: 74 | L131: LG HVAC solutions designed for diverse business environments and all climate needs. Discover LG's high-quality, energy-efficient air solutions. | M131: 143 | N131: ['LG HVAC Solutions'] | O131: 1 | P131: Pass | Q131: https://www.lg.com/africa/business/air-solution | S131: Pass | T131: 42% | U131: ['A person touches a tablet screen displaying the LG Lead Portal page. There are icons of email, settings, cloud, and map pointer around the tablet.', 'Four experts are inspecting one of the LG MULTI V i machines installed next to the wall, carefully checking its performance and key components.', 'The three-story hotel with a basement has a perspective drawing. Hydro Kits and MULTI V i are connected to Indoor Units in a room and reception by several pipes.', 'The two-story house has a perspective drawing. Wall Mounted Cassette, One Way Ceiling Cassette, and Ceiling Mounted Cassette emit fresh air. There are palm trees behind the house.', 'The two-story house with a red roof has a perspective drawing. The floor is covered with red pipes, which connect HVAC products. There is a garden in front of the house.'] | V131: [146, 143, 161, 179, 169] | W131: 50 | X131: 0 | Y131: 20 | Z131: 15 | AA131: 15 | AB131: 0
A132: MEA | B132: Nigeria | C132: AFRICA : NG (en) | D132: 5.0 | E132: PLP | F132: HVAC BLOG | G132: HVAC BLOG | H132: N | I132: https://www.lg.com/africa/business/air-solution/blog-list | J132: LG HVAC Insights & Tips | Air Solution Blog | LG Africa Business | K132: 64 | L132: Stay updated with LG’s latest HVAC innovations, expert tips, & real-world insights to help your business choose the right air solutions. | M132: 136 | N132: ['Explore Expert HVAC Articles from LG Air Solution'] | O132: 1 | P132: Pass | Q132: https://www.lg.com/africa/business/air-solution/blog-list | S132: Pass | T132: 0% | U132: ['pass'] | V132: [] | W132: 65 | X132: 0 | Y132: 20 | Z132: 15 | AA132: 15 | AB132: 15
A133: MEA | B133: Nigeria | C133: AFRICA : NG (en) | D133: 5.0 | E133: PLP | F133: HVAC CASE STUDY | G133: HVAC CASE STUDY | H133: N | I133: https://www.lg.com/africa/business/hvac-case-study | J133: Real-World HVAC Case Studies from LG Business Solutions | LG Africa | K133: 67 | L133: Read all about our HVAC projects around the world on LG's HVAC Case Study Center. From office spaces to shopping malls and residential buildings. | M133: 145 | N133: ['CASE STUDY'] | O133: 1 | P133: Pass | Q133: https://www.lg.com/africa/business/hvac-case-study | S133: Pass | T133: 0% | U133: ['pass'] | V133: [] | W133: 65 | X133: 0 | Y133: 20 | Z133: 15 | AA133: 15 | AB133: 15
A134: MEA | B134: Nigeria | C134: AFRICA : NG (en) | D134: 5.0 | E134: PLP | F134: Heating Solution (AWHP) | G134: Heating Solution (AWHP) | H134: Y | I134: https://www.lg.com/africa/business/heating-awhp | J134: Air to Water Heat Pumps - HVAC | Business | LG Global | K134: 53 | L134: LG Air to Water Heat Pumps, THERMA V, is a sustainable heating solution providing heating, cooling and hot water for comfort, replacing gas boilers with renewable technology. | M134: 174 | N134: ['Reliable Air to Water Heat Pump Systems by LG'] | O134: 1 | P134: Pass | Q134: https://www.lg.com/africa/business/hvac/residential-solutions/air-to-water-heat-pumps | S134: Pass | T134: 40% | U134: ['With Black LG THERMA V product, there is a graph showing that the Air-to-Water-Heat-Pumps method can save money over Conventional-Boiler.', 'An installer in front of the LG Therma V heat pump placed on the exterior of a house is facing the couple and explaining the heating solution.', 'An outdoor unit located between a snow-covered brick wall and a two-storied house with wide transparent windows showing through a living room.', 'An outdoor unit located between a snow-covered brick wall and a two-storied house with wide transparent windows showing through a living room.'] | V134: [137, 142, 142, 142] | W134: 35 | X134: 20 | Y134: 0 | Z134: 15 | AA134: 0 | AB134: 0
A135: MEA | B135: Nigeria | C135: AFRICA : NG (en) | D135: 5.0 | E135: PLP | F135: Hospital | G135: Hospital | H135: N | I135: https://www.lg.com/africa/business/hospital | J135: LG HVAC Solutions for Hospitals | Clean & Efficient Air | LG Africa Business | K135: 76 | L135: LG HVAC hospital solution provides comfort and safety for patients staff while making it easy to control and monitor the environment. | M135: 133 | N135: ['Reliable HVAC Systems for Healthcare Facilities'] | O135: 1 | P135: Pass | Q135: https://www.lg.com/africa/business/hospital | S135: Pass | T135: 9% | U135: ['An image of a hospital with thumbnails of a patient room, common areas, an operating room, a radiology room, and a control center.'] | V135: [130] | W135: 50 | X135: 0 | Y135: 20 | Z135: 15 | AA135: 15 | AB135: 0
A136: MEA | B136: Nigeria | C136: AFRICA : NG (en) | D136: 5.0 | E136: PLP | F136: Hot Water Solution (Hydro Kit) | G136: Hot Water Solution (Hydro Kit) | H136: Y | I136: https://www.lg.com/africa/business/hot-water-solution-hydro-kit | J136: LG Hydro Kit: Efficient Hot Water Solutions for Businesses | LG Africa Business | K136: 79 | L136: Hydro kits provide hot water and connect to LG’s Multi V VRF product range.They are compact and require no exhaust to the outside of a boiler as a boiler does. | M136: 159 | N136: ['Hot Water Solution (Hydro Kit)'] | O136: 1 | P136: Pass | Q136: https://www.lg.com/africa/business/hot-water-solution-hydro-kit | S136: Pass | T136: 0% | U136: ['pass'] | V136: [] | W136: 65 | X136: 0 | Y136: 20 | Z136: 15 | AA136: 15 | AB136: 15
A137: MEA | B137: Nigeria | C137: AFRICA : NG (en) | D137: 5.0 | E137: PLP | F137: Hotel | G137: Hotel | H137: N | I137: https://www.lg.com/africa/business/hotel | J137: LG HVAC Solutions for Hotels | Comfort and Efficiency | LG Africa Business | K137: 74 | L137: Enhance guest comfort with LG HVAC solutions tailored for hotels, combining energy efficiency with reliable climate control. | M137: 124 | N137: ['Premium HVAC Systems Designed for Hotel Environments'] | O137: 1 | P137: Pass | Q137: https://www.lg.com/africa/business/hotel | S137: Pass | T137: 0% | U137: ['pass'] | V137: [] | W137: 65 | X137: 0 | Y137: 20 | Z137: 15 | AA137: 15 | AB137: 15
A138: MEA | B138: Nigeria | C138: AFRICA : NG (en) | D138: 5.0 | E138: PLP | F138: Individual Controller | G138: Individual Controller | H138: Y | I138: https://www.lg.com/africa/business/individual-controller | J138: LG Individual Controller | HVAC | LG Africa Business | K138: 52 | L138: LG Individual Controller is designed with an intuitive interface and various setting options for easy and simple management. | M138: 124 | N138: ['Individual Controller'] | O138: 1 | P138: Pass | Q138: https://www.lg.com/africa/business/individual-controller | S138: Pass | T138: 0% | U138: ['pass'] | V138: [] | W138: 85 | X138: 20 | Y138: 20 | Z138: 15 | AA138: 15 | AB138: 15
...

Sheet Blog
B2: Region | C2: Country | D2: URL | E2: Latest Blog Date | F2: No of Blog Past 3 Months | G2: Score
B3: ASIA | C3: Indonesia | D3: https://www.lg.com/id/business/mengenai-lg-air-solution/blog-list/ | E3: 2025-08-22 | F3: 1 | G3: 10 | I3: =_xlfn.XLOOKUP(C3,'Summary (최종)'!C:C,'Summary (최종)'!D:D,0) -> GP1
B4: MEA | C4: Jordan | D4: https://www.lg.com/levant_ar/business/blog-list | E4: 2023-07-25 | F4: 0 | G4: 0 | I4: =_xlfn.XLOOKUP(C4,'Summary (최종)'!C:C,'Summary (최종)'!D:D,0) -> 5.0
B5: EU | C5: UK | D5: https://www.lg.com/uk/business/hvac/hvac-blog-on-air/ | E5: 2025-08-11 | F5: 1 | G5: 10 | I5: =_xlfn.XLOOKUP(C5,'Summary (최종)'!C:C,'Summary (최종)'!D:D,0) -> GP1
B6: LATAM | C6: Chile | D6: https://www.lg.com/cl/business/hvac/blog-list/ | E6: 2025-10-30 | F6: 3 | G6: 10 | I6: =_xlfn.XLOOKUP(C6,'Summary (최종)'!C:C,'Summary (최종)'!D:D,0) -> GP1
B7: ASIA | C7: Australia | D7: https://www.lg.com/au/business/air-solution/air-solutions-blog/ | E7: 2025-08-06 | F7: 2 | G7: 10 | I7: =_xlfn.XLOOKUP(C7,'Summary (최종)'!C:C,'Summary (최종)'!D:D,0) -> GP1
B8: MEA | C8: Egypt | D8: http://www.lg.com/eg_en/business/air-solution/blog-list/ | E8: 2023-06-13 | F8: 0 | G8: 0 | I8: =_xlfn.XLOOKUP(C8,'Summary (최종)'!C:C,'Summary (최종)'!D:D,0) -> GP1
B9: EU | C9: Spain | D9: https://www.lg.com/es/business/display-profesional/casos-de-exito/ | E9: 2024-10-22 | F9: 0 | G9: 0 | I9: =_xlfn.XLOOKUP(C9,'Summary (최종)'!C:C,'Summary (최종)'!D:D,0) -> GP1
B10: LATAM | C10: Colombia | D10: https://www.lg.com/co/business/blog/aire-acondicionado/ | E10: 2025-10-01 | F10: 3 | G10: 10 | I10: =_xlfn.XLOOKUP(C10,'Summary (최종)'!C:C,'Summary (최종)'!D:D,0) -> GP1
B11: MEA | C11: Nigeria | D11: https://www.lg.com/africa/business/air-solution/blog-list | E11: 2025-08-12 | F11: 2 | G11: 10 | I11: =_xlfn.XLOOKUP(C11,'Summary (최종)'!C:C,'Summary (최종)'!D:D,0) -> 5.0
B12: MEA | C12: Turkey | D12: https://www.lg.com/tr/business/iklimlendirme-cozumleri/blog-list/ | E12: 2025-09-30 | F12: 3 | G12: 10 | I12: =_xlfn.XLOOKUP(C12,'Summary (최종)'!C:C,'Summary (최종)'!D:D,0) -> GP1
B13: INDIA | C13: India | D13: https://www.lg.com/in/business/air-solution/blog-list/ | E13: 2025-10-14 | F13: 2 | G13: 10 | I13: =_xlfn.XLOOKUP(C13,'Summary (최종)'!C:C,'Summary (최종)'!D:D,0) -> GP1
B14: EU | C14: Czech | D14: https://www.lg.com/cz/business/klimatizace/blog-list/ | E14: 2025-08-18 | F14: 2 | G14: 10 | I14: =_xlfn.XLOOKUP(C14,'Summary (최종)'!C:C,'Summary (최종)'!D:D,0) -> GP1
... B35: MEA | C35: Kenya | D35: https://www.lg.com/eastafrica/business/air-solution/blog-list | E35: 2025-09-25 | F35: 1 | G35: 10 | I35: =_xlfn.XLOOKUP(C35,'Summary (최종)'!C:C,'Summary (최종)'!D:D,0) -> 5.0

Sheet Feature Card Alt Text Error
B2: COUNTRY | C2: URL | D2: Card Index | E2: Src | F2: SRCset | G2: Alt | H2: Alt Length | I2: Alt Comment
B3: Algeria | C3: https://www.lg.com/dz/business/hydrosplit-duo-ecs-r32 | D3: 5 | E3: /dz/images/business/hydrosplit-duo-ecs-r32/H-A-AS-Hydrosplit-IWT-06-Desktop.jpg | G3: Factories belch dark smog in the background as an LG Smart Inverter unit, encased in a transparent box with a metallic shield, stands on the right. | H3: 147 | I3: exceeds 125 characters
B4: Algeria | C4: https://www.lg.com/dz/business/mono-split | D4: 1 | E4: /dz/images/business/mono-split/lg-hvac-single-split-kv-d.jpg | G4: D챕monstration d'une unit챕 ext챕rieure LG Smart Inverter au centre, accompagn챕e de divers cas d'installation d'unit챕s int챕rieures par l'arri챔re. | H4: 142 | I4: exceeds 125 characters
B5: Algeria | C5: https://www.lg.com/dz/business/mono-split | D5: 2 | E5: /dz/images/business/mono-split/lg-hvac-single-split-what-is-thumb-d.jpg | G5: Du point de vue d'une fourmi, un caf챕 se d챕voile orn챕 de chaises, de tables et de plantes, tandis qu'une cassette round LG est suspendu au plafond. | H5: 147 | I5: exceeds 125 characters
B6: Algeria | C6: https://www.lg.com/dz/business/mono-split | D6: 3 | E6: /dz/images/business/mono-split/lg-hvac-single-split-flexible-compatibility-thumb-d.jpg | G6: Une unit챕 ext챕rieure LG Smart Inverter se trouve 횪 gauche, tandis qu'une unit챕 int챕rieure LG unit챕 sur pieds est install챕e dans la salle 횪 manger 횪 droite. | H6: 155 | I6: exceeds 125 characters
B7: Algeria | C7: https://www.lg.com/dz/business/mono-split | D7: 4 | E7: /dz/images/business/mono-split/lg-hvac-single-split-energy-saving-d.jpg | G7: L'unit챕 d?셞xt챕rieure LG Smart Inverter est pr챕sent챕e avec une section agrandie au centre, r챕v챕lant l'int챕rieur complexe du compresseur Smart Inverter. | H7: 150 | I7: exceeds 125 characters
B8: Algeria | C8: https://www.lg.com/dz/business/mono-split | D8: 5 | E8: /dz/images/business/mono-split/lg-hvac-single-split-reliability-thumb-d.jpg | G8: Les usines crachent une brum챕e sombre en arri챔re-plan alors qu'une unit챕 LG Smart Inverter, encastr챕e dans une bo챤te transparente avec un bouclier m챕tallique, se trouve sur la droite. | H8: 183 | I8: exceeds 125 characters
B9: Algeria | C9: https://www.lg.com/dz/business/mono-split | D9: 6 | E9: /dz/images/business/mono-split/lg-hvac-single-split-lg-thinq-thumb-d.jpg | G9: Un smartphone affichant l'application LG ThinQ se trouve 횪 gauche, connect챕 횪 une unit챕 murale LG install챕e dans un contour 횪 droite via une ligne pointill챕e. | H9: 158 | I9: exceeds 125 characters
B10: Argentina | C10: https://www.lg.com/ar/business/instalaciono-a-piso | D10: 1 | E10: /ar/images/business/floor-standing/lg-hvac-single-split-floor-standing-kv-ideal-for-modern-interiors-d.jpg | G10: The white, rectangular-shaped LG Floor Standing Unit is displayed on the left side of an upscale restaurant, backed by a gold-colored and wood wall. | H10: 148 | I10: exceeds 125 characters
B11: Argentina | C11: https://www.lg.com/ar/business/instalaciono-a-piso | D11: 2 | E11: /ar/images/business/floor-standing/lg-hvac-single-split-floor-standing-stylish-design-d.jpg | G11: LG Floor Standing Unit is positioned in front of a marble pillar in the lobby area of a modern hotel, flanked symmetrically by two plants. | H11: 138 | I11: exceeds 125 characters
B12: Argentina | C12: https://www.lg.com/ar/business/multi-split | D12: 2 | E12: /ar/images/business/lg-multi-split/lg-hvac-multi-split-flexible-installation-d.jpg | G12: Se muestra el cassette de techo LG One Way, con una l챠nea de puntos y una flecha roja que marcan la altura del cuerpo de la unidad de 132 mm. | H12: 141 | I12: exceeds 125 characters
B13: Argentina | C13: https://www.lg.com/ar/business/multi-split | D13: 4 | E13: /ar/images/business/lg-multi-split/lg-hvac-multi-split-lg-thinq-thumb-d.jpg | G13: Un smartphone con la aplicaci처n LG ThinQ se sit첬a a la izquierda, conectado a una unidad LG Wall alojada en un contorno a la derecha a trav챕s de una l챠nea de puntos. | H13: 165 | I13: exceeds 125 characters
B14: Argentina | C14: https://www.lg.com/ar/business/multi-split | D14: 5 | E14: /ar/images/business/lg-multi-split/lg-hvac-multi-split-kv-d.jpg | G14: Una mansi처n de dos plantas muestra cuatro unidades interiores LG a trav챕s de grandes ventanales de cristal, con su flujo de aire perceptible, y una unidad Smart Inverter LG en el exterior. | H14: 188 | I14: exceeds 125 characters
... B24: Argentina | C24: https://www.lg.com/ar/business/s-cassette | D24: 21 | E24: /ar/images/business/s-cassette/lg-hvac-single-split-ceiling-mounted-cassette-4-way-stylish-design-panel-d.jpg | G24: The bottom view of the LG ceiling unit with three key features: a detachable corner, interior fit, and a lineless surface for center ventilation. | H24: 145 | I24: exceeds 125 characters
B25: Argentina | C25: https://www.lg.com/ar/business/soluciones-de-ventilacion | D25: 4 | E25: /ar/images/business/soluciones-de-ventilacion/D04_H-A-AS-ERV-03-1-Desktop.jpg | H25: 0 | I25: not set
B26: Argentina | C26: https://www.lg.com/ar/business/splits-individuales | D26: 1 | E26: /ar/images/business/splits-individuales/lg-hvac-single-split-what-is-thumb-d.jpg | G26: Desde la perspectiva de una hormiga, se despliega una cafeter챠a adornada con sillas, mesas y plantas, mientras en el techo se despliega un casete redondo LG. | H26: 157 | I26: exceeds 125 characters
B27: Argentina | C27: https://www.lg.com/ar/business/splits-individuales | D27: 2 | E27: /ar/images/business/splits-individuales/lg-hvac-single-split-flexible-compatibility-thumb-d.jpg | G27: Una unidad exterior LG Smart Inverter est찼 a la izquierda, mientras que una unidad interior LG Floor Standing est찼 instalada en el comedor a la derecha. | H27: 152 | I27: exceeds 125 characters
B28: Argentina | C28: https://www.lg.com/ar/business/splits-individuales | D28: 3 | E28: /ar/images/business/splits-individuales/lg-hvac-single-split-energy-saving-d.jpg | G28: La unidad exterior Smart Inverter de LG se presenta con una secci처n ampliada en el centro, que revela el complejo interior del compresor Smart Inverter. | H28: 152 | I28: exceeds 125 characters
B29: Argentina | C29: https://www.lg.com/ar/business/splits-individuales | D29: 4 | E29: /ar/images/business/splits-individuales/lg-hvac-single-split-reliability-thumb-d.jpg | G29: En el fondo, las f찼bricas emiten un humo oscuro, mientras a la derecha se ve un Smart Inverter de LG, encerrado en una caja transparente con un escudo met찼lico. | H29: 160 | I29: exceeds 125 characters
B30: Argentina | C30: https://www.lg.com/ar/business/splits-individuales | D30: 6 | E30: /ar/images/business/splits-individuales/lg-hvac-single-split-product-ceiling-mounted-cassette-thumb.jpg | H30: 0 | I30: not set
B31: Argentina | C31: https://www.lg.com/ar/business/splits-individuales | D31: 7 | E31: /ar/images/business/splits-individuales/lg-hvac-single-split-product-round-cassette-thumb.jpg | H31: 0 | I31: not set
B32: Argentina | C32: https://www.lg.com/ar/business/splits-individuales | D32: 8 | E32: /ar/images/business/splits-individuales/lg-hvac-single-split-product-dual-vane-cassette-thumb.jpg | H32: 0 | I32: not set
B33: Argentina | C33: https://www.lg.com/ar/business/splits-individuales | D33: 9 | E33: /ar/images/business/splits-individuales/lg-hvac-single-split-product-ceiling-concealed-duct-thumb.jpg | H33: 0 | I33: not set
B34: Argentina | C34: https://www.lg.com/ar/business/splits-individuales | D34: 10 | E34: /ar/images/business/splits-individuales/lg-hvac-single-split-product-ceiling-suspended-thumb.jpg | H34: 0 | I34: not set
B35: Argentina | C35: https://www.lg.com/ar/business/splits-individuales | D35: 11 | E35: /ar/images/business/splits-individuales/lg-hvac-single-split-kv-d.jpg | G35: Muestra una unidad exterior LG Smart Inverter en el centro, con varios casos de instalaci처n de unidades interiores por detr찼s. | H35: 126 | I35: exceeds 125 characters
B36: Argentina | C36: https://www.lg.com/ar/business/unidad-interior-ducto | D36: 2 | E36: /ar/images/business/unidad-interior-ducto/D02_BG-1600X900-D.jpg | G36: Un videoclip que sigue el viento desde el interior del conducto oculto de techo LG hasta una oficina interior, donde est찼 instalado el conducto. | H36: 144 | I36: exceeds 125 characters
B37: Global | C37: https://www.lg.com/global/business/hvac/commercial-solutions | D37: 9 | E37: /global/images/business/HVAC/commercial-solutions/lg-hvac-commercial-solutions-retail-d.jpeg | G37: Five customer cases: Showrooms, large restaurants, stylish coffee shops, limited space clothing stores, restaurants with hot water washing. | H37: 139 | I37: exceeds 125 characters
B38: Global | C38: https://www.lg.com/global/business/hvac/commercial-solutions/single-split/ceiling-suspended-floor-convertible | D38: 1 | E38: /global/images/lg-hvac-single-split-ceiling-suspended-kv-modern-aesthetics-d.jpg | G38: LG Ceiling Suspended unit, featuring a white body with a black front structure, is mounted on the ceiling adorned with a series of lights. | H38: 138 | I38: exceeds 125 characters
B39: Global | C39: https://www.lg.com/global/business/hvac/commercial-solutions/single-split/ceiling-suspended-floor-convertible | D39: 3 | E39: /global/images/lg-hvac-single-split-ceiling-suspended-two-thermistors-control-optional-d.jpg | G39: The LG Ceiling Suspended unit is located on the left and the controller is centrally positioned on the wall. Each unit has a red, arch-shaped coverage range. | H39: 157 | I39: exceeds 125 characters
B40: Global | C40: https://www.lg.com/global/business/hvac/commercial-solutions/single-split/ceiling-suspended-floor-convertible | D40: 4 | E40: /global/images/lg-hvac-single-split-ceiling-suspended-easy-installation-maintenance-d.jpg | G40: LG Ceiling Suspended features a filter with arrow indicators at the bottom, while the front view shows two red circles indicating screw locations. | H40: 146 | I40: exceeds 125 characters
B41: Global | C41: https://www.lg.com/global/business/hvac/commercial-solutions/single-split/console | D41: 1 | E41: /global/images/lg-hvac-single-split-console-kv-comfortably-cooling-your-space-d.jpg | G41: In a hallway styled area featuring a marble floor, three long-backed black chairs are arranged with an LG Single Split Console displayed between them. | H41: 150 | I41: exceeds 125 characters
B42: Global | C42: https://www.lg.com/global/business/hvac/commercial-solutions/single-split/console | D42: 2 | E42: /global/images/lg-hvac-single-split-console-5-step-vane-control-d.jpg | G42: Mounted on the wall adjacent to a pair of outdoor chairs, the LG Single Split Console disperses visible air flow into five different stages. | H42: 140 | I42: exceeds 125 characters
B43: Global | C43: https://www.lg.com/global/business/hvac/residential-solutions/residential-erv-ventilation | D43: 1 | E43: /global/images/business/ventilation-solution-residential-erv/lg-hvac-residential-erv-ventilation-solution-kv-breathe-easy-home-d.jpg | G43: LG's white box-shaped residential ERV unit features two circular ventilation ducts positioned on the front panel's top corners. | H43: 127 | I43: exceeds 125 characters
B44: Global | C44: https://www.lg.com/global/business/hvac/residential-solutions/residential-erv-ventilation | D44: 2 | E44: /global/images/business/ventilation-solution-residential-erv/lg-hvac-residential-erv-ventilation-solution-kv-breathe-easy-home-livingroom-d.jpg | G44: A woman sits on a chair in the living room with a couch. Twin air ducts on the ceiling cleanse the space, replacing pollution with clean blue air. | H44: 146 | I44: exceeds 125 characters
B45: Global | C45: https://www.lg.com/global/business/hvac/residential-solutions/residential-erv-ventilation | D45: 6 | E45: /global/images/business/ventilation-solution-residential-erv/lg-hvac-residential-erv-ventilation-energy-saving-home-d.jpg | G45: LG residential ERV unit from the top, two ventilation ducts on each side are blowing and absorbing air from the outside and inside of the residence. | H45: 148 | I45: exceeds 125 characters
B46: Global | C46: https://www.lg.com/global/business/hvac/residential-solutions/residential-erv-ventilation | D46: 8 | E46: /global/images/business/ventilation-solution-residential-erv/lg-hvac-residential-erv-ventilation-total-control-anytime-anywhere-d.jpg | G46: An LG wall-mounted controller displays dust levels, paired with a smartphone on the right showing an air quality history page. | H46: 126 | I46: exceeds 125 characters
B47: Global | C47: https://www.lg.com/global/business/ventilation-solution-erv | D47: 4 | E47: /global/images/H-A-AS-ERV-03-1-Desktop.jpg | H47: 0 | I47: not set
B48: Greece | C48: https://www.lg.com/gr/business/air-cooled-scroll-chiller | D48: 7 | E48: /gr/images/business/air-cooled-scroll-chiller/lg-hvac-chiller-inverter-scroll-chiller-2024-powerful-heating-performance-thumb-d.jpg | G48: ?館慣 觀恝館?菅館? ?貫郭館恝 ?恝? ??恝菅?琯官恝? LG Inverter Scroll Chiller 灌琯官?館琯菅 ?菅? 罐??琯? 琯菅??灌恝? 觀慣菅 琯刮?灌恝? 慣琯?官恝? ?恝? ??館灌串恝館?慣菅 ?琯 關琯?慣貫貫菅觀恝?? ??貫冠館琯?. | H48: 141 | I48: exceeds 125 characters
B49: Greece | C49: https://www.lg.com/gr/business/air-cooled-scroll-chiller | D49: 8 | E49: /gr/images/business/air-cooled-scroll-chiller/lg-hvac-chiller-inverter-scroll-chiller-2024-cooling-thumb-d.jpg | G49: 課恝 LG Inverter Scroll Chiller 琯關?慣館官瓘琯?慣菅 ?琯 關菅慣 ?慣?郭??慣 關琯 串館慣 ?菅恝館菅?關串館恝 棺恝?館? ??恝 ??館?恝, 灌官?貫慣 ?琯 串館慣 款?郭?管關慣 ??款觀?菅?管? 罐琯?關恝觀?慣?菅?館 關琯 關?貫琯 灌菅慣棺慣罐關官?琯菅?. 課恝 LG Inverter Scroll Chiller 琯關?慣館官瓘琯?慣菅 ?琯 關菅慣 ?慣?郭??慣 關琯 串館慣 慣??菅觀? ?恝?官恝 ??恝 管貫菅恝棺慣?官貫琯關慣, 灌官?貫慣 ?琯 串館慣 款?郭?管關慣 ??款觀?菅?管? 罐琯?關恝觀?慣?菅?館 關琯 觀?觀觀菅館琯? 灌菅慣棺慣罐關官?琯菅?. | H49: 322 | I49: exceeds 125 characters
B50: Greece | C50: https://www.lg.com/gr/business/air-cooled-scroll-chiller | D50: 10 | E50: /gr/images/business/air-cooled-scroll-chiller/lg-hvac-chiller-inverter-scroll-chiller-2024-gwp-comparison-d.jpg | G50: ?菅觀?館慣 ??款觀?菅?管? ?恝? ??館慣關菅觀恝? ??琯?罐串?關慣館?管? ?恝? ?貫慣館冠?管 (GWP) ??館 ??觀?菅觀?館 關串??館 R410A 觀慣菅 R32, 灌官?貫慣 ?琯 灌?恝 關恝館郭灌琯? ??刮管? LG 關??恝??郭 慣?? 串館慣 ???菅觀? ??館?恝. | H50: 156 | I50: exceeds 125 characters
B51: Greece | C51: https://www.lg.com/gr/business/air-cooled-scroll-chiller | D51: 11 | E51: /gr/images/business/air-cooled-scroll-chiller/lg-hvac-chiller-inverter-scroll-chiller-2024-contact-us-d.jpg | G51: ??恝 琯菅觀恝館菅觀郭 ?慣?郭罐??慣 恝貫恝款?慣關關郭??館 ?慣 恝?恝官慣 ??館恝關菅貫恝?館 觀慣菅 琯?菅觀恝菅館?館恝?館 關慣瓘官 關慣? 慣菅??恝?館?慣菅 灌官?貫慣 ??恝館 ?恝?管?? ??恝貫恝款菅??冠 觀慣菅 ?恝?恝罐琯?恝?館?慣菅 ?串?菅慣 ?官?? ?恝??. | H51: 155 | I51: exceeds 125 characters
B52: Greece | C52: https://www.lg.com/gr/business/air-cooled-scroll-chiller | D52: 12 | E52: /gr/images/business/air-cooled-scroll-chiller/lg-hvac-chiller-inverter-scroll-chiller-2024-ultimate-efficiency-with-hipor-thumb-d.jpg | G52: ?館慣 灌菅郭款?慣關關慣 灌琯官?館琯菅 ?管 ?恝冠 ??觀?菅觀恝? 關串?恝? 觀慣菅 貫慣灌菅恝? 關串?? ?恝? LG Inverter Scroll Chiller 關琯 棺串貫管 ?恝? ??恝灌琯菅觀館?恝?館 ?管 灌菅琯?罐?館?管. | H52: 129 | I52: exceeds 125 characters
B53: Greece | C53: https://www.lg.com/gr/business/air-solution | D53: 2 | E53: /gr/images/business/hvac/D04-01_lg-hvac-main-expertise.jpg | G53: ?館慣 郭?恝關恝 慣觀恝?關?郭 ?管館 恝罐?館管 琯館?? tablet ?恝? 琯關?慣館官瓘琯菅 ?管 ?琯貫官灌慣 LG Lead Portal. 跨?郭??恝?館 琯菅觀恝館官灌菅慣 關琯 email, ??罐關官?琯菅?, cloud 觀慣菅 灌琯官觀?管 ?郭??管 款??? 慣?? ?恝 tablet. | H53: 162 | I53: exceeds 125 characters
B54: Greece | C54: https://www.lg.com/gr/business/air-solution | D54: 3 | E54: /gr/images/business/hvac/D04-02_lg-hvac-main-commitment.jpg | G54: 課串??琯?菅? 琯菅灌菅觀恝官 琯?菅罐琯??恝?館 串館慣 慣?? ?慣 關管?慣館冠關慣?慣 LG MULTI V i ?恝? 琯官館慣菅 琯款觀慣?琯??管關串館慣 灌官?貫慣 ??恝館 ?恝官?恝, 琯貫串款?恝館?慣? ??恝?琯觀?菅觀郭 ?管館 慣??灌恝?管 觀慣菅 ?慣 棺慣?菅觀郭 琯刮慣??冠關慣?郭 ?恝?. | H54: 168 | I54: exceeds 125 characters
B55: Greece | C55: https://www.lg.com/gr/business/air-solution | D55: 5 | E55: /gr/images/business/hvac/D06-01_lg-hvac-main-commercial-solutions-d.png | G55: 課恝 ??菅??恝?恝 刮琯館恝灌恝?琯官恝 關琯 ???款琯菅恝 串?琯菅 串館慣 ??恝恝??菅觀? ??串灌菅恝. Hydro Kits 觀慣菅 MULTI V i ??館灌串恝館?慣菅 關琯 琯???琯?菅觀串? 關恝館郭灌琯? ?琯 串館慣 灌?關郭?菅恝 觀慣菅 ??管 ?琯?琯?菅?館 關琯 灌菅觀??恝 ??貫管館??琯?館. | H55: 172 | I55: exceeds 125 characters
B56: Greece | C56: https://www.lg.com/gr/business/air-solution | D56: 6 | E56: /gr/images/business/hvac/D07-01_lg-hvac-main-residential-solutions-d.png | G56: ? 灌菅??恝?管 觀慣?恝菅觀官慣 串?琯菅 串館慣 ??恝恝??菅觀? ??串灌菅恝. ??菅?恝官?菅慣 觀慣?串?慣, 觀慣?串?慣 恝?恝?冠? 關恝館冠? 觀慣?琯?罐?館?管? 觀慣菅 觀慣?串?慣 琯款觀慣?琯??管關串館管 ??管館 恝?恝?冠 琯觀?串關?恝?館 ??串?觀恝 慣串?慣. 跨?郭??恝?館 ?恝菅館菅觀?灌琯館??慣 ?官?? 慣?? ?管館 觀慣?恝菅觀官慣. | H56: 200 | I56: exceeds 125 characters
B57: Greece | C57: https://www.lg.com/gr/business/air-solution | D57: 7 | E57: /gr/images/business/hvac/D08-01_lg-hvac-main-control-solutions-d.png | G57: ? 灌菅??恝?管 觀慣?恝菅觀官慣 關琯 觀?觀觀菅館管 ??串款管 串?琯菅 串館慣 ??恝恝??菅觀? ??串灌菅恝. 課恝 灌郭?琯灌恝 琯官館慣菅 觀慣貫?關關串館恝 關琯 觀?觀觀菅館恝 灌官觀??恝 ??貫管館??琯?館 , ?恝? ??館灌串恝?館 ??恝??館?慣 HVAC. 跨?郭??琯菅 串館慣? 觀冠?恝? 關??恝??郭 慣?? ?管館 觀慣?恝菅觀官慣. | H57: 192 | I57: exceeds 125 characters
B58: Greece | C58: https://www.lg.com/gr/business/air-to-water-heat-pumps | D58: 3 | E58: /gr/images/business/heating-solution-awhp/lg-hvac-air-to-water-heat-pumps-annual-cost-saving-d.jpg | G58: ?琯 ?管 關慣??管 ???觀琯?冠 LG THERMA V, ??郭??琯菅 串館慣 款?郭?管關慣 ?恝? 灌琯官?館琯菅 ??菅 管 貫??管 ??館 慣館?貫菅?館 罐琯?關??管?慣? 慣串?慣/館琯?恝? 關?恝?琯官 館慣 琯刮恝菅觀恝館恝關冠?琯菅 ??冠關慣?慣 ?琯 ??串?管 關琯 ?恝館 ??關棺慣?菅觀? 貫串棺管?慣. | H58: 175 | I58: exceeds 125 characters
B59: Greece | C59: https://www.lg.com/gr/business/air-to-water-heat-pumps | D59: 4 | E59: /gr/images/business/heating-solution-awhp/lg-hvac-air-to-water-heat-pumps-easy-install-maintenance-d.jpg | G59: ?館慣? ?琯?館菅觀?? 琯款觀慣?郭??慣?管? 關??恝??郭 慣?? 關菅慣 慣館?貫官慣 罐琯?關??管?慣? LG Therma V ?恝? 棺?官?觀琯?慣菅 ??恝 琯刮??琯?菅觀? ?恝? ??菅?菅恝? 琯官館慣菅 ???慣關關串館恝? ??恝? ?恝 瓘琯?款郭?菅 觀慣菅 琯刮管款琯官 ?管 貫??管 罐串?關慣館?管?. | H59: 175 | I59: exceeds 125 characters
... B100: Israel | C100: https://www.lg.com/il/business/air-solution/commercial-solutions/chiller/air-cooled-inverter-scroll-chiller | D100: 4 | E100: /il/images/business/HVAC/air-cooled-inverter-scroll-chiller/D09_lg-hvac-chiller-inverter-scroll-chiller-2024-cooling-d.jpg | G100: LG Inverter Scroll Chiller ??屢? 鬧? ?? 鬧? ?淚 ??漏?? ?淚樓鬧, ?屢? ???瘻 ?漏???瘻 ??壘淚??淚? 鬧? 漏?壘?鬧?? ??????. LG Inverter Scroll Chiller ??屢? 鬧? ?? 鬧? ??龍 漏樓?鬧? 鬧?淚??? ?淚樓鬧, ?屢? ???瘻 ?漏???瘻 ??壘淚??淚? 鬧? 漏?壘?鬧?? ??????. | H100: 207 | I100: exceeds 125 characters
B101: Israel | C101: https://www.lg.com/il/business/ventilation-solution-erv | D101: 4 | E101: /il/images/business/ventilation-solution-erv/new/D04_H-A-AS-ERV-03-1-Desktop.jpg | H101: 0 | I101: not set
B102: Jordan | C102: https://www.lg.com/levant_ar/business/multi-v-i | D102: 4 | E102: /levant_ar/images/business/multi-v-i/lg-hvac-vrf-system-multi-v-i-mea-energy-saving-thumb-d.jpg | G102: ??彎??幕 碼?邈卍? 碼?磨?碼?? 碼??卍磨馬 碼??痲??馬 碼??卍魔?膜?馬 ?魔???邈 碼?慢碼?馬 (碼??幕?邈 巒) ??碼磨? 碼?粒?碼? (碼??幕?邈 卍)? ?晩 ?寞?膜 漠慢 粒漠彎邈 ??彎幕 碼?魔?膜? ?? 0 瑪?? 100% 磨幕??? 碼???? 30. | H102: 153 | I102: exceeds 125 characters
B103: Jordan | C103: https://www.lg.com/levant_ar/business/single-packaged-air-solution | D103: 6 | E103: /levant_ar/images/air-solution/single-packaged/single-packaged-2024-direct-drive-motor-product-d.jpg | G103: ??挽邈 ??慢晩? ??幕膜馬 Single Package ?卍?慢 碼?彎?立 晩?? 晩寞?馬 碼??邈?幕馬. ???娩?邈 碼??巒 碼??晩邈?彎 瑪?? 粒?? "?碼 魔?寞膜 ?慢晩 瑪彎碼??馬 (?慢晩 粒?? ?魔?碼??? 晩?碼?馬 粒??)". | H103: 138 | I103: exceeds 125 characters
B104: Kenya | C104: https://www.lg.com/eastafrica/business/multi-split | D104: 4 | E104: /eastafrica/images/business/multi-split/lg-hvac-multi-split-multiple-indoor-units-thumb-d.jpg | G104: An LG Ceiling Mounted Cassette circulates visible airflow in a spacious, warm-toned living room filled with a sofa, table, and trees. | H104: 133 | I104: exceeds 125 characters
B105: Kenya | C105: https://www.lg.com/eastafrica/business/retrofit-solution | D105: 3 | E105: /eastafrica/images/business/homeowner/D04_B2B-HA-AS-For-Homeowners-07-Service-Warranty-desktop.jpg | H105: 0 | I105: not set
B106: Kenya | C106: https://www.lg.com/eastafrica/business/ventilation-solution-erv | D106: 4 | E106: /eastafrica/images/H-A-AS-ERV-03-1-Desktop.jpg | H106: 0 | I106: not set
B107: Nigeria | C107: https://www.lg.com/africa_fr/business/hvac | D107: 2 | E107: /africa_fr/images/business/air-solution/04-01_lg-hvac-main-expertise.jpg | G107: Une personne touche l?쇒쯢ran d?셵ne table qui affiche la page du Portail LG Lead. Des ic척nes pour les e-mails, param챔tres, Cloud et le curseur de carte apparaissent autour de la tablette. | H107: 185 | I107: exceeds 125 characters
B108: Nigeria | C108: https://www.lg.com/africa_fr/business/hvac | D108: 3 | E108: /africa_fr/images/business/air-solution/04-02_lg-hvac-main-commitment.jpg | G108: Quatre experts inspectent l?셵ne des machines LG MULTI V i install챕es pr챔s du mur, examinant en d챕tail ses performances et composants cl챕s. | H108: 138 | I108: exceeds 125 characters
B109: Nigeria | C109: https://www.lg.com/africa_fr/business/hvac | D109: 5 | E109: /africa_fr/images/business/air-solution/lg-hvac-main-commercial-solutions-d.png | G109: L?셡척tel 횪 trois 챕tages avec sous-sol pr챕sente un dessin en perspective. Des kits Hydro et MULTI V i sont connect챕s par des unit챕s int챕rieures dans une pi챔ce et la r챕ception par plusieurs tuyaux. | H109: 194 | I109: exceeds 125 characters
B110: Nigeria | C110: https://www.lg.com/africa_fr/business/hvac | D110: 6 | E110: /africa_fr/images/business/air-solution/lg-hvac-main-residential-solutions-d.png | G110: La maison 횪 deux 챕tages pr챕sente un dessin en perspective. Une cassette fix챕e au mur, une cassette de plafond unidirectionnelle et une cassette fix챕e au plafond diffusent de l?셙ir frais. Il y a des palmiers derri챔re une maison. | H110: 227 | I110: exceeds 125 characters
B111: Nigeria | C111: https://www.lg.com/africa_fr/business/hvac | D111: 7 | E111: /africa_fr/images/business/air-solution/lg-hvac-main-control-solutions-d.png | G111: La maison 횪 deux 챕tages avec un toit rouge pr챕sente un dessin en perspective. Le sol est couvert de tuyaux rouges, qui connectent des produits HVAC. On voit un jardin devant la maison. | H111: 184 | I111: exceeds 125 characters
B112: Nigeria | C112: https://www.lg.com/africa_fr/business/hvac | D112: 12 | E112: /africa_fr/images/business/air-solution/lg-hvac-main-inquire-to-buy-d.jpg | G112: Deux fen챗tres hologrammes virtuelles pour le Tchat et Nous contacter flottant 횪 c척t챕 de l?셭rdinateur portable et des mains sont plac챕es derri챔re elles. | H112: 151 | I112: exceeds 125 characters
B113: Nigeria | C113: https://www.lg.com/africa_fr/business/multi-split | D113: 1 | E113: /africa_fr/images/business/multi-split/D02-01_lg-hvac-multi-split-kv-d.jpg | G113: A two-story mansion showcases four LG indoor units through large glass windows, their airflow discernible, with an LG Smart Inverter unit outside. | H113: 146 | I113: exceeds 125 characters
B114: Nigeria | C114: https://www.lg.com/africa_fr/business/multi-split | D114: 3 | E114: /africa_fr/images/business/multi-split/D09-01_lg-hvac-multi-split-multiple-indoor-units-thumb-d.jpg | G114: An LG Ceiling Mounted Cassette circulates visible airflow in a spacious, warm-toned living room filled with a sofa, table, and trees. | H114: 133 | I114: exceeds 125 characters
B115: Nigeria | C115: https://www.lg.com/africa_fr/business/multi-split | D115: 4 | E115: /africa_fr/images/business/multi-split/D10-01_lg-hvac-multi-split-lg-thinq-thumb-d.jpg | G115: A smartphone showing the LG ThinQ app sits on the left, connected to an LG Wall-mounted unit housed in an outline on the right via a dotted line. | H115: 145 | I115: exceeds 125 characters
B116: Nigeria | C116: https://www.lg.com/africa_fr/business/single-split | D116: 1 | E116: /africa_fr/images/business/air-control-solutions/single-split/lg-hvac-single-split-kv-d.jpg | G116: D챕monstration d'une unit챕 ext챕rieure LG Smart Inverter au centre, accompagn챕e de divers cas d'installation d'unit챕s int챕rieures par l'arri챔re. | H116: 142 | I116: exceeds 125 characters
B117: Nigeria | C117: https://www.lg.com/africa_fr/business/single-split | D117: 2 | E117: /africa_fr/images/business/air-control-solutions/single-split/lg-hvac-single-split-what-is-thumb-d.jpg | G117: Du point de vue d'une fourmi, un caf챕 se d챕voile orn챕 de chaises, de tables et de plantes, tandis qu'une cassette round LG est suspendu au plafond. | H117: 147 | I117: exceeds 125 characters
B118: Nigeria | C118: https://www.lg.com/africa_fr/business/single-split | D118: 3 | E118: /africa_fr/images/business/air-control-solutions/single-split/lg-hvac-single-split-flexible-compatibility-thumb-d.jpg | G118: Une unit챕 ext챕rieure LG Smart Inverter se trouve 횪 gauche, tandis qu'une unit챕 int챕rieure LG unit챕 sur pieds est install챕e dans la salle 횪 manger 횪 droite. | H118: 155 | I118: exceeds 125 characters
... B138: UAE | C138: https://www.lg.com/ae/business/hvac/commercial-solutions/vrf-system | D138: 6 | E138: /ae/images/business/hvac/lg-hvac-vrf-system-vrf-renewal-service.jpg | G138: An installer wearing a safety helmet and glasses tries to separate the front panel of the Ceiling Mounted Cassette installed on the ceiling. | H138: 140 | I138: exceeds 125 characters

Sheet Product Category
A1: ◀ | B1: Product Category
B3: ○: existing / X: missing / N/A: not applicable | E3: GR-gr | F3: UK-en | G3: PL-pl | H3: HU-hu | I3: CZ-cz | J3: FR-fr | K3: DE-de | L3: ES-es | M3: 제외 | N3: LEVANT-ar | O3: LEVANT-en | P3: TR-tr | Q3: AE-ar | R3: AE-en | S3: EG-en | T3: EG-ar | U3: SA-ar | V3: SA-en | W3: EASTAFRICA-en | X3: ZA-en | Y3: AFRICA-en | Z3: AFRICA-fr | AA3: IL-he | AB3: DZ-fr | AC3: CA-en | AD3: CA-fr | AE3: PA-es | AF3: MX-es | AG3: PE-es | AH3: BR-pt | AI3: AR-es | AJ3: CL-es | AK3: CO-es | AL3: IN-en | AM3: VN-vi | AN3: PH-en | AO3: ID-id | AP3: AU-en | AQ3: TH-th | AR3: SG-en | AS3: CN-zh
E4: 0 | F4: 0 | G4: 0 | H4: 0 | I4: 0 | J4: 1 | K4: 0 | M4: 4 | N4: 0 | O4: 0 | P4: 0 | Q4: 0 | R4: 0 | S4: 0 | U4: 0 | V4: 0 | W4: 0 | X4: 0 | Y4: 0 | Z4: 2 | AC4: 0 | AD4: 0 | AE4: 0 | AF4: 0 | AG4: 3 | AH4: 0 | AI4: 1 | AJ4: 6 | AK4: 0 | AL4: 0 | AM4: 0 | AN4: 0 | AO4: 0 | AP4: 0 | AQ4: 0 | AR4: 0 | AS4: 0
B5: Products | E5: EU | M5: CIS | N5: MEA | AC5: NA | AE5: LATAM | AL5: INDIA | AM5: ASIA
E6: LGEHS | F6: LGEUK | G6: LGEPL | H6: LGEMK | I6: LGECZ | J6: LGEFS | K6: LGEDG | L6: LGEES | M6: LGERA | N6: LGELF | P6: LGETK | Q6: LGEGF | S6: LGEEG | U6: LGESJ | W6: LGEEF | X6: LGESA | Y6: LGEAF | AA6: LGEYK | AB6: LGEAS | AC6: LGECI | AE6: LGEPS | AF6: LGEMS | AG6: LGEPR | AH6: LGESP | AI6: LGEAR | AJ6: LGECL | AK6: LGECB | AL6: LGEIL | AM6: LGEVH | AN6: LGEPH | AO6: LGEIN | AP6: LGEAP | AQ6: LGETH | AR6: LGESL | AS6: LGECH
E7: Greece | F7: UK | G7: Poland | H7: Hungary | I7: Czech | J7: France | K7: Germany | L7: Spain | M7: Ukraine | N7: Jordan | P7: Turkey | Q7: UAE | S7: Egypt | U7: SaudiArabia | W7: Kenya | X7: SouthAfrica | Y7: Nigeria | AA7: Israel | AB7: Algeria | AC7: Canada | AE7: Panama | AF7: Mexico | AG7: Peru | AH7: Brazil | AI7: Argentina | AJ7: Chile | AK7: Colombia | AL7: India | AM7: Vietnam | AN7: Philippines | AO7: Indonesia | AP7: Australia | AQ7: Thailand | AR7: Singapore | AS7: China
E8: Greek | F8: English | G8: Polish | H8: Hungarian | I8: Czech | J8: French | K8: German | L8: Spanish | M8: Ukraine | N8: Arabic | O8: English | P8: Turkish | Q8: Arabic | R8: English | S8: English | T8: Arabic | U8: Arabic | V8: English | W8: English | X8: English | Y8: English | Z8: French | AA8: Hebrew | AB8: French | AC8: English | AD8: French | AE8: Spanish | AF8: Spanish | AG8: Spanish | AH8: Portuguese | AI8: Spanish | AJ8: Spanish | AK8: Spanish | AL8: English | AM8: Vietnamese | AN8: English | AO8: Indonesian | AP8: English | AQ8: Thai | AR8: English | AS8: Chinese
E9: GR : GR (el) | F9: UK : GB (en) | G9: PL : PL (pl) | H9: HU : HU (hu) | I9: CZ : CZ (cs) | J9: FR : FR (fr) | K9: DE : DE (de) | L9: ES : ES (es) | M9: Ukraine | N9: LEVANT_AR : JO (ar) | O9: LEVANT_EN : JO (en) | P9: TR : TR (tr) | Q9: AE_AR : AE (ar) | R9: AE : AE (en) | S9: EG_EN : EG (en) | T9: EG_AR : EG (ar) | U9: SA : SA (ar) | V9: SA_EN : SA (en) | W9: EASTAFRICA : KE (en) | X9: ZA : ZA (en) | Y9: AFRICA : NG (en) | Z9: AFRICA_FR : NG (fr) | AA9: IL : IL (iw) | AB9: DZ : DZ (fr) | AC9: CA_EN : CA (en) | AD9: CA_FR : CA (fr) | AE9: PA : PA (es) | AF9: MX : MX (es) | AG9: PE : PE (es) | AH9: BR : BR (pt) | AI9: AR : AR (es) | AJ9: CL : CL (es) | AK9: CO : CO (es) | AL9: IN : IN (en) | AM9: VN : VN (vi) | AN9: PH : PH (en) | AO9: ID : ID (in) | AP9: AU : AU (en) | AQ9: TH : TH (th) | AR9: SG : SG (en) | AS9: CN : CN (zh) | BY9: Reference Page(5.0) | BZ9: Reference Page(GP1) | CA9: Remark
B10: VRF | D10: MULTI V 5 | E10: {=IF(E74<>"", E74, IF(SUMPRODUCT(--(PLP_BUSINESS!$C$3:$C$2925=E$9)*(--(LOWER(PLP_BUSINESS!$G$3:$G$2925)=$AU10:$BY10)))>0,"O","X"))} -> N/A | F10: {=IF(F74<>"", F74, IF(SUMPRODUCT(--(PLP_BUSINESS!$C$3:$C$2925=F$9)*(--(LOWER(PLP_BUSINESS!$G$3:$G$2925)=$AU10:$BY10)))>0,"O","X"))} -> N/A | G10: {=IF(G74<>"", G74, IF(SUMPRODUCT(--(PLP_BUSINESS!$C$3:$C$2925=G$9)*(--(LOWER(PLP_BUSINESS!$G$3:$G$2925)=$AU10:$BY10)))>0,"O","X"))} -> N/A | H10: {=IF(H74<>"", H74, IF(SUMPRODUCT(--(PLP_BUSINESS!$C$3:$C$2925=H$9)*(--(LOWER(PLP_BUSINESS!$G$3:$G$2925)=$AU10:$BY10)))>0,"O","X"))} -> N/A | I10: {=IF(I74<>"", I74, IF(SUMPRODUCT(--(PLP_BUSINESS!$C$3:$C$2925=I$9)*(--(LOWER(PLP_BUSINESS!$G$3:$G$2925)=$AU10:$BY10)))>0,"O","X"))} -> N/A | J10: {=IF(J74<>"", J74, IF(SUMPRODUCT(--(PLP_BUSINESS!$C$3:$C$2925=J$9)*(--(LOWER(PLP_BUSINESS!$G$3:$G$2925)=$AU10:$BY10)))>0,"O","X"))} -> N/A | K10: {=IF(K74<>"", K74, IF(SUMPRODUCT(--(PLP_BUSINESS!$C$3:$C$2925=K$9)*(--(LOWER(PLP_BUSINESS!$G$3:$G$2925)=$AU10:$BY10)))>0,"O","X"))} -> N/A | L10: {=IF(L74<>"", L74, IF(SUMPRODUCT(--(PLP_BUSINESS!$C$3:$C$2925=L$9)*(--(LOWER(PLP_BUSINESS!$G$3:$G$2925)=$AU10:$BY10)))>0,"O","X"))} -> N/A | ... AS10: {=IF(AS74<>"", AS74, IF(SUMPRODUCT(--(PLP_BUSINESS!$C$3:$C$2925=AS$9)*(--(LOWER(PLP_BUSINESS!$G$3:$G$2925)=$AU10:$BY10)))>0,"O","X"))} -> O | AU10: multi v 5 | AV10: multi v5 | AW10: multi v 5 air conditioning system | AX10: multi v 5 mvs | AY10: multi v 5 pro | AZ10: fill | BA10: fill | BB10: fill | BC10: fill | BD10: fill | BE10: fill | BF10: fill | BG10: fill | BH10: fill | BI10: fill | BJ10: fill | BK10: fill | BL10: fill | BM10: fill | BN10: fill | BO10: fill | BP10: fill | BQ10: fill | BR10: fill | BS10: fill | BT10: fill | BU10: fill | BV10: fill | BW10: fill
D11: MULTI V i | E11: {=IF(E75<>"", E75, IF(SUMPRODUCT(--(PLP_BUSINESS!$C$3:$C$2925=E$9)*(--(LOWER(PLP_BUSINESS!$G$3:$G$2925)=$AU11:$BY11)))>0,"O","X"))} -> O | F11: {=IF(F75<>"", F75, IF(SUMPRODUCT(--(PLP_BUSINESS!$C$3:$C$2925=F$9)*(--(LOWER(PLP_BUSINESS!$G$3:$G$2925)=$AU11:$BY11)))>0,"O","X"))} -> O | G11: {=IF(G75<>"", G75, IF(SUMPRODUCT(--(PLP_BUSINESS!$C$3:$C$2925=G$9)*(--(LOWER(PLP_BUSINESS!$G$3:$G$2925)=$AU11:$BY11)))>0,"O","X"))} -> O | H11: {=IF(H75<>"", H75, IF(SUMPRODUCT(--(PLP_BUSINESS!$C$3:$C$2925=H$9)*(--(LOWER(PLP_BUSINESS!$G$3:$G$2925)=$AU11:$BY11)))>0,"O","X"))} -> O | I11: {=IF(I75<>"", I75, IF(SUMPRODUCT(--(PLP_BUSINESS!$C$3:$C$2925=I$9)*(--(LOWER(PLP_BUSINESS!$G$3:$G$2925)=$AU11:$BY11)))>0,"O","X"))} -> O | J11: {=IF(J75<>"", J75, IF(SUMPRODUCT(--(PLP_BUSINESS!$C$3:$C$2925=J$9)*(--(LOWER(PLP_BUSINESS!$G$3:$G$2925)=$AU11:$BY11)))>0,"O","X"))} -> O | K11: {=IF(K75<>"", K75, IF(SUMPRODUCT(--(PLP_BUSINESS!$C$3:$C$2925=K$9)*(--(LOWER(PLP_BUSINESS!$G$3:$G$2925)=$AU11:$BY11)))>0,"O","X"))} -> O | L11: {=IF(L75<>"", L75, IF(SUMPRODUCT(--(PLP_BUSINESS!$C$3:$C$2925=L$9)*(--(LOWER(PLP_BUSINESS!$G$3:$G$2925)=$AU11:$BY11)))>0,"O","X"))} -> O | ... AS11: {=IF(AS75<>"", AS75, IF(SUMPRODUCT(--(PLP_BUSINESS!$C$3:$C$2925=AS$9)*(--(LOWER(PLP_BUSINESS!$G$3:$G$2925)=$AU11:$BY11)))>0,"O","X"))} -> N/A | AU11: multi v i | AV11: multi v i upward blowing | AW11: multi vi | AX11: fill | AY11: fill | AZ11: fill | BA11: fill | BB11: fill | BC11: fill | BD11: fill | BE11: fill | BF11: fill | BG11: fill | BH11: fill | BI11: fill | BJ11: fill | BK11: fill | BL11: fill | BM11: fill | BN11: fill | BO11: fill | BP11: fill | BQ11: fill | BR11: fill | BS11: fill | BT11: fill | BU11: fill | BV11: fill | BW11: fill
D12: MULTI V S | E12: {=IF(E76<>"", E76, IF(SUMPRODUCT(--(PLP_BUSINESS!$C$3:$C$2925=E$9)*(--(LOWER(PLP_BUSINESS!$G$3:$G$2925)=$AU12:$BY12)))>0,"O","X"))} -> O | F12: {=IF(F76<>"", F76, IF(SUMPRODUCT(--(PLP_BUSINESS!$C$3:$C$2925=F$9)*(--(LOWER(PLP_BUSINESS!$G$3:$G$2925)=$AU12:$BY12)))>0,"O","X"))} -> O | G12: {=IF(G76<>"", G76, IF(SUMPRODUCT(--(PLP_BUSINESS!$C$3:$C$2925=G$9)*(--(LOWER(PLP_BUSINESS!$G$3:$G$2925)=$AU12:$BY12)))>0,"O","X"))} -> O | H12: {=IF(H76<>"", H76, IF(SUMPRODUCT(--(PLP_BUSINESS!$C$3:$C$2925=H$9)*(--(LOWER(PLP_BUSINESS!$G$3:$G$2925)=$AU12:$BY12)))>0,"O","X"))} -> O | I12: {=IF(I76<>"", I76, IF(SUMPRODUCT(--(PLP_BUSINESS!$C$3:$C$2925=I$9)*(--(LOWER(PLP_BUSINESS!$G$3:$G$2925)=$AU12:$BY12)))>0,"O","X"))} -> O | J12: {=IF(J76<>"", J76, IF(SUMPRODUCT(--(PLP_BUSINESS!$C$3:$C$2925=J$9)*(--(LOWER(PLP_BUSINESS!$G$3:$G$2925)=$AU12:$BY12)))>0,"O","X"))} -> O | K12: {=IF(K76<>"", K76, IF(SUMPRODUCT(--(PLP_BUSINESS!$C$3:$C$2925=K$9)*(--(LOWER(PLP_BUSINESS!$G$3:$G$2925)=$AU12:$BY12)))>0,"O","X"))} -> O | L12: {=IF(L76<>"", L76, IF(SUMPRODUCT(--(PLP_BUSINESS!$C$3:$C$2925=L$9)*(--(LOWER(PLP_BUSINESS!$G$3:$G$2925)=$AU12:$BY12)))>0,"O","X"))} -> O | ... AS12: {=IF(AS76<>"", AS76, IF(SUMPRODUCT(--(PLP_BUSINESS!$C$3:$C$2925=AS$9)*(--(LOWER(PLP_BUSINESS!$G$3:$G$2925)=$AU12:$BY12)))>0,"O","X"))} -> O | AU12: multi v s | AV12: multi vs | AW12: multi vs. | AX12: multi vs air conditioning system | AY12: multi vs - vrf system - hvac | lg france professional | AZ12: s-different air conditioning system | BA12: multi vs r32 | BB12: multi vs side blow | BC12: fill | BD12: fill | BE12: fill | BF12: fill | BG12: fill | BH12: fill | BI12: fill | BJ12: fill | BK12: fill | BL12: fill | BM12: fill | BN12: fill | BO12: fill | BP12: fill | BQ12: fill | BR12: fill | BS12: fill | BT12: fill | BU12: fill | BV12: fill | BW12: fill
D13: MULTI V WATER 5 | E13: {=IF(E77<>"", E77, IF(SUMPRODUCT(--(PLP_BUSINESS!$C$3:$C$2925=E$9)*(--(LOWER(PLP_BUSINESS!$G$3:$G$2925)=$AU13:$BY13)))>0,"O","X"))} -> O | F13: {=IF(F77<>"", F77, IF(SUMPRODUCT(--(PLP_BUSINESS!$C$3:$C$2925=F$9)*(--(LOWER(PLP_BUSINESS!$G$3:$G$2925)=$AU13:$BY13)))>0,"O","X"))} -> O | G13: {=IF(G77<>"", G77, IF(SUMPRODUCT(--(PLP_BUSINESS!$C$3:$C$2925=G$9)*(--(LOWER(PLP_BUSINESS!$G$3:$G$2925)=$AU13:$BY13)))>0,"O","X"))} -> O | H13: {=IF(H77<>"", H77, IF(SUMPRODUCT(--(PLP_BUSINESS!$C$3:$C$2925=H$9)*(--(LOWER(PLP_BUSINESS!$G$3:$G$2925)=$AU13:$BY13)))>0,"O","X"))} -> O | I13: {=IF(I77<>"", I77, IF(SUMPRODUCT(--(PLP_BUSINESS!$C$3:$C$2925=I$9)*(--(LOWER(PLP_BUSINESS!$G$3:$G$2925)=$AU13:$BY13)))>0,"O","X"))} -> O | J13: {=IF(J77<>"", J77, IF(SUMPRODUCT(--(PLP_BUSINESS!$C$3:$C$2925=J$9)*(--(LOWER(PLP_BUSINESS!$G$3:$G$2925)=$AU13:$BY13)))>0,"O","X"))} -> O | K13: {=IF(K77<>"", K77, IF(SUMPRODUCT(--(PLP_BUSINESS!$C$3:$C$2925=K$9)*(--(LOWER(PLP_BUSINESS!$G$3:$G$2925)=$AU13:$BY13)))>0,"O","X"))} -> O | L13: {=IF(L77<>"", L77, IF(SUMPRODUCT(--(PLP_BUSINESS!$C$3:$C$2925=L$9)*(--(LOWER(PLP_BUSINESS!$G$3:$G$2925)=$AU13:$BY13)))>0,"O","X"))} -> O | ... AS13: {=IF(AS77<>"", AS77, IF(SUMPRODUCT(--(PLP_BUSINESS!$C$3:$C$2925=AS$9)*(--(LOWER(PLP_BUSINESS!$G$3:$G$2925)=$AU13:$BY13)))>0,"O","X"))} -> N/A | AU13: multi v water 5 | AV13: multi-v-water-5 | AW13: multi v water 5 - vrf system - hvac | lg france professional | AX13: fill | AY13: fill | AZ13: fill | BA13: fill | BB13: fill | BC13: fill | BD13: fill | BE13: fill | BF13: fill | BG13: fill | BH13: fill | BI13: fill | BJ13: fill | BK13: fill | BL13: fill | BM13: fill | BN13: fill | BO13: fill | BP13: fill | BQ13: fill | BR13: fill | BS13: fill | BT13: fill | BU13: fill | BV13: fill | BW13: fill
D14: MULTI V WATER IV | E14: {=IF(E78<>"", E78, IF(SUMPRODUCT(--(PLP_BUSINESS!$C$3:$C$2925=E$9)*(--(LOWER(PLP_BUSINESS!$G$3:$G$2925)=$AU14:$BY14)))>0,"O","X"))} -> N/A | F14: {=IF(F78<>"", F78, IF(SUMPRODUCT(--(PLP_BUSINESS!$C$3:$C$2925=F$9)*(--(LOWER(PLP_BUSINESS!$G$3:$G$2925)=$AU14:$BY14)))>0,"O","X"))} -> N/A | G14: {=IF(G78<>"", G78, IF(SUMPRODUCT(--(PLP_BUSINESS!$C$3:$C$2925=G$9)*(--(LOWER(PLP_BUSINESS!$G$3:$G$2925)=$AU14:$BY14)))>0,"O","X"))} -> N/A | H14: {=IF(H78<>"", H78, IF(SUMPRODUCT(--(PLP_BUSINESS!$C$3:$C$2925=H$9)*(--(LOWER(PLP_BUSINESS!$G$3:$G$2925)=$AU14:$BY14)))>0,"O","X"))} -> N/A | I14: {=IF(I78<>"", I78, IF(SUMPRODUCT(--(PLP_BUSINESS!$C$3:$C$2925=I$9)*(--(LOWER(PLP_BUSINESS!$G$3:$G$2925)=$AU14:$BY14)))>0,"O","X"))} -> N/A | J14: {=IF(J78<>"", J78, IF(SUMPRODUCT(--(PLP_BUSINESS!$C$3:$C$2925=J$9)*(--(LOWER(PLP_BUSINESS!$G$3:$G$2925)=$AU14:$BY14)))>0,"O","X"))} -> N/A | K14: {=IF(K78<>"", K78, IF(SUMPRODUCT(--(PLP_BUSINESS!$C$3:$C$2925=K$9)*(--(LOWER(PLP_BUSINESS!$G$3:$G$2925)=$AU14:$BY14)))>0,"O","X"))} -> N/A | L14: {=IF(L78<>"", L78, IF(SUMPRODUCT(--(PLP_BUSINESS!$C$3:$C$2925=L$9)*(--(LOWER(PLP_BUSINESS!$G$3:$G$2925)=$AU14:$BY14)))>0,"O","X"))} -> N/A | ... AS14: {=IF(AS78<>"", AS78, IF(SUMPRODUCT(--(PLP_BUSINESS!$C$3:$C$2925=AS$9)*(--(LOWER(PLP_BUSINESS!$G$3:$G$2925)=$AU14:$BY14)))>0,"O","X"))} -> O | AU14: multi v water iv | AV14: multi v water iv air conditioning system | AW14: multi v water 5 | AX14: multi v water iv variable air conditioning system | AY14: multi in the cooler with water 4 | AZ14: fill | BA14: fill | BB14: fill | BC14: fill | BD14: fill | BE14: fill | BF14: fill | BG14: fill | BH14: fill | BI14: fill | BJ14: fill | BK14: fill | BL14: fill | BM14: fill | BN14: fill | BO14: fill | BP14: fill | BQ14: fill | BR14: fill | BS14: fill | BT14: fill | BU14: fill | BV14: fill | BW14: fill
D15: MULTI V M | E15: {=IF(E79<>"", E79, IF(SUMPRODUCT(--(PLP_BUSINESS!$C$3:$C$2925=E$9)*(--(LOWER(PLP_BUSINESS!$G$3:$G$2925)=$AU15:$BY15)))>0,"O","X"))} -> O | F15: {=IF(F79<>"", F79, IF(SUMPRODUCT(--(PLP_BUSINESS!$C$3:$C$2925=F$9)*(--(LOWER(PLP_BUSINESS!$G$3:$G$2925)=$AU15:$BY15)))>0,"O","X"))} -> O | G15: {=IF(G79<>"", G79, IF(SUMPRODUCT(--(PLP_BUSINESS!$C$3:$C$2925=G$9)*(--(LOWER(PLP_BUSINESS!$G$3:$G$2925)=$AU15:$BY15)))>0,"O","X"))} -> O | H15: {=IF(H79<>"", H79, IF(SUMPRODUCT(--(PLP_BUSINESS!$C$3:$C$2925=H$9)*(--(LOWER(PLP_BUSINESS!$G$3:$G$2925)=$AU15:$BY15)))>0,"O","X"))} -> O | I15: {=IF(I79<>"", I79, IF(SUMPRODUCT(--(PLP_BUSINESS!$C$3:$C$2925=I$9)*(--(LOWER(PLP_BUSINESS!$G$3:$G$2925)=$AU15:$BY15)))>0,"O","X"))} -> O | J15: {=IF(J79<>"", J79, IF(SUMPRODUCT(--(PLP_BUSINESS!$C$3:$C$2925=J$9)*(--(LOWER(PLP_BUSINESS!$G$3:$G$2925)=$AU15:$BY15)))>0,"O","X"))} -> O | K15: {=IF(K79<>"", K79, IF(SUMPRODUCT(--(PLP_BUSINESS!$C$3:$C$2925=K$9)*(--(LOWER(PLP_BUSINESS!$G$3:$G$2925)=$AU15:$BY15)))>0,"O","X"))} -> O | L15: {=IF(L79<>"", L79, IF(SUMPRODUCT(--(PLP_BUSINESS!$C$3:$C$2925=L$9)*(--(LOWER(PLP_BUSINESS!$G$3:$G$2925)=$AU15:$BY15)))>0,"O","X"))} -> O | ... AS15: {=IF(AS79<>"", AS79, IF(SUMPRODUCT(--(PLP_BUSINESS!$C$3:$C$2925=AS$9)*(--(LOWER(PLP_BUSINESS!$G$3:$G$2925)=$AU15:$BY15)))>0,"O","X"))} -> N/A | AU15: multi v m | AV15: multi-vm | AW15: multi vm air conditioning system | AX15: multi vm | AY15: fill | AZ15: fill | BA15: fill | BB15: fill | BC15: fill | BD15: fill | BE15: fill | BF15: fill | BG15: fill | BH15: fill | BI15: fill | BJ15: fill | BK15: fill | BL15: fill | BM15: fill | BN15: fill | BO15: fill | BP15: fill | BQ15: fill | BR15: fill | BS15: fill | BT15: fill | BU15: fill | BV15: fill | BW15: fill
D16: Indoor Round Cassette | E16: {=IF(E80<>"", E80, IF(SUMPRODUCT(--(PLP_BUSINESS!$C$3:$C$2925=E$9)*(--(LOWER(PLP_BUSINESS!$G$3:$G$2925)=$AU16:$BY16)))>0,"O","X"))} -> N/A | F16: {=IF(F80<>"", F80, IF(SUMPRODUCT(--(PLP_BUSINESS!$C$3:$C$2925=F$9)*(--(LOWER(PLP_BUSINESS!$G$3:$G$2925)=$AU16:$BY16)))>0,"O","X"))} -> N/A | G16: {=IF(G80<>"", G80, IF(SUMPRODUCT(--(PLP_BUSINESS!$C$3:$C$2925=G$9)*(--(LOWER(PLP_BUSINESS!$G$3:$G$2925)=$AU16:$BY16)))>0,"O","X"))} -> N/A | H16: {=IF(H80<>"", H80, IF(SUMPRODUCT(--(PLP_BUSINESS!$C$3:$C$2925=H$9)*(--(LOWER(PLP_BUSINESS!$G$3:$G$2925)=$AU16:$BY16)))>0,"O","X"))} -> N/A | I16: {=IF(I80<>"", I80, IF(SUMPRODUCT(--(PLP_BUSINESS!$C$3:$C$2925=I$9)*(--(LOWER(PLP_BUSINESS!$G$3:$G$2925)=$AU16:$BY16)))>0,"O","X"))} -> N/A | J16: {=IF(J80<>"", J80, IF(SUMPRODUCT(--(PLP_BUSINESS!$C$3:$C$2925=J$9)*(--(LOWER(PLP_BUSINESS!$G$3:$G$2925)=$AU16:$BY16)))>0,"O","X"))} -> N/A | K16: {=IF(K80<>"", K80, IF(SUMPRODUCT(--(PLP_BUSINESS!$C$3:$C$2925=K$9)*(--(LOWER(PLP_BUSINESS!$G$3:$G$2925)=$AU16:$BY16)))>0,"O","X"))} -> N/A | L16: {=IF(L80<>"", L80, IF(SUMPRODUCT(--(PLP_BUSINESS!$C$3:$C$2925=L$9)*(--(LOWER(PLP_BUSINESS!$G$3:$G$2925)=$AU16:$BY16)))>0,"O","X"))} -> N/A | ... AS16: {=IF(AS80<>"", AS80, IF(SUMPRODUCT(--(PLP_BUSINESS!$C$3:$C$2925=AS$9)*(--(LOWER(PLP_BUSINESS!$G$3:$G$2925)=$AU16:$BY16)))>0,"O","X"))} -> N/A | AU16: indoor round cassette | AV16: round cassette indoor unit | AW16: round cassette indoor units | AX16: round cassette | AY16: fill | AZ16: fill | BA16: fill | BB16: fill | BC16: fill | BD16: fill | BE16: fill | BF16: fill | BG16: fill | BH16: fill | BI16: fill | BJ16: fill | BK16: fill | BL16: fill | BM16: fill | BN16: fill | BO16: fill | BP16: fill | BQ16: fill | BR16: fill | BS16: fill | BT16: fill | BU16: fill | BV16: fill | BW16: fill | BY16: https://www.lg.com/global/business/hvac/commercial-solutions/vrf-system/indoor-unit/round-cassette | BZ16: https://www.lg.com/eg_en/business/indoor-round-cassette/ | CA16: https://www.lg.com/br/business/ar-condicionado/comercial-leve/commercial-leve-round-cassette/ -> using this asset, plz update it.
D17: Indoor Ceiling Mounted Cassette | E17: {=IF(E81<>"", E81, IF(SUMPRODUCT(--(PLP_BUSINESS!$C$3:$C$2925=E$9)*(--(LOWER(PLP_BUSINESS!$G$3:$G$2925)=$AU17:$BY17)))>0,"O","X"))} -> N/A | F17: {=IF(F81<>"", F81, IF(SUMPRODUCT(--(PLP_BUSINESS!$C$3:$C$2925=F$9)*(--(LOWER(PLP_BUSINESS!$G$3:$G$2925)=$AU17:$BY17)))>0,"O","X"))} -> N/A | G17: {=IF(G81<>"", G81, IF(SUMPRODUCT(--(PLP_BUSINESS!$C$3:$C$2925=G$9)*(--(LOWER(PLP_BUSINESS!$G$3:$G$2925)=$AU17:$BY17)))>0,"O","X"))} -> N/A | H17: {=IF(H81<>"", H81, IF(SUMPRODUCT(--(PLP_BUSINESS!$C$3:$C$2925=H$9)*(--(LOWER(PLP_BUSINESS!$G$3:$G$2925)=$AU17:$BY17)))>0,"O","X"))} -> N/A | I17: {=IF(I81<>"", I81, IF(SUMPRODUCT(--(PLP_BUSINESS!$C$3:$C$2925=I$9)*(--(LOWER(PLP_BUSINESS!$G$3:$G$2925)=$AU17:$BY17)))>0,"O","X"))} -> N/A | J17: {=IF(J81<>"", J81, IF(SUMPRODUCT(--(PLP_BUSINESS!$C$3:$C$2925=J$9)*(--(LOWER(PLP_BUSINESS!$G$3:$G$2925)=$AU17:$BY17)))>0,"O","X"))} -> N/A | K17: {=IF(K81<>"", K81, IF(SUMPRODUCT(--(PLP_BUSINESS!$C$3:$C$2925=K$9)*(--(LOWER(PLP_BUSINESS!$G$3:$G$2925)=$AU17:$BY17)))>0,"O","X"))} -> N/A | L17: {=IF(L81<>"", L81, IF(SUMPRODUCT(--(PLP_BUSINESS!$C$3:$C$2925=L$9)*(--(LOWER(PLP_BUSINESS!$G$3:$G$2925)=$AU17:$BY17)))>0,"O","X"))} -> N/A | ... AS17: {=IF(AS81<>"", AS81, IF(SUMPRODUCT(--(PLP_BUSINESS!$C$3:$C$2925=AS$9)*(--(LOWER(PLP_BUSINESS!$G$3:$G$2925)=$AU17:$BY17)))>0,"O","X"))} -> N/A | AU17: indoor ceiling mounted cassette | AV17: cassette indoor unit | AW17: multi v ic unit 4 way cassette | AX17: ceiling cassette indoor units | AY17: cassette | AZ17: multi v ic unite 4 way cassette | BA17: fill | BB17: fill | BC17: fill | BD17: fill | BE17: fill | BF17: fill | BG17: fill | BH17: fill | BI17: fill | BJ17: fill | BK17: fill | BL17: fill | BM17: fill | BN17: fill | BO17: fill | BP17: fill | BQ17: fill | BR17: fill | BS17: fill | BT17: fill | BU17: fill | BV17: fill | BW17: fill | BY17: https://www.lg.com/global/business/hvac/commercial-solutions/vrf-system/indoor-unit/ceiling-mounted-cassette | BZ17: https://www.lg.com/eg_en/business/indoor-ceiling-mounted-cassette/
D18: Indoor Ceiling Concealed Duct | E18: {=IF(E82<>"", E82, IF(SUMPRODUCT(--(PLP_BUSINESS!$C$3:$C$2925=E$9)*(--(LOWER(PLP_BUSINESS!$G$3:$G$2925)=$AU18:$BY18)))>0,"O","X"))} -> N/A | F18: {=IF(F82<>"", F82, IF(SUMPRODUCT(--(PLP_BUSINESS!$C$3:$C$2925=F$9)*(--(LOWER(PLP_BUSINESS!$G$3:$G$2925)=$AU18:$BY18)))>0,"O","X"))} -> N/A | G18: {=IF(G82<>"", G82, IF(SUMPRODUCT(--(PLP_BUSINESS!$C$3:$C$2925=G$9)*(--(LOWER(PLP_BUSINESS!$G$3:$G$2925)=$AU18:$BY18)))>0,"O","X"))} -> N/A | H18: {=IF(H82<>"", H82, IF(SUMPRODUCT(--(PLP_BUSINESS!$C$3:$C$2925=H$9)*(--(LOWER(PLP_BUSINESS!$G$3:$G$2925)=$AU18:$BY18)))>0,"O","X"))} -> N/A | I18: {=IF(I82<>"", I82, IF(SUMPRODUCT(--(PLP_BUSINESS!$C$3:$C$2925=I$9)*(--(LOWER(PLP_BUSINESS!$G$3:$G$2925)=$AU18:$BY18)))>0,"O","X"))} -> N/A | J18: {=IF(J82<>"", J82, IF(SUMPRODUCT(--(PLP_BUSINESS!$C$3:$C$2925=J$9)*(--(LOWER(PLP_BUSINESS!$G$3:$G$2925)=$AU18:$BY18)))>0,"O","X"))} -> N/A | K18: {=IF(K82<>"", K82, IF(SUMPRODUCT(--(PLP_BUSINESS!$C$3:$C$2925=K$9)*(--(LOWER(PLP_BUSINESS!$G$3:$G$2925)=$AU18:$BY18)))>0,"O","X"))} -> N/A | L18: {=IF(L82<>"", L82, IF(SUMPRODUCT(--(PLP_BUSINESS!$C$3:$C$2925=L$9)*(--(LOWER(PLP_BUSINESS!$G$3:$G$2925)=$AU18:$BY18)))>0,"O","X"))} -> N/A | ... AS18: {=IF(AS82<>"", AS82, IF(SUMPRODUCT(--(PLP_BUSINESS!$C$3:$C$2925=AS$9)*(--(LOWER(PLP_BUSINESS!$G$3:$G$2925)=$AU18:$BY18)))>0,"O","X"))} -> N/A | AU18: indoor ceiling concealed duct | AV18: indoor duct unit | AW18: multi v ic unit concealed ceiling type | AX18: vrf indoor unit ceiling concealed duct | AY18: hanging implicit | AZ18: ductable hidden in ceiling | BA18: fill | BB18: fill | BC18: fill | BD18: fill | BE18: fill | BF18: fill | BG18: fill | BH18: fill | BI18: fill | BJ18: fill | BK18: fill | BL18: fill | BM18: fill | BN18: fill | BO18: fill | BP18: fill | BQ18: fill | BR18: fill | BS18: fill | BT18: fill | BU18: fill | BV18: fill | BW18: fill | BY18: https://www.lg.com/global/business/hvac/commercial-solutions/vrf-system/indoor-unit/ceiling-concealed-duct | BZ18: https://www.lg.com/cl/business/climatizacion/single-split/ducto/
D19: Indoor Wall Mounted Unit | E19: {=IF(E83<>"", E83, IF(SUMPRODUCT(--(PLP_BUSINESS!$C$3:$C$2925=E$9)*(--(LOWER(PLP_BUSINESS!$G$3:$G$2925)=$AU19:$BY19)))>0,"O","X"))} -> N/A | F19: {=IF(F83<>"", F83, IF(SUMPRODUCT(--(PLP_BUSINESS!$C$3:$C$2925=F$9)*(--(LOWER(PLP_BUSINESS!$G$3:$G$2925)=$AU19:$BY19)))>0,"O","X"))} -> N/A | G19: {=IF(G83<>"", G83, IF(SUMPRODUCT(--(PLP_BUSINESS!$C$3:$C$2925=G$9)*(--(LOWER(PLP_BUSINESS!$G$3:$G$2925)=$AU19:$BY19)))>0,"O","X"))} -> N/A | H19: {=IF(H83<>"", H83, IF(SUMPRODUCT(--(PLP_BUSINESS!$C$3:$C$2925=H$9)*(--(LOWER(PLP_BUSINESS!$G$3:$G$2925)=$AU19:$BY19)))>0,"O","X"))} -> N/A | I19: {=IF(I83<>"", I83, IF(SUMPRODUCT(--(PLP_BUSINESS!$C$3:$C$2925=I$9)*(--(LOWER(PLP_BUSINESS!$G$3:$G$2925)=$AU19:$BY19)))>0,"O","X"))} -> N/A | J19: {=IF(J83<>"", J83, IF(SUMPRODUCT(--(PLP_BUSINESS!$C$3:$C$2925=J$9)*(--(LOWER(PLP_BUSINESS!$G$3:$G$2925)=$AU19:$BY19)))>0,"O","X"))} -> N/A | K19: {=IF(K83<>"", K83, IF(SUMPRODUCT(--(PLP_BUSINESS!$C$3:$C$2925=K$9)*(--(LOWER(PLP_BUSINESS!$G$3:$G$2925)=$AU19:$BY19)))>0,"O","X"))} -> N/A | L19: {=IF(L83<>"", L83, IF(SUMPRODUCT(--(PLP_BUSINESS!$C$3:$C$2925=L$9)*(--(LOWER(PLP_BUSINESS!$G$3:$G$2925)=$AU19:$BY19)))>0,"O","X"))} -> N/A | ... AS19: {=IF(AS83<>"", AS83, IF(SUMPRODUCT(--(PLP_BUSINESS!$C$3:$C$2925=AS$9)*(--(LOWER(PLP_BUSINESS!$G$3:$G$2925)=$AU19:$BY19)))>0,"O","X"))} -> N/A | AU19: indoor wall mounted unit | AV19: indoor wall-mounted unit | AW19: indoor unit wall installation | AX19: indoor unit wall-mounted unit | AY19: multi v indoor unit wall type | AZ19: vrf indoor unit wall mounted unit | BA19: wall-mounted indoor units | BB19: wall-mounted indoor unit | BC19: multi v ic unit wall type | BD19: fill | BE19: fill | BF19: fill | BG19: fill | BH19: fill | BI19: fill | BJ19: fill | BK19: fill | BL19: fill | BM19: fill | BN19: fill | BO19: fill | BP19: fill | BQ19: fill | BR19: fill | BS19: fill | BT19: fill | BU19: fill | BV19: fill | BW19: fill
D20: Indoor Ceiling & Floor | E20: {=IF(E84<>"", E84, IF(SUMPRODUCT(--(PLP_BUSINESS!$C$3:$C$2925=E$9)*(--(LOWER(PLP_BUSINESS!$G$3:$G$2925)=$AU20:$BY20)))>0,"O","X"))} -> N/A | F20: {=IF(F84<>"", F84, IF(SUMPRODUCT(--(PLP_BUSINESS!$C$3:$C$2925=F$9)*(--(LOWER(PLP_BUSINESS!$G$3:$G$2925)=$AU20:$BY20)))>0,"O","X"))} -> N/A | G20: {=IF(G84<>"", G84, IF(SUMPRODUCT(--(PLP_BUSINESS!$C$3:$C$2925=G$9)*(--(LOWER(PLP_BUSINESS!$G$3:$G$2925)=$AU20:$BY20)))>0,"O","X"))} -> N/A | H20: {=IF(H84<>"", H84, IF(SUMPRODUCT(--(PLP_BUSINESS!$C$3:$C$2925=H$9)*(--(LOWER(PLP_BUSINESS!$G$3:$G$2925)=$AU20:$BY20)))>0,"O","X"))} -> N/A | I20: {=IF(I84<>"", I84, IF(SUMPRODUCT(--(PLP_BUSINESS!$C$3:$C$2925=I$9)*(--(LOWER(PLP_BUSINESS!$G$3:$G$2925)=$AU20:$BY20)))>0,"O","X"))} -> N/A | J20: {=IF(J84<>"", J84, IF(SUMPRODUCT(--(PLP_BUSINESS!$C$3:$C$2925=J$9)*(--(LOWER(PLP_BUSINESS!$G$3:$G$2925)=$AU20:$BY20)))>0,"O","X"))} -> N/A | K20: {=IF(K84<>"", K84, IF(SUMPRODUCT(--(PLP_BUSINESS!$C$3:$C$2925=K$9)*(--(LOWER(PLP_BUSINESS!$G$3:$G$2925)=$AU20:$BY20)))>0,"O","X"))} -> N/A | L20: {=IF(L84<>"", L84, IF(SUMPRODUCT(--(PLP_BUSINESS!$C$3:$C$2925=L$9)*(--(LOWER(PLP_BUSINESS!$G$3:$G$2925)=$AU20:$BY20)))>0,"O","X"))} -> N/A | ... AS20: {=IF(AS84<>"", AS84, IF(SUMPRODUCT(--(PLP_BUSINESS!$C$3:$C$2925=AS$9)*(--(LOWER(PLP_BUSINESS!$G$3:$G$2925)=$AU20:$BY20)))>0,"O","X"))} -> N/A | AU20: indoor ceiling & floor | AV20: indoor ceiling floor convertible | AW20: indoor ceiling floor | AX20: interior ceiling floor convertible | AY20: indoor unit ceiling and floor | AZ20: indoor console | BA20: indoor ceiling | BB20: multi v ic unit floor ceiling type | BC20: vrf indoor unit ceiling floor | BD20: floor-ceiling indoor units | BE20: fill | BF20: fill | BG20: fill | BH20: fill | BI20: fill | BJ20: fill | BK20: fill | BL20: fill | BM20: fill | BN20: fill | BO20: fill | BP20: fill | BQ20: fill | BR20: fill | BS20: fill | BT20: fill | BU20: fill | BV20: fill | BW20: fill | BY20: https://www.lg.com/africa/business/indoor-ceiling-floor-convertible | BZ20: https://www.lg.com/eg_en/business/indoor-ceiling-floor-convertible/
D21: Indoor Console | E21: {=IF(E85<>"", E85, IF(SUMPRODUCT(--(PLP_BUSINESS!$C$3:$C$2925=E$9)*(--(LOWER(PLP_BUSINESS!$G$3:$G$2925)=$AU21:$BY21)))>0,"O","X"))} -> N/A | F21: {=IF(F85<>"", F85, IF(SUMPRODUCT(--(PLP_BUSINESS!$C$3:$C$2925=F$9)*(--(LOWER(PLP_BUSINESS!$G$3:$G$2925)=$AU21:$BY21)))>0,"O","X"))} -> N/A | G21: {=IF(G85<>"", G85, IF(SUMPRODUCT(--(PLP_BUSINESS!$C$3:$C$2925=G$9)*(--(LOWER(PLP_BUSINESS!$G$3:$G$2925)=$AU21:$BY21)))>0,"O","X"))} -> N/A | H21: {=IF(H85<>"", H85, IF(SUMPRODUCT(--(PLP_BUSINESS!$C$3:$C$2925=H$9)*(--(LOWER(PLP_BUSINESS!$G$3:$G$2925)=$AU21:$BY21)))>0,"O","X"))} -> N/A | I21: {=IF(I85<>"", I85, IF(SUMPRODUCT(--(PLP_BUSINESS!$C$3:$C$2925=I$9)*(--(LOWER(PLP_BUSINESS!$G$3:$G$2925)=$AU21:$BY21)))>0,"O","X"))} -> N/A | J21: {=IF(J85<>"", J85, IF(SUMPRODUCT(--(PLP_BUSINESS!$C$3:$C$2925=J$9)*(--(LOWER(PLP_BUSINESS!$G$3:$G$2925)=$AU21:$BY21)))>0,"O","X"))} -> N/A | K21: {=IF(K85<>"", K85, IF(SUMPRODUCT(--(PLP_BUSINESS!$C$3:$C$2925=K$9)*(--(LOWER(PLP_BUSINESS!$G$3:$G$2925)=$AU21:$BY21)))>0,"O","X"))} -> N/A | L21: {=IF(L85<>"", L85, IF(SUMPRODUCT(--(PLP_BUSINESS!$C$3:$C$2925=L$9)*(--(LOWER(PLP_BUSINESS!$G$3:$G$2925)=$AU21:$BY21)))>0,"O","X"))} -> N/A | ... AS21: {=IF(AS85<>"", AS85, IF(SUMPRODUCT(--(PLP_BUSINESS!$C$3:$C$2925=AS$9)*(--(LOWER(PLP_BUSINESS!$G$3:$G$2925)=$AU21:$BY21)))>0,"O","X"))} -> N/A | AU21: indoor console | AV21: indoor vrf console unit | AW21: indoor console unit | AX21: fill | AY21: fill | AZ21: fill | BA21: fill | BB21: fill | BC21: fill | BD21: fill | BE21: fill | BF21: fill | BG21: fill | BH21: fill | BI21: fill | BJ21: fill | BK21: fill | BL21: fill | BM21: fill | BN21: fill | BO21: fill | BP21: fill | BQ21: fill | BR21: fill | BS21: fill | BT21: fill | BU21: fill | BV21: fill | BW21: fill | BY21: https://www.lg.com/africa/business/indoor-vrf-console-unit
D22: Hot Water Solution (Hydro Kit) | E22: {=IF(E86<>"", E86, IF(SUMPRODUCT(--(PLP_BUSINESS!$C$3:$C$2925=E$9)*(--(LOWER(PLP_BUSINESS!$G$3:$G$2925)=$AU22:$BY22)))>0,"O","X"))} -> O | F22: {=IF(F86<>"", F86, IF(SUMPRODUCT(--(PLP_BUSINESS!$C$3:$C$2925=F$9)*(--(LOWER(PLP_BUSINESS!$G$3:$G$2925)=$AU22:$BY22)))>0,"O","X"))} -> O | G22: {=IF(G86<>"", G86, IF(SUMPRODUCT(--(PLP_BUSINESS!$C$3:$C$2925=G$9)*(--(LOWER(PLP_BUSINESS!$G$3:$G$2925)=$AU22:$BY22)))>0,"O","X"))} -> O | H22: {=IF(H86<>"", H86, IF(SUMPRODUCT(--(PLP_BUSINESS!$C$3:$C$2925=H$9)*(--(LOWER(PLP_BUSINESS!$G$3:$G$2925)=$AU22:$BY22)))>0,"O","X"))} -> O | I22: {=IF(I86<>"", I86, IF(SUMPRODUCT(--(PLP_BUSINESS!$C$3:$C$2925=I$9)*(--(LOWER(PLP_BUSINESS!$G$3:$G$2925)=$AU22:$BY22)))>0,"O","X"))} -> O | J22: {=IF(J86<>"", J86, IF(SUMPRODUCT(--(PLP_BUSINESS!$C$3:$C$2925=J$9)*(--(LOWER(PLP_BUSINESS!$G$3:$G$2925)=$AU22:$BY22)))>0,"O","X"))} -> O | K22: {=IF(K86<>"", K86, IF(SUMPRODUCT(--(PLP_BUSINESS!$C$3:$C$2925=K$9)*(--(LOWER(PLP_BUSINESS!$G$3:$G$2925)=$AU22:$BY22)))>0,"O","X"))} -> O | L22: {=IF(L86<>"", L86, IF(SUMPRODUCT(--(PLP_BUSINESS!$C$3:$C$2925=L$9)*(--(LOWER(PLP_BUSINESS!$G$3:$G$2925)=$AU22:$BY22)))>0,"O","X"))} -> O | ... AS22: {=IF(AS86<>"", AS86, IF(SUMPRODUCT(--(PLP_BUSINESS!$C$3:$C$2925=AS$9)*(--(LOWER(PLP_BUSINESS!$G$3:$G$2925)=$AU22:$BY22)))>0,"O","X"))} -> N/A | AU22: hot water solution (hydro kit) | AV22: hot water solution (hydrokit) | AW22: hot water solution(hydro kit) | AX22: hot water solutions (hydro kit) | AY22: hot water solutions (hidrokit) | AZ22: hot water solution hydro kit | BA22: solutions for dhw hydro kit | BB22: hydro kit: hot water solution | BC22: hydro kit | BD22: hydro kits | BE22: hydro kit domestic water heating solutions | BF22: water heating solutions | BG22: hydraulic kits | BH22: water heater solution (hydro kit) | BI22: hydrokit | BJ22: hot water solution | BK22: water heating solutions (hydro kit) | BL22: hydro kit (hot water solution) | BM22: hot water solutions (hydrokit) | BN22: hot water solutions | BO22: fill | BP22: fill | BQ22: fill | BR22: fill | BS22: fill | BT22: fill | BU22: fill | BV22: fill | BW22: fill
D23: Ventilation Solution (ERV) | E23: {=IF(E87<>"", E87, IF(SUMPRODUCT(--(PLP_BUSINESS!$C$3:$C$2925=E$9)*(--(LOWER(PLP_BUSINESS!$G$3:$G$2925)=$AU23:$BY23)))>0,"O","X"))} -> O | F23: {=IF(F87<>"", F87, IF(SUMPRODUCT(--(PLP_BUSINESS!$C$3:$C$2925=F$9)*(--(LOWER(PLP_BUSINESS!$G$3:$G$2925)=$AU23:$BY23)))>0,"O","X"))} -> O | G23: {=IF(G87<>"", G87, IF(SUMPRODUCT(--(PLP_BUSINESS!$C$3:$C$2925=G$9)*(--(LOWER(PLP_BUSINESS!$G$3:$G$2925)=$AU23:$BY23)))>0,"O","X"))} -> O | H23: {=IF(H87<>"", H87, IF(SUMPRODUCT(--(PLP_BUSINESS!$C$3:$C$2925=H$9)*(--(LOWER(PLP_BUSINESS!$G$3:$G$2925)=$AU23:$BY23)))>0,"O","X"))} -> O | I23: {=IF(I87<>"", I87, IF(SUMPRODUCT(--(PLP_BUSINESS!$C$3:$C$2925=I$9)*(--(LOWER(PLP_BUSINESS!$G$3:$G$2925)=$AU23:$BY23)))>0,"O","X"))} -> O | J23: {=IF(J87<>"", J87, IF(SUMPRODUCT(--(PLP_BUSINESS!$C$3:$C$2925=J$9)*(--(LOWER(PLP_BUSINESS!$G$3:$G$2925)=$AU23:$BY23)))>0,"O","X"))} -> O | K23: {=IF(K87<>"", K87, IF(SUMPRODUCT(--(PLP_BUSINESS!$C$3:$C$2925=K$9)*(--(LOWER(PLP_BUSINESS!$G$3:$G$2925)=$AU23:$BY23)))>0,"O","X"))} -> O | L23: {=IF(L87<>"", L87, IF(SUMPRODUCT(--(PLP_BUSINESS!$C$3:$C$2925=L$9)*(--(LOWER(PLP_BUSINESS!$G$3:$G$2925)=$AU23:$BY23)))>0,"O","X"))} -> O | ... AS23: {=IF(AS87<>"", AS87, IF(SUMPRODUCT(--(PLP_BUSINESS!$C$3:$C$2925=AS$9)*(--(LOWER(PLP_BUSINESS!$G$3:$G$2925)=$AU23:$BY23)))>0,"O","X"))} -> N/A | AU23: ventilation solution (erv) | AV23: erv | AW23: ventilation solutions | AX23: ventilation solution | AY23: ventilation solutions (erv) | AZ23: energy recovery ventilation (erv) | BA23: recuperative ventilation units | BB23: ventilation chamber kits | BC23: heat recovery ventilation (erv) | BD23: commercial erv (ventilation) | BE23: commercial erv ventilation | BF23: ventilation unit | BG23: ventilation solution (energy recovery ventilator - erv) | BH23: erv ventilation | BI23: aeration | BJ23: erv ventilation solutions | BK23: energy recovery ventilator (erv) | BL23: recuperadores de calor | BM23: ventilation systems (vre) | BN23: ventilation | BO23: total heat exchanger | BP23: heat recovery units | BQ23: fill | BR23: fill | BS23: fill | BT23: fill | BU23: fill | BV23: fill | BW23: fill
D24: Air Handling Unit (AHU) | E24: {=IF(E88<>"", E88, IF(SUMPRODUCT(--(PLP_BUSINESS!$C$3:$C$2925=E$9)*(--(LOWER(PLP_BUSINESS!$G$3:$G$2925)=$AU24:$BY24)))>0,"O","X"))} -> O | F24: {=IF(F88<>"", F88, IF(SUMPRODUCT(--(PLP_BUSINESS!$C$3:$C$2925=F$9)*(--(LOWER(PLP_BUSINESS!$G$3:$G$2925)=$AU24:$BY24)))>0,"O","X"))} -> O | G24: {=IF(G88<>"", G88, IF(SUMPRODUCT(--(PLP_BUSINESS!$C$3:$C$2925=G$9)*(--(LOWER(PLP_BUSINESS!$G$3:$G$2925)=$AU24:$BY24)))>0,"O","X"))} -> O | H24: {=IF(H88<>"", H88, IF(SUMPRODUCT(--(PLP_BUSINESS!$C$3:$C$2925=H$9)*(--(LOWER(PLP_BUSINESS!$G$3:$G$2925)=$AU24:$BY24)))>0,"O","X"))} -> O | I24: {=IF(I88<>"", I88, IF(SUMPRODUCT(--(PLP_BUSINESS!$C$3:$C$2925=I$9)*(--(LOWER(PLP_BUSINESS!$G$3:$G$2925)=$AU24:$BY24)))>0,"O","X"))} -> O | J24: {=IF(J88<>"", J88, IF(SUMPRODUCT(--(PLP_BUSINESS!$C$3:$C$2925=J$9)*(--(LOWER(PLP_BUSINESS!$G$3:$G$2925)=$AU24:$BY24)))>0,"O","X"))} -> O | K24: {=IF(K88<>"", K88, IF(SUMPRODUCT(--(PLP_BUSINESS!$C$3:$C$2925=K$9)*(--(LOWER(PLP_BUSINESS!$G$3:$G$2925)=$AU24:$BY24)))>0,"O","X"))} -> O | L24: {=IF(L88<>"", L88, IF(SUMPRODUCT(--(PLP_BUSINESS!$C$3:$C$2925=L$9)*(--(LOWER(PLP_BUSINESS!$G$3:$G$2925)=$AU24:$BY24)))>0,"O","X"))} -> N/A | ... AS24: {=IF(AS88<>"", AS88, IF(SUMPRODUCT(--(PLP_BUSINESS!$C$3:$C$2925=AS$9)*(--(LOWER(PLP_BUSINESS!$G$3:$G$2925)=$AU24:$BY24)))>0,"O","X"))} -> O | AU24: air handling unit (ahu) | AV24: air handling unit | AW24: air handling units (ahu) | AX24: air handling units (uma) | AY24: air handling unit (lah) | AZ24: ahu comms kit | BA24: ahu kits | BB24: air conditioning unit (ahu) | BC24: ahu air conditioning unit | BD24: ahu solutions for multi v | BE24: standard ahu | BF24: combined air conditioner (ahu) | BG24: direct expansion ahu | BH24: central air conditioning units | BI24: air connection kit | BJ24: air handling units (ahu) | BK24: air treatment unit | BL24: solutions for ahu ventilation units | BM24: humidity and heat treatment solution (ahu) | BN24: air handling units | BO24: solutions for ahu air handling units | BP24: air-conditioning and humidification solutions (ahu) | BQ24: fill | BR24: fill | BS24: fill | BT24: fill | BU24: fill | BV24: fill | BW24: fill
D25: GAS Heat Pump (GHP) | E25: {=IF(E89<>"", E89, IF(SUMPRODUCT(--(PLP_BUSINESS!$C$3:$C$2925=E$9)*(--(LOWER(PLP_BUSINESS!$G$3:$G$2925)=$AU25:$BY25)))>0,"O","X"))} -> N/A | F25: {=IF(F89<>"", F89, IF(SUMPRODUCT(--(PLP_BUSINESS!$C$3:$C$2925=F$9)*(--(LOWER(PLP_BUSINESS!$G$3:$G$2925)=$AU25:$BY25)))>0,"O","X"))} -> N/A | G25: {=IF(G89<>"", G89, IF(SUMPRODUCT(--(PLP_BUSINESS!$C$3:$C$2925=G$9)*(--(LOWER(PLP_BUSINESS!$G$3:$G$2925)=$AU25:$BY25)))>0,"O","X"))} -> N/A | H25: {=IF(H89<>"", H89, IF(SUMPRODUCT(--(PLP_BUSINESS!$C$3:$C$2925=H$9)*(--(LOWER(PLP_BUSINESS!$G$3:$G$2925)=$AU25:$BY25)))>0,"O","X"))} -> N/A | I25: {=IF(I89<>"", I89, IF(SUMPRODUCT(--(PLP_BUSINESS!$C$3:$C$2925=I$9)*(--(LOWER(PLP_BUSINESS!$G$3:$G$2925)=$AU25:$BY25)))>0,"O","X"))} -> N/A | J25: {=IF(J89<>"", J89, IF(SUMPRODUCT(--(PLP_BUSINESS!$C$3:$C$2925=J$9)*(--(LOWER(PLP_BUSINESS!$G$3:$G$2925)=$AU25:$BY25)))>0,"O","X"))} -> N/A | K25: {=IF(K89<>"", K89, IF(SUMPRODUCT(--(PLP_BUSINESS!$C$3:$C$2925=K$9)*(--(LOWER(PLP_BUSINESS!$G$3:$G$2925)=$AU25:$BY25)))>0,"O","X"))} -> N/A | L25: {=IF(L89<>"", L89, IF(SUMPRODUCT(--(PLP_BUSINESS!$C$3:$C$2925=L$9)*(--(LOWER(PLP_BUSINESS!$G$3:$G$2925)=$AU25:$BY25)))>0,"O","X"))} -> N/A | ... AS25: {=IF(AS89<>"", AS89, IF(SUMPRODUCT(--(PLP_BUSINESS!$C$3:$C$2925=AS$9)*(--(LOWER(PLP_BUSINESS!$G$3:$G$2925)=$AU25:$BY25)))>0,"O","X"))} -> N/A | AU25: gas heat pump (ghp) | AV25: ghp (gas heat pump) | AW25: gas heat pumps ghp | AX25: gas fired heating unit (ghp) | AY25: ghp | AZ25: fill | BA25: fill | BB25: fill | BC25: fill | BD25: fill | BE25: fill | BF25: fill | BG25: fill | BH25: fill | BI25: fill | BJ25: fill | BK25: fill | BL25: fill | BM25: fill | BN25: fill | BO25: fill | BP25: fill | BQ25: fill | BR25: fill | BS25: fill | BT25: fill | BU25: fill | BV25: fill | BW25: fill | BZ25: https://www.lg.com/eg_en/business/air-solution/vrf/gas-heat-pump/
B26: Single | D26: Retrofit Solution | E26: {=IF(E90<>"", E90, IF(SUMPRODUCT(--(PLP_BUSINESS!$C$3:$C$2925=E$9)*(--(LOWER(PLP_BUSINESS!$G$3:$G$2925)=$AU26:$BY26)))>0,"O","X"))} -> N/A | F26: {=IF(F90<>"", F90, IF(SUMPRODUCT(--(PLP_BUSINESS!$C$3:$C$2925=F$9)*(--(LOWER(PLP_BUSINESS!$G$3:$G$2925)=$AU26:$BY26)))>0,"O","X"))} -> N/A | G26: {=IF(G90<>"", G90, IF(SUMPRODUCT(--(PLP_BUSINESS!$C$3:$C$2925=G$9)*(--(LOWER(PLP_BUSINESS!$G$3:$G$2925)=$AU26:$BY26)))>0,"O","X"))} -> N/A | H26: {=IF(H90<>"", H90, IF(SUMPRODUCT(--(PLP_BUSINESS!$C$3:$C$2925=H$9)*(--(LOWER(PLP_BUSINESS!$G$3:$G$2925)=$AU26:$BY26)))>0,"O","X"))} -> N/A | I26: {=IF(I90<>"", I90, IF(SUMPRODUCT(--(PLP_BUSINESS!$C$3:$C$2925=I$9)*(--(LOWER(PLP_BUSINESS!$G$3:$G$2925)=$AU26:$BY26)))>0,"O","X"))} -> N/A | J26: {=IF(J90<>"", J90, IF(SUMPRODUCT(--(PLP_BUSINESS!$C$3:$C$2925=J$9)*(--(LOWER(PLP_BUSINESS!$G$3:$G$2925)=$AU26:$BY26)))>0,"O","X"))} -> N/A | K26: {=IF(K90<>"", K90, IF(SUMPRODUCT(--(PLP_BUSINESS!$C$3:$C$2925=K$9)*(--(LOWER(PLP_BUSINESS!$G$3:$G$2925)=$AU26:$BY26)))>0,"O","X"))} -> N/A | L26: {=IF(L90<>"", L90, IF(SUMPRODUCT(--(PLP_BUSINESS!$C$3:$C$2925=L$9)*(--(LOWER(PLP_BUSINESS!$G$3:$G$2925)=$AU26:$BY26)))>0,"O","X"))} -> N/A | ... AS26: {=IF(AS90<>"", AS90, IF(SUMPRODUCT(--(PLP_BUSINESS!$C$3:$C$2925=AS$9)*(--(LOWER(PLP_BUSINESS!$G$3:$G$2925)=$AU26:$BY26)))>0,"O","X"))} -> N/A | AU26: retrofit solution | AV26: retrofit | AW26: replacement solution | AX26: fill | AY26: fill | AZ26: fill | BA26: fill | BB26: fill | BC26: fill | BD26: fill | BE26: fill | BF26: fill | BG26: fill | BH26: fill | BI26: fill | BJ26: fill | BK26: fill | BL26: fill | BM26: fill | BN26: fill | BO26: fill | BP26: fill | BQ26: fill | BR26: fill | BS26: fill | BT26: fill | BU26: fill | BV26: fill | BW26: fill
D27: Round Cassette | E27: {=IF(E91<>"", E91, IF(SUMPRODUCT(--(PLP_BUSINESS!$C$3:$C$2925=E$9)*(--(LOWER(PLP_BUSINESS!$G$3:$G$2925)=$AU27:$BY27)))>0,"O","X"))} -> O | F27: {=IF(F91<>"", F91, IF(SUMPRODUCT(--(PLP_BUSINESS!$C$3:$C$2925=F$9)*(--(LOWER(PLP_BUSINESS!$G$3:$G$2925)=$AU27:$BY27)))>0,"O","X"))} -> O | G27: {=IF(G91<>"", G91, IF(SUMPRODUCT(--(PLP_BUSINESS!$C$3:$C$2925=G$9)*(--(LOWER(PLP_BUSINESS!$G$3:$G$2925)=$AU27:$BY27)))>0,"O","X"))} -> O | H27: {=IF(H91<>"", H91, IF(SUMPRODUCT(--(PLP_BUSINESS!$C$3:$C$2925=H$9)*(--(LOWER(PLP_BUSINESS!$G$3:$G$2925)=$AU27:$BY27)))>0,"O","X"))} -> O | I27: {=IF(I91<>"", I91, IF(SUMPRODUCT(--(PLP_BUSINESS!$C$3:$C$2925=I$9)*(--(LOWER(PLP_BUSINESS!$G$3:$G$2925)=$AU27:$BY27)))>0,"O","X"))} -> O | J27: {=IF(J91<>"", J91, IF(SUMPRODUCT(--(PLP_BUSINESS!$C$3:$C$2925=J$9)*(--(LOWER(PLP_BUSINESS!$G$3:$G$2925)=$AU27:$BY27)))>0,"O","X"))} -> O | K27: {=IF(K91<>"", K91, IF(SUMPRODUCT(--(PLP_BUSINESS!$C$3:$C$2925=K$9)*(--(LOWER(PLP_BUSINESS!$G$3:$G$2925)=$AU27:$BY27)))>0,"O","X"))} -> O | L27: {=IF(L91<>"", L91, IF(SUMPRODUCT(--(PLP_BUSINESS!$C$3:$C$2925=L$9)*(--(LOWER(PLP_BUSINESS!$G$3:$G$2925)=$AU27:$BY27)))>0,"O","X"))} -> O | ... AS27: {=IF(AS91<>"", AS91, IF(SUMPRODUCT(--(PLP_BUSINESS!$C$3:$C$2925=AS$9)*(--(LOWER(PLP_BUSINESS!$G$3:$G$2925)=$AU27:$BY27)))>0,"O","X"))} -> N/A | AU27: round cassette | AV27: round catridges | AW27: round suspended ceiling unit | AX27: mono-split round cassette | AY27: round cassettes | AZ27: round cassette indoor unit | BA27: circular casette | BB27: circular cassette | BC27: mono-split: round cassette | BD27: single split round cassette | BE27: round embedded | BF27: fill | BG27: fill | BH27: fill | BI27: fill | BJ27: fill | BK27: fill | BL27: fill | BM27: fill | BN27: fill | BO27: fill | BP27: fill | BQ27: fill | BR27: fill | BS27: fill | BT27: fill | BU27: fill | BV27: fill | BW27: fill
D28: Ceiling Mounted Cassette | E28: {=IF(E92<>"", E92, IF(SUMPRODUCT(--(PLP_BUSINESS!$C$3:$C$2925=E$9)*(--(LOWER(PLP_BUSINESS!$G$3:$G$2925)=$AU28:$BY28)))>0,"O","X"))} -> O | F28: {=IF(F92<>"", F92, IF(SUMPRODUCT(--(PLP_BUSINESS!$C$3:$C$2925=F$9)*(--(LOWER(PLP_BUSINESS!$G$3:$G$2925)=$AU28:$BY28)))>0,"O","X"))} -> O | G28: {=IF(G92<>"", G92, IF(SUMPRODUCT(--(PLP_BUSINESS!$C$3:$C$2925=G$9)*(--(LOWER(PLP_BUSINESS!$G$3:$G$2925)=$AU28:$BY28)))>0,"O","X"))} -> O | H28: {=IF(H92<>"", H92, IF(SUMPRODUCT(--(PLP_BUSINESS!$C$3:$C$2925=H$9)*(--(LOWER(PLP_BUSINESS!$G$3:$G$2925)=$AU28:$BY28)))>0,"O","X"))} -> O | I28: {=IF(I92<>"", I92, IF(SUMPRODUCT(--(PLP_BUSINESS!$C$3:$C$2925=I$9)*(--(LOWER(PLP_BUSINESS!$G$3:$G$2925)=$AU28:$BY28)))>0,"O","X"))} -> O | J28: {=IF(J92<>"", J92, IF(SUMPRODUCT(--(PLP_BUSINESS!$C$3:$C$2925=J$9)*(--(LOWER(PLP_BUSINESS!$G$3:$G$2925)=$AU28:$BY28)))>0,"O","X"))} -> O | K28: {=IF(K92<>"", K92, IF(SUMPRODUCT(--(PLP_BUSINESS!$C$3:$C$2925=K$9)*(--(LOWER(PLP_BUSINESS!$G$3:$G$2925)=$AU28:$BY28)))>0,"O","X"))} -> O | L28: {=IF(L92<>"", L92, IF(SUMPRODUCT(--(PLP_BUSINESS!$C$3:$C$2925=L$9)*(--(LOWER(PLP_BUSINESS!$G$3:$G$2925)=$AU28:$BY28)))>0,"O","X"))} -> O | ... AS28: {=IF(AS92<>"", AS92, IF(SUMPRODUCT(--(PLP_BUSINESS!$C$3:$C$2925=AS$9)*(--(LOWER(PLP_BUSINESS!$G$3:$G$2925)=$AU28:$BY28)))>0,"O","X"))} -> O | AU28: ceiling mounted cassette | AV28: ceiling mounted | AW28: ceiling-mounted cassette | AX28: one way ceiling cassette | AY28: ceiling cassette | AZ28: ceiling cassette models 4-way cassette | BA28: single/double outlet ceiling unit | BB28: cassette | BC28: cassettes | BD28: cassette indoor unit | BE28: cartridge | BF28: 4-way cassette | BG28: 4 way cassette | BH28: single split cassette | BI28: four-way cassette | BJ28: ceiling gable | BK28: mono-split: ceiling light | BL28: ceiling cassette air conditioner | BM28: fill | BN28: fill | BO28: fill | BP28: fill | BQ28: fill | BR28: fill | BS28: fill | BT28: fill | BU28: fill | BV28: fill | BW28: fill
